Workbook
Name NativeTimeline_Dashboard_Order_Date: #N/A
Name Slicer_Category: #REF!
Name Slicer_Category1: #N/A
Name Slicer_MentorName: #REF!
Name Slicer_Platform: #REF!
Name Slicer_Region: #N/A

Sheet Sales_data
A1: Order_ID | B1: Customer_ID | C1: Product_ID | D1: Order_Date | E1: Delivery_Date | F1: Customer_Name | G1: Gender | H1: DOB | I1: City | J1: Region | K1: Category | L1: Product_Name | M1: Quantity | N1: Unit_Price | O1: Discount_% | P1: Sales | Q1: Rating | R1: Payment_Mode | S1: Salesperson | T1: Email | U1: Phone | V1: Order_Status
A2: ORD10001 | B2: C008 | C2: P202 | D2: 18/09/2025 | E2: 22/09/2025 | F2: Kavya Nair | G2: Female | H2: 01/08/1976 | I2: Hyderabad | J2: South | K2: Home Appliances | L2: Iron | M2: 4 | N2: 2200 | O2: 10 | P2: 7920 | Q2: 4 | R2: Cash | S2: Ritika | T2: KAvya.nair@company.com | U2: 9431429797 | V2: Completed
A3: ORD10002 | B3: C008 | C3: P104 | D3: 27/04/2025 | E3: 04/05/2025 | F3: Kavya Nair | G3: Female | H3: 16/10/2000 | I3: Delhi | J3: North | K3: Electronics | L3: Monitor | M3: 17 | N3: 12000 | O3: 10 | P3: 183600 | Q3: 1 | R3: NetBanking | S3: Rahul | T3: kavya.nair@company.com | U3: 9129865339 | V3: Completed
A4: ORD10003 | B4: C010 | C4: P101 | D4: 03/09/2025 | E4: 14/09/2025 | F4: pooja shah | G4: Female | H4: 16/09/1994 | I4: Bengaluru | J4: South | K4: Electronics | L4: Laptop | M4: 5 | N4: 55000 | O4: 5 | P4: 261250 | Q4: 3 | R4: NetBanking | S4: Aisha | T4: pooja.shah@company.com | U4: 9380975626 | V4: Pending
A5: ORD10002 | B5: C008 | C5: P202 | D5: 21/03/2026 | E5: 02/04/2026 | F5: Kavya Nair | G5: Female | H5: 07/03/2004 | I5: Bengaluru | J5: South | K5: Home Appliances | L5: Iron | M5: 5 | N5: 2200 | O5: 5 | P5: 10450 | Q5: 5 | R5: NetBanking | S5: Aisha | T5: kavya.nair@company.com | U5: 9600261125 | V5: Cancelled
A6: ORD10005 | B6: C009 | C6: P103 | D6: 27/09/2025 | E6: 07/10/2025 | F6: Mohit Verma | G6: Male | H6: 13/04/1976 | I6: Delhi | J6: North | K6: Electronics | L6: Keyboard | M6: 8 | N6: 1200 | O6: 5 | P6: 9120 | Q6: 2 | R6: Card | S6: Aisha | T6: mohit.verma@company.com | U6: 9724635978 | V6: Pending
A7: ORD10006 | B7: C007 | C7: P202 | D7: 04/01/2026 | E7: 12/01/2026 | F7: arjun Rao | G7: Male | H7: 07/02/1988 | I7: Hyderabad | J7: South | K7: Home Appliances | L7: Iron | M7: 4 | N7: 2200 | O7: 0 | P7: 8800 | Q7: 1 | R7: UPI | S7: Ritika | T7: arjun.rao@company.com | U7: 9780584905 | V7: Completed
A8: ORD10007 | B8: C008 | C8: P201 | D8: 31/02/2025 | E8: 25/02/2026 | F8: Kavya Nair | G8: Female | H8: 20/03/2003 | I8: Hyderabad | J8: South | K8: Home Appliances | L8: Mixer | M8: 2 | N8: 3500 | O8: 5 | P8: 6650 | Q8: 1 | R8: UPI | S8: Ritika | T8: kavya.nair@company.com | U8: 9958252176 | V8: Completed
A9: ORD10008 | B9: C002 | C9: P104 | D9: 13/04/2025 | E9: 19/04/2025 | F9: Priya Patel | G9: Female | H9: 07/03/1995 | I9: Mumbai | J9: West | K9: Electronics | L9: Monitor | M9: 14 | N9: 12000 | O9: 15 | P9: 142800 | Q9: 4 | R9: NetBanking | S9: Ritika | T9: priYa.patel@company.com | U9: 9705521654 | V9: Completed
A10: ORD10009 | B10: C008 | C10: P104 | D10: 31/01/2026 | E10: 02/02/2026 | F10: kavya Nair | G10: Female | H10: 06/04/1997 | I10: Pune | J10: West | K10: Electronics | L10: Monitor | M10: 4 | N10: 12000 | O10: 15 | P10: 40800 | Q10: 4 | R10: UPI | S10: Neha | T10: kavya.nair@company.com | U10: 9588041011 | V10: Completed
A11: ORD10010 | B11: C002 | C11: P301 | D11: 25/03/2025 | E11: 27/03/2025 | F11: Priya Patel | G11: Female | H11: 07/01/1990 | I11: Mumbai | J11: West | K11: Stationery | L11: Notebook | M11: 6 | N11: 60 | O11: 0 | P11: 360 | Q11: 4 | R11: Card | S11: Neha | T11: PRiya.patel@company.com | U11: 9340540608 | V11: Completed
A12: ORD10011 | B12: C003 | C12: P202 | D12: 19/09/2025 | E12: 23/09/2025 | F12: Rohit Singh | G12: Male | H12: 10/05/1982 | I12: Delhi | J12: North | K12: Home Appliances | L12: Iron | M12: -3 | N12: 2200 | O12: 0 | P12: 35200 | Q12: 2 | R12: Card | S12: Rahul | T12: rohit.singh@company.com | U12: 9521710321 | V12: Pending
A13: ORD10012 | B13: C008 | C13: P201 | D13: 08/03/2025 | E13: 15/03/2025 | F13: Kavya Nair | G13: Female | H13: 23/01/1982 | I13: Ahmedabad | J13: West | K13: Home Appliances | L13: Mixer | M13: 10 | N13: 3500 | O13: 5 | P13: 33250 | Q13: 5 | R13: Card | S13: Aisha | T13: kavya.nair@company.com | U13: 9123535241 | V13: Cancelled
... A39: ORD10038 | B39: C006 | C39: P201 | D39: 08/03/2026 | E39: 20/03/2026 | F39: Sneha Joshi | G39: Female | H39: 21/06/1980 | I39: Delhi | J39: North | K39: Home Appliances | L39: Mixer | M39: 20 | N39: 3500 | O39: 10 | P39: 63000 | Q39: 3 | R39: Card | S39: Rahul | T39: sneha.joshi@company.com | U39: 9283578533 | V39: Cancelled
A40: ORD10039 | B40: C008 | C40: P302 | D40: 13/02/2025 | E40: 19/02/2025 | F40: Kavya Nair | G40: Female | H40: 17/06/1979 | I40: Pune | J40: West | K40: Stationery | L40: Pen | M40: 5 | N40: 1200 | O40: 0 | P40: 100 | Q40: 1 | R40: Cash | S40: Rahul | T40: kavya.nair@company.com | U40: 9963005771 | V40: Cancelled
A41: ORD10040 | B41: C010 | C41: P203 | D41: 05/10/2025 | E41: 15/10/2025 | F41: Pooja Shah | G41: Female | H41: 18/06/1992 | I41: Mumbai | J41: West | K41: Home Appliances | L41: Microwave | M41: 20 | N41: 8500 | O41: 0 | P41: 170000 | Q41: 1 | R41: UPI | S41: Neha | T41: pooja.shah@company.com | U41: 9484632635 | V41: Cancelled
A42: ORD10041 | B42: C007 | C42: P301 | D42: 10/02/2026 | E42: 12/02/2026 | F42: Arjun Rao | G42: Male | H42: 06/06/1994 | I42: Bengaluru | J42: South | K42: Stationery | L42: Notebook | M42: 8 | N42: 60 | O42: 15 | P42: 408 | Q42: 5 | R42: UPI | S42: Rahul | T42: arjun.rao@company.com | U42: 9276319484 | V42: Pending
A43: ORD10042 | B43: C010 | C43: P201 | D43: 04/06/2025 | E43: 16/06/2025 | F43: Pooja Shah | G43: Female | H43: 22/09/1988 | I43: Pune | J43: West | K43: Home Appliances | L43: Mixer | M43: 8 | N43: 3500 | O43: 5 | P43: 26600 | Q43: 1 | R43: Card | S43: Neha | T43: pooja.shah@company.com | U43: 9619034852 | V43: Pending
A44: ORD10043 | B44: C009 | C44: P203 | D44: 08/02/2026 | E44: 14/02/2026 | F44: Mohit Verma | G44: Male | H44: 14/07/2001 | I44: Jaipur | J44: North | K44: Home Appliances | L44: Microwave | M44: 1 | N44: 8500 | O44: 0 | P44: 8500 | Q44: 2 | R44: Card | S44: Neha | T44: mohit.verma@company.com | U44: 9636416962 | V44: Pending
A45: ORD10044 | B45: C001 | C45: P303 | D45: 30/03/2025 | E45: 31/03/2025 | F45: amit Sharma | G45: Male | H45: 09/08/1991 | I45: Pune | J45: West | K45: Stationery | L45: Marker | M45: 8 | N45: 45 | O45: 15 | P45: 306 | Q45: 2 | R45: Card | S45: Aisha | T45: amit.sharma@company.com | U45: 9357133880 | V45: Completed
A46: ORD10045 | B46: C006 | C46: P202 | D46: 25/04/2025 | E46: 28/04/2025 | F46: Sneha Joshi | G46: Female | H46: 21/10/1988 | I46: Pune | J46: West | K46: Home Appliances | L46: Iron | M46: 16 | N46: 2200 | O46: 5 | P46: 33440 | Q46: 5 | R46: Card | S46: Aisha | T46: sneha.joshi@company.com | U46: 9575210324 | V46: Cancelled
A47: ORD10046 | B47: C009 | C47: P201 | D47: 13/10/2025 | E47: 23/10/2025 | F47: Mohit Verma | G47: Male | H47: 19/11/2002 | I47: Bengaluru | J47: South | K47: Home Appliances | L47: Mixer | M47: 19 | N47: 3500 | O47: 20 | P47: 53200 | Q47: 3 | R47: Cash | S47: Karan | T47: mohit.verma@company.com | U47: 9276080204 | V47: Cancelled
A48: ORD10047 | B48: C006 | C48: P102 | D48: 11/10/2025 | E48: 14/10/2025 | F48: Sneha Joshi | G48: Female | H48: 06/07/2000 | I48: Pune | J48: West | K48: Electronics | L48: Mouse | M48: 15 | N48: 700 | O48: 15 | P48: 8925 | Q48: 4 | R48: UPI | S48: Neha | T48: sneha.joshicompany.com | U48: 9856624471 | V48: Completed
A49: ORD10048 | B49: C006 | C49: P102 | D49: 27/11/2025 | E49: 03/12/2025 | F49: Sneha Joshi | G49: Female | H49: 26/11/1998 | I49: Jaipur | J49: North | K49: Electronics | L49: Mouse | M49: 19 | N49: 700 | O49: 20 | P49: 10640 | Q49: 1 | R49: Cash | S49: Neha | T49: sneha.joshi@company.com | U49: 9238141322 | V49: Completed
A50: ORD10049 | B50: C009 | C50: P104 | D50: 19/04/2026 | F50: Mohit Verma | G50: Male | H50: 03/06/1996 | I50: Delhi | J50: North | K50: Electronics | L50: Monitor | M50: 19 | N50: 12000 | O50: 0 | P50: 228000 | Q50: 1 | R50: NetBanking | S50: Aisha | T50: mohit.verma@company.com | U50: 9890380030 | V50: Completed
A51: ORD10050 | B51: C004 | C51: P103 | D51: 19/04/2026 | E51: 21/04/2026 | F51: Anita Gupta | G51: Female | H51: 15/03/1987 | I51: Pune | J51: West | K51: Electronics | L51: Keyboard | M51: 6 | N51: 1200 | O51: 5 | P51: 6840 | Q51: 2 | R51: Cash | S51: Ritika | T51: anita.gupta@company.com | U51: 9495893170 | V51: Pending
A52: ORD10051 | B52: C010 | C52: P202 | D52: 28/03/2025 | E52: 07/04/2025 | F52: POoja Shah | G52: Female | H52: 20/02/1979 | I52: Bengaluru | J52: South | K52: Home Appliances | L52: Iron | M52: 7 | N52: 2200 | O52: 15 | P52: 13090 | Q52: 1 | R52: UPI | S52: Aisha | T52: pooja.shah@company.com | U52: 9485166307 | V52: Completed
A53: ORD10052 | B53: C002 | C53: P301 | D53: 25/08/2025 | E53: 28/08/2025 | F53: Priya Patel | G53: Female | H53: 09/08/2000 | I53: Jaipur | J53: North | K53: Stationery | L53: Notebook | M53: 8 | N53: 60 | O53: 10 | P53: 432 | Q53: 5 | R53: Card | S53: Aisha | T53: priya.patel@company.com | U53: 9924709648 | V53: Cancelled
A54: ORD10053 | B54: C005 | C54: P101 | D54: 19/08/2025 | E54: 23/08/2025 | F54: Vikas Mehta | G54: Male | H54: 17/01/1976 | I54: Kolkata | J54: East | K54: Electronics | L54: Laptop | M54: 12 | N54: 55000 | O54: 5 | P54: 627000 | Q54: 2 | R54: UPI | S54: Rahul | T54: vikas.mehta@company.com | U54: 9350554626 | V54: Pending
A55: ORD10054 | B55: C008 | C55: P102 | D55: 27/07/2025 | E55: 05/08/2025 | F55: Kavya Nair | G55: Female | H55: 04/04/1975 | I55: Jaipur | J55: North | K55: Electronics | L55: Mouse | M55: 3 | N55: 700 | O55: 0 | P55: 2100 | Q55: 3 | R55: Card | S55: Karan | T55: kavya.nair@company.com | U55: 9743295580 | V55: Cancelled
A56: ORD10055 | B56: C003 | C56: P301 | D56: 21/02/2025 | E56: 26/02/2025 | F56: RoHit Singh | G56: Male | H56: 11/12/1976 | I56: Ahmedabad | J56: West | K56: Stationery | L56: Notebook | M56: 19 | N56: 60 | O56: 15 | P56: 969 | Q56: 4 | R56: Card | S56: Rahul | T56: rohit.singh@company.com | U56: 9822926495 | V56: Cancelled
A57: ORD10056 | B57: C001 | C57: P301 | D57: 10/08/2025 | E57: 11/08/2025 | F57: Amit Sharma | G57: Male | H57: 03/12/1979 | I57: Jaipur | J57: North | K57: Stationery | L57: Notebook | M57: 9 | N57: 60 | O57: 20 | P57: 432 | Q57: 1 | R57: NetBanking | S57: Neha | T57: amit.sharma@company.com | U57: 9518298190 | V57: Pending
A58: ORD10057 | B58: C001 | C58: P102 | D58: 24/03/2026 | E58: 30/03/2026 | F58: Amit Sharma | G58: Male | H58: 27/12/1978 | I58: Bengaluru | J58: South | K58: Electronics | L58: Mouse | M58: 6 | N58: 700 | O58: 0 | P58: 4200 | Q58: 4 | R58: UPI | S58: Rahul | T58: amit.sharmcompany.com | U58: 9366223547 | V58: Cancelled
A59: ORD10058 | B59: C003 | C59: P303 | D59: 13/03/2026 | E59: 19/03/2026 | F59: Rohit Singh | G59: Male | H59: 15/04/1975 | I59: Delhi | J59: North | K59: Stationery | L59: Marker | M59: 18 | N59: 45 | O59: 5 | P59: 769.5 | Q59: 1 | R59: Card | S59: Aisha | T59: rohit.singh@company.com | U59: 9701988524 | V59: Pending
A60: ORD10059 | B60: C007 | C60: P302 | D60: 15/06/2025 | E60: 26/06/2025 | F60: Arjun Rao | G60: Male | H60: 19/12/1988 | I60: Jaipur | J60: North | K60: Stationery | L60: Pen | M60: 8 | N60: 20 | O60: 5 | P60: 152 | Q60: 1 | R60: Card | S60: Ritika | T60: arjun.rao@company.com | U60: 9836327649 | V60: completed
A61: ORD10060 | B61: C005 | C61: P102 | D61: 05/03/2025 | E61: 06/03/2025 | F61: Vikas Mehta | G61: Male | H61: 07/03/1979 | I61: Jaipur | J61: North | K61: Electronics | L61: Mouse | M61: 8 | N61: 700 | O61: 10 | P61: 5040 | Q61: 1 | R61: NetBanking | S61: Aisha | T61: Vikas.mehta@company.com | U61: 9261800516 | V61: Cancelled
A62: ORD10061 | B62: C008 | C62: P302 | D62: 09/04/2026 | E62: 19/04/2026 | F62: Kavya Nair | G62: Female | H62: 17/12/2003 | I62: Delhi | J62: North | K62: Stationery | L62: Pen | M62: 7 | N62: 20 | O62: 15 | P62: 119 | Q62: 5 | R62: Card | S62: Rahul | T62: kavya.nair@company.com | U62: 9950802015 | V62: Completed
... A74: ORD10073 | B74: C008 | C74: P103 | D74: 13/12/2025 | E74: 23/12/2025 | F74: Kavya Nair | G74: Female | H74: 22/09/1981 | I74: Jaipur | J74: North | K74: Electronics | L74: Keyboard | M74: 1 | N74: 1200 | O74: 5 | P74: 1140 | Q74: 3 | R74: UPI | S74: Aisha | T74: kavya.nair@company.com | U74: 9808988530 | V74: Cancelled
A75: ORD10074 | B75: C010 | C75: P202 | D75: 04/02/2026 | E75: 16/02/2026 | F75: Pooja Shah | G75: Female | H75: 20/06/1980 | J75: South | K75: Home Appliances | L75: Iron | M75: 1 | N75: 2200 | O75: 15 | P75: 1870 | Q75: 4 | R75: Card | S75: Aisha | T75: pooja.shah@company.com | U75: 9286410494 | V75: Completed
A76: ORD10075 | B76: C003 | C76: P103 | D76: 26/01/2026 | E76: 28/01/2026 | F76: Rohit Singh | G76: Male | H76: 02/11/1982 | I76: Pune | J76: West | K76: Electronics | L76: Keyboard | M76: 3 | N76: 1200 | O76: 10 | P76: 3240 | Q76: 5 | R76: Cash | S76: Rahul | T76: rohit.singh@company.com | U76: 9311555196 | V76: Completed
A77: ORD10076 | B77: C008 | C77: P201 | D77: 27/06/2025 | E77: 07/07/2025 | F77: Kavya Nair | G77: Female | H77: 10/01/1980 | I77: Bengaluru | J77: South | K77: Home Appliances | L77: Mixer | M77: 10 | N77: 3500 | O77: 20 | P77: 28000 | Q77: 5 | R77: Card | S77: Ritika | T77: kavya.nair@company.com | U77: 9101810266 | V77: Completed
A78: ORD10077 | B78: C007 | C78: P102 | D78: 17/03/2026 | E78: 19/03/2026 | F78: Arjun Rao | G78: Male | H78: 27/04/1981 | I78: Delhi | J78: North | K78: Electronics | L78: Mouse | M78: 18 | N78: 700 | O78: 5 | P78: 11970 | Q78: 3 | R78: Card | S78: Neha | T78: arjun.rao@company.com | U78: 9464556593 | V78: Cancelled
A79: ORD10078 | B79: C005 | C79: P102 | D79: 09/06/2025 | E79: 18/06/2025 | F79: Vikas Mehta | G79: Male | H79: 12/03/1985 | I79: Bengaluru | J79: South | K79: Electronics | L79: Mouse | M79: 12 | N79: 700 | O79: 15 | P79: 7140 | Q79: 2 | R79: UPI | S79: Rahul | T79: vikas.mehta@company.com | U79: 9338278358 | V79: Completed
A80: ORD10079 | B80: C009 | C80: P103 | D80: 15/11/2025 | E80: 16/11/2025 | F80: Mohit Verma | G80: Male | H80: 15/03/1999 | I80: Mumbai | J80: West | K80: Electronics | L80: Keyboard | M80: 8 | N80: 1200 | O80: 0 | P80: 9600 | Q80: 4 | R80: Card | S80: Rahul | T80: mohit.verma@company.com | U80: 9621410770 | V80: Pending
A81: ORD10080 | B81: C003 | C81: P301 | D81: 06/11/2025 | E81: 10/11/2025 | F81: Rohit Singh | G81: Male | H81: 07/07/1983 | I81: Pune | J81: West | K81: Stationery | L81: Notebook | M81: 2 | N81: 60 | O81: 0 | P81: 120 | Q81: 2 | R81: UPI | S81: Rahul | T81: rohit.singh@company.com | U81: 9981333189 | V81: Completed
A82: ORD10081 | B82: C001 | C82: P303 | D82: 01/01/2025 | E82: 07/01/2025 | F82: Amit Sharma | G82: Male | H82: 06/03/1989 | I82: Pune | J82: West | K82: Stationery | L82: Marker | M82: 10 | N82: 45 | O82: 15 | P82: 382.5 | Q82: 3 | R82: NetBanking | S82: Ritika | T82: amit.sharma@company.com | U82: 9723450355 | V82: Cancelled
A83: ORD10082 | B83: C005 | C83: P201 | D83: 25/04/2026 | E83: 03/05/2026 | F83: Vikas Mehta | G83: Male | H83: 20/06/1982 | I83: Kolkata | J83: East | K83: Home Appliances | L83: Mixer | M83: 12 | N83: 3500 | O83: 5 | P83: 39900 | Q83: 3 | R83: NetBanking | S83: Aisha | T83: vikas.mehta@company.com | U83: 9886243907 | V83: Pending
A84: ORD10083 | B84: C003 | C84: P301 | D84: 19/09/2025 | E84: 27/09/2025 | F84: Rohit Singh | G84: Male | H84: 23/06/2001 | I84: Mumbai | J84: West | K84: Stationery | L84: Notebook | M84: 2 | N84: 60 | O84: 15 | P84: 102 | Q84: 1 | R84: UPI | S84: Neha | T84: rohit.singh@company.com | U84: 9473931904 | V84: Completed
A85: ORD10084 | B85: C003 | C85: P103 | D85: 18/03/2025 | E85: 21/03/2025 | F85: Rohit Singh | G85: Male | H85: 19/07/1983 | I85: Hyderabad | J85: South | K85: Electronics | L85: Keyboard | M85: 18 | N85: 1200 | O85: 15 | P85: 18360 | Q85: 3 | R85: Card | S85: Neha | T85: rohit.singh@company.com | U85: 9287159610 | V85: Pending
A86: ORD10085 | B86: C008 | C86: P104 | D86: 30/10/2025 | E86: 31/10/2025 | F86: Kavya Nair | G86: Female | H86: 24/03/1993 | I86: Mumbai | J86: West | K86: Electronics | L86: Monitor | M86: 18 | N86: 12000 | O86: 15 | P86: 183600 | Q86: 2 | R86: Cash | S86: Rahul | T86: kavya.nair@company.com | U86: 9876513858 | V86: Completed
A87: ORD10086 | B87: C007 | C87: P302 | D87: 31/10/2025 | E87: 11/11/2025 | F87: Arjun Rao | G87: Male | H87: 10/05/1995 | I87: Ahmedabad | J87: West | K87: Stationery | L87: Pen | M87: 7 | N87: 20 | O87: 0 | P87: 140 | Q87: 2 | R87: Card | S87: Ritika | T87: arjun.rao@company.com | U87: 9237400853 | V87: Cancelled
... A119: ORD10118 | B119: C001 | C119: P303 | D119: 31/05/2025 | E119: 11/06/2025 | F119: Amit Sharma | G119: Male | H119: 07/09/1995 | I119: Pune | J119: West | K119: Stationery | L119: Marker | M119: 16 | N119: 45 | O119: 0 | P119: 720 | Q119: 1 | R119: NetBanking | S119: Aisha | T119: amit.sharma@company.com | U119: 9807154421 | V119: Completed
A120: ORD10119 | B120: C009 | C120: P103 | D120: 30/05/2025 | E120: 02/06/2025 | F120: Mohit Verma | G120: Male | H120: 08/03/1988 | I120: Ahmedabad | J120: West | K120: Electronics | L120: Keyboard | N120: 1200 | O120: 15 | P120: 7140 | Q120: 4 | R120: UPI | S120: Karan | T120: mohit.verma@company.com | U120: 9919834000 | V120: Pending
A121: ORD10120 | B121: C002 | C121: P104 | D121: 19/08/2025 | E121: 30/08/2025 | F121: Priya Patel | G121: Female | H121: 07/07/1989 | I121: Jaipur | J121: North | K121: Electronics | L121: Monitor | M121: 14 | N121: 12000 | O121: 15 | P121: 142800 | Q121: 2 | R121: NetBanking | S121: Aisha | T121: priya.patel@company.com | U121: 9739798818 | V121: Pending
A122: ORD10121 | B122: C003 | C122: P203 | D122: 14/12/2025 | E122: 16/12/2025 | F122: Rohit Singh | G122: Male | H122: 11/11/1993 | I122: Pune | J122: West | K122: Home Appliances | L122: Microwave | M122: 8 | N122: 8500 | O122: 20 | P122: 54400 | Q122: 3 | R122: Card | S122: Rahul | T122: rohit.singh@company.com | U122: 9208625306 | V122: Completed
A123: ORD10122 | B123: C007 | C123: P303 | D123: 31/01/2026 | E123: 10/02/2026 | F123: Arjun Rao | G123: Male | H123: 01/02/2000 | I123: Bengaluru | J123: South | K123: Stationery | L123: Marker | M123: 3 | N123: 45 | O123: 0 | P123: 135 | Q123: 4 | R123: UPI | S123: Aisha | T123: arjun.rao@company.com | U123: 9970178536 | V123: Cancelled
A124: ORD10123 | B124: C001 | C124: P102 | D124: 03/01/2026 | E124: 04/01/2026 | F124: Amit Sharma | G124: Male | H124: 22/06/1986 | I124: Jaipur | J124: North | K124: Electronics | L124: Mouse | M124: 13 | N124: 700 | O124: 5 | P124: 8645 | Q124: 3 | R124: Card | S124: Neha | T124: amit.sharma@company.com | U124: 9633745195 | V124: Pending
A125: ORD10124 | B125: C004 | C125: P103 | D125: 20/10/2025 | E125: 26/10/2025 | F125: Anita Gupta | G125: Female | H125: 16/02/1986 | I125: Mumbai | J125: West | K125: Electronics | L125: Keyboard | M125: 14 | N125: 1200 | O125: 20 | P125: 13440 | Q125: 5 | R125: NetBanking | S125: Aisha | T125: anita.gupta@company.com | U125: 9922102053 | V125: Completed
A126: ORD10125 | B126: C002 | C126: P303 | D126: 11/05/2025 | E126: 21/05/2025 | F126: Priya Patel | G126: Female | H126: 18/09/1991 | I126: Delhi | J126: North | K126: Stationery | L126: Marker | M126: 2 | N126: 45 | O126: 5 | P126: 85.5 | Q126: 3 | R126: UPI | S126: Ritika | T126: priya.patel@company.com | U126: 9135963930 | V126: Cancelled
A127: ORD10126 | B127: C004 | C127: P103 | D127: 02/01/2026 | E127: 06/01/2026 | F127: Anita Gupta | G127: Female | H127: 04/01/1981 | I127: Bengaluru | J127: South | K127: Electronics | L127: Keyboard | M127: 2 | N127: 1200 | O127: 20 | P127: 1920 | Q127: 3 | R127: Card | S127: Neha | T127: anita.gupta@company.com | U127: 9429405275 | V127: Completed
A128: ORD10127 | B128: C003 | C128: P101 | D128: 20/04/2026 | E128: 26/04/2026 | F128: Rohit Singh | G128: Male | H128: 12/10/2004 | I128: Bengaluru | J128: South | K128: Electronics | L128: Laptop | M128: 10 | N128: 55000 | O128: 5 | P128: 522500 | Q128: 5 | R128: UPI | S128: Aisha | T128: rohit.singh@company.com | U128: 9521757571 | V128: Pending
A129: ORD10128 | B129: C006 | C129: P201 | D129: 04/08/2025 | E129: 05/08/2025 | F129: Sneha Joshi | G129: Female | H129: 25/03/1984 | I129: Jaipur | J129: North | K129: Home Appliances | L129: Mixer | M129: 15 | N129: 3500 | O129: 10 | P129: 47250 | Q129: 3 | R129: NetBanking | S129: Neha | T129: sneha.joshi@company.com | U129: 9467375455 | V129: Completed
A130: ORD10129 | B130: C002 | C130: P202 | D130: 13/08/2025 | E130: 18/08/2025 | F130: Priya Patel | G130: Female | H130: 09/09/1982 | I130: Bengaluru | J130: South | K130: Home Appliances | L130: Iron | M130: 10 | N130: 2200 | O130: 15 | P130: 18700 | Q130: 4 | R130: Card | S130: Rahul | T130: priya.patel@company.com | U130: 9838809695 | V130: Pending
A131: ORD10130 | B131: C006 | C131: P201 | D131: 16/06/2025 | E131: 24/06/2025 | F131: Sneha Joshi | G131: Female | H131: 15/02/1993 | I131: Pune | J131: West | K131: Home Appliances | L131: Mixer | M131: 11 | N131: 3500 | O131: 5 | P131: 36575 | Q131: 5 | R131: Cash | S131: Ritika | T131: sneha.joshi@company.com | U131: 9296609782 | V131: Cancelled
A132: ORD10131 | B132: C004 | C132: P103 | D132: 27/04/2026 | E132: 30/04/2026 | F132: Anita Gupta | G132: Female | H132: 08/04/2003 | I132: Bengaluru | J132: South | K132: Electronics | L132: Keyboard | M132: 14 | N132: 1200 | O132: 0 | P132: 16800 | Q132: 5 | R132: Cash | S132: Rahul | T132: anita.gupta@company.com | U132: 9848259992 | V132: Cancelled
... A299: ORD10298 | B299: C003 | C299: P101 | D299: 13/01/2025 | E299: 16/01/2025 | F299: Rohit Singh | G299: Male | H299: 03/01/2004 | I299: Hyderabad | J299: South | K299: Electronics | L299: Laptop | M299: 11 | N299: 55000 | O299: 5 | P299: 574750 | Q299: 1 | R299: UPI | S299: Ritika | T299: rohit.singh@company.com | U299: 9482699727 | V299: Cancelled
A300: ORD10299 | B300: C007 | C300: P201 | D300: 05/10/2025 | E300: 17/10/2025 | F300: Arjun Rao | G300: Male | H300: 02/05/1992 | I300: Jaipur | J300: North | K300: Home Appliances | L300: Mixer | M300: 12 | N300: 3500 | O300: 0 | P300: 42000 | Q300: 2 | R300: NetBanking | T300: arjun.rao@company.com | U300: 9332473934 | V300: Pending
A301: ORD10300 | B301: C009 | C301: P303 | D301: 25/02/2026 | E301: 08/03/2026 | F301: Mohit Verma | G301: Male | H301: 26/01/2003 | I301: Hyderabad | J301: South | K301: Stationery | L301: Marker | M301: 15 | N301: 45 | O301: 10 | P301: 607.5 | Q301: 2 | R301: Cash | S301: Karan | T301: mohit.verma@company.com | U301: 9647657382 | V301: Pending
A302: ORD10301 | B302: C001 | C302: P303 | D302: 16/05/2025 | E302: 26/05/2025 | F302: Amit Sharma | G302: Male | H302: 20/05/1987 | I302: Bengaluru | J302: South | K302: Stationery | L302: Marker | M302: 13 | N302: 45 | O302: 0 | P302: 585 | Q302: 5 | R302: NetBanking | S302: Rahul | T302: amit.sharma@company.com | U302: 9736797776 | V302: Pending
A303: ORD10302 | B303: C003 | C303: P101 | D303: 02/01/2026 | E303: 05/01/2026 | F303: Rohit Singh | G303: Male | H303: 07/09/1975 | I303: Bengaluru | J303: South | K303: Electronics | L303: Laptop | M303: 8 | N303: 55000 | O303: 0 | P303: 440000 | Q303: 2 | R303: UPI | S303: Karan | T303: rohit.singh@company.com | U303: 9745773533 | V303: Cancelled
A304: ORD10303 | B304: C006 | C304: P101 | D304: 23/07/2025 | E304: 27/07/2025 | F304: Sneha Joshi | G304: Female | H304: 10/08/1980 | I304: Delhi | J304: North | K304: Electronics | L304: Laptop | M304: 4 | N304: 55000 | O304: 20 | P304: 176000 | Q304: 5 | R304: Cash | S304: Rahul | T304: sneha.joshi@company.com | U304: 9246715757 | V304: Pending
A305: ORD10304 | B305: C008 | C305: P201 | D305: 23/04/2026 | E305: 26/04/2026 | F305: Kavya Nair | G305: Female | H305: 07/04/1989 | I305: Ahmedabad | J305: West | K305: Home Appliances | L305: Mixer | M305: 19 | N305: 3500 | O305: 5 | P305: 63175 | Q305: 1 | R305: Card | S305: Neha | T305: kavya.nair@company.com | U305: 9904065774 | V305: Completed
A306: ORD10305 | B306: C005 | C306: P103 | D306: 02/03/2025 | E306: 06/03/2025 | F306: Vikas Mehta | G306: Male | H306: 20/08/1998 | I306: Jaipur | J306: North | K306: Electronics | L306: Keyboard | M306: 17 | N306: 1200 | O306: 15 | P306: 17340 | Q306: 2 | R306: NetBanking | S306: Rahul | T306: vikas.mehta@company.com | U306: 9652985385 | V306: Completed
A307: ORD10306 | B307: C008 | C307: P202 | D307: 09/02/2026 | E307: 17/02/2026 | F307: Kavya Nair | G307: Female | H307: 03/04/2001 | I307: Hyderabad | J307: South | K307: Home Appliances | L307: Iron | M307: 8 | N307: 2200 | O307: 5 | P307: 16720 | Q307: 3 | R307: Card | S307: Neha | T307: kavya.nair@company.com | U307: 9427001508 | V307: Pending
A308: ORD10307 | B308: C006 | C308: P102 | D308: 16/02/2025 | E308: 26/02/2025 | F308: Sneha Joshi | G308: Female | H308: 05/03/1992 | I308: Mumbai | J308: West | K308: Electronics | L308: Mouse | M308: 17 | N308: 700 | O308: 20 | P308: 9520 | Q308: 4 | R308: NetBanking | S308: Neha | T308: sneha.joshi@company.com | U308: 9666803655 | V308: Completed
A309: ORD10308 | B309: C006 | C309: P203 | D309: 28/08/2025 | E309: 08/09/2025 | F309: Sneha Joshi | G309: Female | H309: 28/12/1976 | I309: Pune | J309: West | K309: Home Appliances | L309: Microwave | M309: 6 | N309: 8500 | O309: 15 | P309: 43350 | Q309: 1 | R309: Cash | S309: Aisha | T309: sneha.joshi@company.com | U309: 9134878547 | V309: Completed
A310: ORD10309 | B310: C010 | C310: P201 | D310: 06/10/2025 | E310: 11/10/2025 | F310: Pooja Shah | G310: Female | H310: 04/09/1986 | I310: Hyderabad | J310: South | K310: Home Appliances | L310: Mixer | M310: 3 | N310: 3500 | O310: 10 | P310: 9450 | Q310: 1 | R310: NetBanking | S310: Rahul | T310: pooja.shah@company.com | U310: 9253593557 | V310: Completed
A311: ORD10310 | B311: C009 | C311: P104 | D311: 17/01/2025 | E311: 29/01/2025 | F311: Mohit Verma | G311: Male | H311: 14/08/1989 | I311: Ahmedabad | J311: West | K311: Electronics | L311: Monitor | M311: 2 | N311: 12000 | O311: 20 | P311: 19200 | Q311: 1 | R311: Card | S311: Aisha | T311: mohit.verma@company.com | U311: 9183094051 | V311: Completed
A312: ORD10311 | B312: C005 | C312: P302 | D312: 13/10/2025 | E312: 16/10/2025 | F312: Vikas Mehta | G312: Male | H312: 02/03/1991 | I312: Delhi | J312: North | K312: Stationery | L312: Pen | M312: 12 | N312: 20 | O312: 20 | P312: 192 | Q312: 2 | R312: Card | S312: Rahul | T312: vikas.mehta@company.com | U312: 9293147620 | V312: Completed
... A370: ORD10369 | B370: C010 | C370: P301 | D370: 01/04/2026 | E370: 05/04/2026 | F370: Pooja Shah | G370: Female | H370: 04/01/1987 | I370: Hyderabad | J370: South | K370: Stationery | L370: Notebook | M370: 19 | N370: 60 | O370: 15 | P370: 969 | Q370: 4 | R370: NetBanking | S370: Neha | T370: pooja.shah@company.com | U370: 9435947486 | V370: Cancelled
A371: ORD10370 | B371: C001 | C371: P101 | E371: 02/02/2025 | F371: Amit Sharma | G371: Male | H371: 14/05/1992 | I371: Delhi | J371: North | K371: Electronics | L371: Laptop | M371: 15 | N371: 55000 | O371: 0 | P371: 825000 | Q371: 5 | R371: Card | S371: Neha | T371: amit.sharma@company.com | U371: 9411668831 | V371: Cancelled
A372: ORD10371 | B372: C009 | C372: P303 | D372: 06/10/2025 | E372: 08/10/2025 | F372: Mohit Verma | G372: Male | H372: 03/05/1989 | I372: Bengaluru | J372: South | K372: Stationery | L372: Marker | M372: 11 | N372: 45 | O372: 5 | P372: 470.25 | Q372: 5 | R372: NetBanking | S372: Karan | T372: mohit.verma@company.com | U372: 9523682403 | V372: Completed
A373: ORD10372 | B373: C006 | C373: P302 | D373: 12/06/2025 | E373: 17/06/2025 | F373: Sneha Joshi | G373: Female | H373: 19/12/1990 | I373: Jaipur | J373: North | K373: Stationery | L373: Pen | M373: 9 | N373: 20 | O373: 10 | P373: 162 | Q373: 1 | R373: Card | S373: Rahul | T373: sneha.joshi@company.com | U373: 9652936744 | V373: Cancelled
A374: ORD10373 | B374: C004 | C374: P303 | D374: 18/11/2025 | E374: 20/11/2025 | F374: Anita Gupta | G374: Female | H374: 09/07/1995 | I374: Bengaluru | J374: South | K374: Stationery | L374: Marker | M374: 5 | N374: 45 | O374: 5 | P374: 213.75 | Q374: 3 | R374: Card | S374: Neha | T374: anita.gupta@company.com | U374: 9726464733 | V374: Pending
A375: ORD10374 | B375: C007 | C375: P102 | D375: 01/11/2025 | E375: 02/11/2025 | F375: Arjun Rao | G375: Male | H375: 23/12/1998 | I375: Hyderabad | J375: South | K375: Electronics | L375: Mouse | M375: 5 | N375: 700 | O375: 10 | P375: 3150 | Q375: 2 | R375: UPI | S375: Rahul | T375: arjun.rao@company.com | U375: 9273520544 | V375: Completed
A376: ORD10375 | B376: C005 | C376: P102 | D376: 24/01/2025 | E376: 31/01/2025 | F376: Vikas Mehta | G376: Male | H376: 23/12/1979 | I376: Kolkata | J376: East | K376: Electronics | L376: Mouse | M376: 1 | N376: 700 | O376: 0 | P376: 700 | Q376: 1 | R376: UPI | S376: Karan | T376: vikas.mehta@company.com | U376: 9374259988 | V376: Completed
A377: ORD10376 | B377: C008 | C377: P102 | D377: 13/02/2026 | E377: 21/02/2026 | F377: Kavya Nair | G377: Female | H377: 15/12/1975 | I377: Mumbai | J377: West | K377: Electronics | L377: Mouse | M377: 13 | N377: 700 | O377: 20 | P377: 7280 | Q377: 2 | R377: Card | S377: Ritika | T377: kavya.nair@company.com | U377: 9538129419 | V377: Completed
A378: ORD10377 | B378: C009 | C378: P104 | D378: 08/02/2025 | E378: 19/02/2025 | F378: Mohit Verma | G378: Male | H378: 17/05/1993 | I378: Pune | J378: West | K378: Electronics | L378: Monitor | M378: 20 | N378: 12000 | O378: 0 | P378: 240000 | Q378: 2 | R378: Card | S378: Neha | T378: mohit.verma@company.com | U378: 9382815686 | V378: Completed
A379: ORD10378 | B379: C007 | C379: P103 | D379: 28/12/2025 | E379: 06/01/2026 | F379: Arjun Rao | G379: Male | H379: 17/09/1976 | I379: Kolkata | J379: East | K379: Electronics | L379: Keyboard | M379: 9 | N379: 1200 | O379: 15 | P379: 9180 | Q379: 1 | R379: UPI | S379: Ritika | T379: arjun.rao@company.com | U379: 9450746157 | V379: Pending
A380: ORD10379 | B380: C007 | C380: P302 | D380: 01/10/2025 | E380: 03/10/2025 | F380: Arjun Rao | G380: Male | H380: 22/12/1996 | I380: Jaipur | J380: North | K380: Stationery | L380: Pen | M380: 3 | N380: 20 | O380: 15 | P380: 51 | Q380: 3 | R380: Cash | S380: Neha | T380: arjun.rao@company.com | U380: 9349012570 | V380: Pending
A381: ORD10380 | B381: C006 | C381: P101 | D381: 18/12/2025 | E381: 19/12/2025 | F381: Sneha Joshi | G381: Female | H381: 25/12/1995 | I381: Delhi | J381: North | K381: Electronics | L381: Laptop | M381: 8 | N381: 55000 | O381: 20 | P381: 352000 | Q381: 5 | R381: Card | S381: Karan | T381: sneha.joshi@company.com | U381: 9442163790 | V381: Pending
A382: ORD10381 | B382: C006 | C382: P301 | D382: 29/09/2025 | E382: 07/10/2025 | F382: Sneha Joshi | G382: Female | H382: 23/06/1985 | I382: Delhi | J382: North | K382: Stationery | L382: Notebook | M382: 17 | N382: 60 | O382: 20 | P382: 816 | Q382: 1 | R382: UPI | S382: Ritika | T382: sneha.joshi@company.com | U382: 9953329223 | V382: Pending
A383: ORD10382 | B383: C003 | C383: P302 | D383: 14/05/2025 | E383: 22/05/2025 | F383: Rohit Singh | G383: Male | H383: 10/02/1984 | I383: Bengaluru | J383: South | K383: Stationery | L383: Pen | M383: 4 | N383: 20 | O383: 15 | P383: 68 | Q383: 3 | R383: NetBanking | S383: Aisha | T383: rohit.singh@company.com | U383: 9202321359 | V383: Pending
... A399: ORD10398 | B399: C007 | C399: P104 | D399: 31/01/2025 | E399: 04/02/2025 | F399: Arjun Rao | G399: Male | H399: 10/12/1978 | I399: Kolkata | J399: East | K399: Electronics | L399: Monitor | M399: 19 | N399: 12000 | O399: 0 | P399: 228000 | Q399: 4 | R399: UPI | S399: Aisha | T399: arjun.rao@company.com | U399: 9136906750 | V399: Pending
A400: ORD10399 | B400: C001 | C400: P102 | E400: 03/11/2025 | F400: Amit Sharma | G400: Male | H400: 01/09/1979 | I400: Bengaluru | J400: South | K400: Electronics | L400: Mouse | M400: 12 | N400: 700 | O400: 15 | P400: 7140 | Q400: 3 | R400: Card | S400: Ritika | T400: amit.sharma@company.com | U400: 9485286324 | V400: Completed
A401: ORD10400 | B401: C008 | C401: P103 | D401: 13/05/2025 | E401: 21/05/2025 | F401: Kavya Nair | G401: Female | H401: 08/04/2001 | I401: Delhi | J401: North | K401: Electronics | L401: Keyboard | M401: 16 | N401: 1200 | O401: 20 | P401: 15360 | Q401: 1 | R401: Cash | S401: Rahul | T401: kavya.nair@company.com | U401: 9414633966 | V401: Pending
A402: ORD10401 | B402: C009 | C402: P203 | D402: 27/12/2025 | E402: 04/01/2026 | F402: Mohit Verma | G402: Male | H402: 01/01/1983 | I402: Hyderabad | J402: South | K402: Home Appliances | L402: Microwave | M402: 10 | N402: 8500 | O402: 5 | P402: 80750 | Q402: 5 | R402: NetBanking | S402: Ritika | T402: mohit.verma@company.com | U402: 9833735234 | V402: Completed
A403: ORD10402 | B403: C008 | C403: P302 | D403: 11/02/2025 | E403: 21/02/2025 | F403: Kavya Nair | G403: Female | H403: 09/08/1989 | I403: Ahmedabad | J403: West | K403: Stationery | L403: Pen | M403: 18 | N403: 20 | O403: 20 | P403: 288 | Q403: 1 | R403: UPI | S403: Ritika | T403: kavya.nair@company.com | U403: 9523689108 | V403: Pending
A404: ORD10403 | B404: C009 | C404: P203 | D404: 13/03/2026 | E404: 19/03/2026 | F404: Mohit Verma | G404: Male | H404: 22/10/1993 | I404: Mumbai | J404: West | K404: Home Appliances | L404: Microwave | M404: 9 | N404: 8500 | O404: 0 | P404: 76500 | Q404: 2 | R404: Card | S404: Ritika | T404: mohit.verma@company.com | U404: 9812909831 | V404: Pending
A405: ORD10404 | B405: C008 | C405: P203 | D405: 01/10/2025 | E405: 12/10/2025 | F405: Kavya Nair | G405: Female | H405: 05/05/2000 | I405: Mumbai | J405: West | K405: Home Appliances | L405: Microwave | M405: 8 | N405: 8500 | O405: 10 | P405: 61200 | Q405: 4 | R405: Cash | S405: Neha | T405: kavya.nair@company.com | U405: 9106290987 | V405: Cancelled
...

Sheet Product_master
A1: Product_ID | B1: Product_Name | C1: Category | D1: Supplier | E1: Cost_Price | F1: Warranty_Months
A2: P101 | B2: Laptop | C2: Electronics | D2: TechHub | E2: 41250 | F2: 12
A3: P102 | B3: Mouse | C3: Electronics | D3: TechHub | E3: 525 | F3: 24
A4: P103 | B4: Keyboard | C4: Electronics | D4: TechHub | E4: 900 | F4: 6
A5: P104 | B5: Monitor | C5: Electronics | D5: Global Trade | E5: 9000 | F5: 24
A6: P201 | B6: Mixer | C6: Home Appliances | D6: Global Trade | E6: 2625 | F6: 6
A7: P202 | B7: Iron | C7: Home Appliances | D7: Global Trade | E7: 1650 | F7: 24
A8: P203 | B8: Microwave | C8: Home Appliances | D8: TechHub | E8: 6375 | F8: 24
A9: P301 | B9: Notebook | C9: Stationery | D9: ABC Corp | E9: 45 | F9: 12
A10: P302 | B10: Pen | C10: Stationery | D10: Prime Supplies | E10: 15 | F10: 12
A11: P303 | B11: Marker | C11: Stationery | D11: TechHub | E11: 33.75 | F11: 12

Sheet Customer_master
A1: Customer_ID | B1: Customer_Name | C1: Membership | D1: State
A2: C001 | B2: Amit Sharma | C2: Silver | D2: RJ
A3: C002 | B3: Priya Patel | C3: Platinum | D3: WB
A4: C003 | B4: Rohit Singh | C4: Gold | D4: DL
A5: C004 | B5: Anita Gupta | C5: Gold | D5: WB
A6: C005 | B6: Vikas Mehta | C6: Gold | D6: DL
A7: C006 | B7: Sneha Joshi | C7: Gold | D7: WB
A8: C007 | B8: Arjun Rao | C8: Silver | D8: RJ
A9: C008 | B9: Kavya Nair | C9: Silver | D9: WB
A10: C009 | B10: Mohit Verma | C10: Platinum | D10: KA
A11: C010 | B11: Pooja Shah | C11: Silver | D11: WB

Sheet Q1
A1: Order_ID | B1: Customer_ID | C1: Product_ID | D1: Order_Date | E1: Delivery_Date | F1: Customer_Name | G1: Gender | H1: DOB | I1: City | J1: Region | K1: Category | L1: Product_Name | M1: Quantity | N1: Unit_Price | O1: Discount_% | P1: Sales | Q1: Rating | R1: Payment_Mode | S1: Salesperson | T1: Email | U1: Phone | V1: Order_Status | W1: Customer Classification
A2: ORD10001 | B2: C008 | C2: P202 | D2: 18/09/2025 | E2: 22/09/2025 | F2: Kavya Nair | G2: Female | H2: 01/08/1976 | I2: Hyderabad | J2: South | K2: Home Appliances | L2: Iron | M2: 4 | N2: 2200 | O2: 10 | P2: 7920 | Q2: 4 | R2: Cash | S2: Ritika | T2: KAvya.nair@company.com | U2: 9431429797 | V2: Completed | W2: {=_xlfn.IFS(OR(V2="Cancelled", Q2<=2), "Blacklisted", AND(P2>=100000, Q2>=4, O2<=0.1, V2="Completed"), "Platinum", AND(P2>=50000, P2<=99999, Q2>=3, V2="Completed"), "Gold", AND(Q2<50000, V2="Completed"), "Silver")} -> Silver
A3: ORD10002 | B3: C008 | C3: P104 | D3: 27/04/2025 | E3: 04/05/2025 | F3: Kavya Nair | G3: Female | H3: 16/10/2000 | I3: Delhi | J3: North | K3: Electronics | L3: Monitor | M3: 17 | N3: 12000 | O3: 10 | P3: 183600 | Q3: 1 | R3: NetBanking | S3: Rahul | T3: kavya.nair@company.com | U3: 9129865339 | V3: Completed | W3: {=_xlfn.IFS(OR(V3="Cancelled", Q3<=2), "Blacklisted", AND(P3>=100000, Q3>=4, O3<=0.1, V3="Completed"), "Platinum", AND(P3>=50000, P3<=99999, Q3>=3, V3="Completed"), "Gold", AND(Q3<50000, V3="Completed"), "Silver")} -> Blacklisted
A4: ORD10003 | B4: C010 | C4: P101 | D4: 03/09/2025 | E4: 14/09/2025 | F4: Pooja Shah | G4: Female | H4: 16/09/1994 | I4: Bengaluru | J4: South | K4: Electronics | L4: Laptop | M4: 5 | N4: 55000 | O4: 5 | P4: 261250 | Q4: 3 | R4: NetBanking | S4: Aisha | T4: pooja.shah@company.com | U4: 9380975626 | V4: Pending | W4: {=_xlfn.IFS(OR(V4="Cancelled", Q4<=2), "Blacklisted", AND(P4>=100000, Q4>=4, O4<=0.1, V4="Completed"), "Platinum", AND(P4>=50000, P4<=99999, Q4>=3, V4="Completed"), "Gold", AND(Q4<50000, V4="Completed"), "Silver", V4="Pending", "Pending")} -> Pending
A5: ORD10002 | B5: C008 | C5: P202 | D5: 21/03/2026 | E5: 02/04/2026 | F5: Kavya Nair | G5: Female | H5: 07/03/2004 | I5: Bengaluru | J5: South | K5: Home Appliances | L5: Iron | M5: 5 | N5: 2200 | O5: 5 | P5: 10450 | Q5: 5 | R5: NetBanking | S5: Aisha | T5: kavya.nair@company.com | U5: 9600261125 | V5: Cancelled | W5: {=_xlfn.IFS(OR(V5="Cancelled", Q5<=2), "Blacklisted", AND(P5>=100000, Q5>=4, O5<=0.1, V5="Completed"), "Platinum", AND(P5>=50000, P5<=99999, Q5>=3, V5="Completed"), "Gold", AND(Q5<50000, V5="Completed"), "Silver", V5="Pending", "Pending")} -> Blacklisted
A6: ORD10005 | B6: C009 | C6: P103 | D6: 27/09/2025 | E6: 07/10/2025 | F6: Mohit Verma | G6: Male | H6: 13/04/1976 | I6: Delhi | J6: North | K6: Electronics | L6: Keyboard | M6: 8 | N6: 1200 | O6: 5 | P6: 9120 | Q6: 2 | R6: Card | S6: Aisha | T6: mohit.verma@company.com | U6: 9724635978 | V6: Pending | W6: {=_xlfn.IFS(OR(V6="Cancelled", Q6<=2), "Blacklisted", AND(P6>=100000, Q6>=4, O6<=0.1, V6="Completed"), "Platinum", AND(P6>=50000, P6<=99999, Q6>=3, V6="Completed"), "Gold", AND(Q6<50000, V6="Completed"), "Silver", V6="Pending", "Pending")} -> Blacklisted
A7: ORD10006 | B7: C007 | C7: P202 | D7: 04/01/2026 | E7: 12/01/2026 | F7: Arjun Rao | G7: Male | H7: 07/02/1988 | I7: Hyderabad | J7: South | K7: Home Appliances | L7: Iron | M7: 4 | N7: 2200 | O7: 0 | P7: 8800 | Q7: 1 | R7: UPI | S7: Ritika | T7: arjun.rao@company.com | U7: 9780584905 | V7: Completed | W7: {=_xlfn.IFS(OR(V7="Cancelled", Q7<=2), "Blacklisted", AND(P7>=100000, Q7>=4, O7<=0.1, V7="Completed"), "Platinum", AND(P7>=50000, P7<=99999, Q7>=3, V7="Completed"), "Gold", AND(Q7<50000, V7="Completed"), "Silver", V7="Pending", "Pending")} -> Blacklisted
A8: ORD10007 | B8: C008 | C8: P201 | D8: 31/02/2025 | E8: 25/02/2026 | F8: Kavya Nair | G8: Female | H8: 20/03/2003 | I8: Hyderabad | J8: South | K8: Home Appliances | L8: Mixer | M8: 2 | N8: 3500 | O8: 5 | P8: 6650 | Q8: 1 | R8: UPI | S8: Ritika | T8: kavya.nair@company.com | U8: 9958252176 | V8: Completed | W8: {=_xlfn.IFS(OR(V8="Cancelled", Q8<=2), "Blacklisted", AND(P8>=100000, Q8>=4, O8<=0.1, V8="Completed"), "Platinum", AND(P8>=50000, P8<=99999, Q8>=3, V8="Completed"), "Gold", AND(Q8<50000, V8="Completed"), "Silver", V8="Pending", "Pending")} -> Blacklisted
A9: ORD10008 | B9: C002 | C9: P104 | D9: 13/04/2025 | E9: 19/04/2025 | F9: Priya Patel | G9: Female | H9: 07/03/1995 | I9: Mumbai | J9: West | K9: Electronics | L9: Monitor | M9: 14 | N9: 12000 | O9: 15 | P9: 142800 | Q9: 4 | R9: NetBanking | S9: Ritika | T9: priYa.patel@company.com | U9: 9705521654 | V9: Completed | W9: {=_xlfn.IFS(OR(V9="Cancelled", Q9<=2), "Blacklisted", AND(P9>=100000, Q9>=4, O9<=0.1, V9="Completed"), "Platinum", AND(P9>=50000, P9<=99999, Q9>=3, V9="Completed"), "Gold", AND(Q9<50000, V9="Completed"), "Silver", V9="Pending", "Pending")} -> Silver
A10: ORD10009 | B10: C008 | C10: P104 | D10: 31/01/2026 | E10: 02/02/2026 | F10: Kavya Nair | G10: Female | H10: 06/04/1997 | I10: Pune | J10: West | K10: Electronics | L10: Monitor | M10: 4 | N10: 12000 | O10: 15 | P10: 40800 | Q10: 4 | R10: UPI | S10: Neha | T10: kavya.nair@company.com | U10: 9588041011 | V10: Completed | W10: {=_xlfn.IFS(OR(V10="Cancelled", Q10<=2), "Blacklisted", AND(P10>=100000, Q10>=4, O10<=0.1, V10="Completed"), "Platinum", AND(P10>=50000, P10<=99999, Q10>=3, V10="Completed"), "Gold", AND(Q10<50000, V10="Completed"), "Silver", V10="Pending", "Pending")} -> Silver
A11: ORD10010 | B11: C002 | C11: P301 | D11: 25/03/2025 | E11: 27/03/2025 | F11: Priya Patel | G11: Female | H11: 07/01/1990 | I11: Mumbai | J11: West | K11: Stationery | L11: Notebook | M11: 6 | N11: 60 | O11: 0 | P11: 360 | Q11: 4 | R11: Card | S11: Neha | T11: PRiya.patel@company.com | U11: 9340540608 | V11: Completed | W11: {=_xlfn.IFS(OR(V11="Cancelled", Q11<=2), "Blacklisted", AND(P11>=100000, Q11>=4, O11<=0.1, V11="Completed"), "Platinum", AND(P11>=50000, P11<=99999, Q11>=3, V11="Completed"), "Gold", AND(Q11<50000, V11="Completed"), "Silver", V11="Pending", "Pending")} -> Silver
A12: ORD10011 | B12: C003 | C12: P202 | D12: 19/09/2025 | E12: 23/09/2025 | F12: Rohit Singh | G12: Male | H12: 10/05/1982 | I12: Delhi | J12: North | K12: Home Appliances | L12: Iron | M12: -3 | N12: 2200 | O12: 0 | P12: 35200 | Q12: 2 | R12: Card | S12: Rahul | T12: rohit.singh@company.com | U12: 9521710321 | V12: Pending | W12: {=_xlfn.IFS(OR(V12="Cancelled", Q12<=2), "Blacklisted", AND(P12>=100000, Q12>=4, O12<=0.1, V12="Completed"), "Platinum", AND(P12>=50000, P12<=99999, Q12>=3, V12="Completed"), "Gold", AND(Q12<50000, V12="Completed"), "Silver", V12="Pending", "Pending")} -> Blacklisted
A13: ORD10012 | B13: C008 | C13: P201 | D13: 08/03/2025 | E13: 15/03/2025 | F13: Kavya Nair | G13: Female | H13: 23/01/1982 | I13: Ahmedabad | J13: West | K13: Home Appliances | L13: Mixer | M13: 10 | N13: 3500 | O13: 5 | P13: 33250 | Q13: 5 | R13: Card | S13: Aisha | T13: kavya.nair@company.com | U13: 9123535241 | V13: Cancelled | W13: {=_xlfn.IFS(OR(V13="Cancelled", Q13<=2), "Blacklisted", AND(P13>=100000, Q13>=4, O13<=0.1, V13="Completed"), "Platinum", AND(P13>=50000, P13<=99999, Q13>=3, V13="Completed"), "Gold", AND(Q13<50000, V13="Completed"), "Silver", V13="Pending", "Pending")} -> Blacklisted
A14: ORD10013 | B14: C002 | C14: P202 | D14: 10/01/2025 | E14: 15/01/2025 | F14: Priya Patel | G14: Female | H14: 06/07/1992 | I14: Pune | J14: West | K14: Home Appliances | L14: Iron | M14: 15 | N14: 2200 | O14: 10 | P14: 29700 | Q14: 1 | R14: UPI | S14: Neha | T14: priya.patel@company.com | U14: 9367316892 | V14: Pending | W14: {=_xlfn.IFS(OR(V14="Cancelled", Q14<=2), "Blacklisted", AND(P14>=100000, Q14>=4, O14<=0.1, V14="Completed"), "Platinum", AND(P14>=50000, P14<=99999, Q14>=3, V14="Completed"), "Gold", AND(Q14<50000, V14="Completed"), "Silver", V14="Pending", "Pending")} -> Blacklisted
A15: ORD10014 | B15: C003 | C15: P202 | D15: 09/03/2025 | E15: 13/03/2025 | F15: Rohit Singh | G15: Male | H15: 19/03/2002 | I15: Mumbai | J15: West | K15: Home Appliances | L15: Iron | M15: 17 | N15: 2200 | O15: 5 | P15: 35530 | Q15: 1 | R15: Cash | S15: Karan | T15: rOhit.singh@company.com | U15: 9778489803 | V15: Completed | W15: {=_xlfn.IFS(OR(V15="Cancelled", Q15<=2), "Blacklisted", AND(P15>=100000, Q15>=4, O15<=0.1, V15="Completed"), "Platinum", AND(P15>=50000, P15<=99999, Q15>=3, V15="Completed"), "Gold", AND(Q15<50000, V15="Completed"), "Silver", V15="Pending", "Pending")} -> Blacklisted
... A39: ORD10038 | B39: C006 | C39: P201 | D39: 08/03/2026 | E39: 20/03/2026 | F39: Sneha Joshi | G39: Female | H39: 21/06/1980 | I39: Delhi | J39: North | K39: Home Appliances | L39: Mixer | M39: 20 | N39: 3500 | O39: 10 | P39: 63000 | Q39: 3 | R39: Card | S39: Rahul | T39: sneha.joshi@company.com | U39: 9283578533 | V39: Cancelled | W39: {=_xlfn.IFS(OR(V39="Cancelled", Q39<=2), "Blacklisted", AND(P39>=100000, Q39>=4, O39<=0.1, V39="Completed"), "Platinum", AND(P39>=50000, P39<=99999, Q39>=3, V39="Completed"), "Gold", AND(Q39<50000, V39="Completed"), "Silver", V39="Pending", "Pending")} -> Blacklisted
A40: ORD10039 | B40: C008 | C40: P302 | D40: 13/02/2025 | E40: 19/02/2025 | F40: Kavya Nair | G40: Female | H40: 17/06/1979 | I40: Pune | J40: West | K40: Stationery | L40: Pen | M40: 5 | N40: 1200 | O40: 0 | P40: 100 | Q40: 1 | R40: Cash | S40: Rahul | T40: kavya.nair@company.com | U40: 9963005771 | V40: Cancelled | W40: {=_xlfn.IFS(OR(V40="Cancelled", Q40<=2), "Blacklisted", AND(P40>=100000, Q40>=4, O40<=0.1, V40="Completed"), "Platinum", AND(P40>=50000, P40<=99999, Q40>=3, V40="Completed"), "Gold", AND(Q40<50000, V40="Completed"), "Silver", V40="Pending", "Pending")} -> Blacklisted
A41: ORD10040 | B41: C010 | C41: P203 | D41: 05/10/2025 | E41: 15/10/2025 | F41: Pooja Shah | G41: Female | H41: 18/06/1992 | I41: Mumbai | J41: West | K41: Home Appliances | L41: Microwave | M41: 20 | N41: 8500 | O41: 0 | P41: 170000 | Q41: 1 | R41: UPI | S41: Neha | T41: pooja.shah@company.com | U41: 9484632635 | V41: Cancelled | W41: {=_xlfn.IFS(OR(V41="Cancelled", Q41<=2), "Blacklisted", AND(P41>=100000, Q41>=4, O41<=0.1, V41="Completed"), "Platinum", AND(P41>=50000, P41<=99999, Q41>=3, V41="Completed"), "Gold", AND(Q41<50000, V41="Completed"), "Silver", V41="Pending", "Pending")} -> Blacklisted
A42: ORD10041 | B42: C007 | C42: P301 | D42: 10/02/2026 | E42: 12/02/2026 | F42: Arjun Rao | G42: Male | H42: 06/06/1994 | I42: Bengaluru | J42: South | K42: Stationery | L42: Notebook | M42: 8 | N42: 60 | O42: 15 | P42: 408 | Q42: 5 | R42: UPI | S42: Rahul | T42: arjun.rao@company.com | U42: 9276319484 | V42: Pending | W42: {=_xlfn.IFS(OR(V42="Cancelled", Q42<=2), "Blacklisted", AND(P42>=100000, Q42>=4, O42<=0.1, V42="Completed"), "Platinum", AND(P42>=50000, P42<=99999, Q42>=3, V42="Completed"), "Gold", AND(Q42<50000, V42="Completed"), "Silver", V42="Pending", "Pending")} -> Pending
A43: ORD10042 | B43: C010 | C43: P201 | D43: 04/06/2025 | E43: 16/06/2025 | F43: Pooja Shah | G43: Female | H43: 22/09/1988 | I43: Pune | J43: West | K43: Home Appliances | L43: Mixer | M43: 8 | N43: 3500 | O43: 5 | P43: 26600 | Q43: 1 | R43: Card | S43: Neha | T43: pooja.shah@company.com | U43: 9619034852 | V43: Pending | W43: {=_xlfn.IFS(OR(V43="Cancelled", Q43<=2), "Blacklisted", AND(P43>=100000, Q43>=4, O43<=0.1, V43="Completed"), "Platinum", AND(P43>=50000, P43<=99999, Q43>=3, V43="Completed"), "Gold", AND(Q43<50000, V43="Completed"), "Silver", V43="Pending", "Pending")} -> Blacklisted
A44: ORD10043 | B44: C009 | C44: P203 | D44: 08/02/2026 | E44: 14/02/2026 | F44: Mohit Verma | G44: Male | H44: 14/07/2001 | I44: Jaipur | J44: North | K44: Home Appliances | L44: Microwave | M44: 1 | N44: 8500 | O44: 0 | P44: 8500 | Q44: 2 | R44: Card | S44: Neha | T44: mohit.verma@company.com | U44: 9636416962 | V44: Pending | W44: {=_xlfn.IFS(OR(V44="Cancelled", Q44<=2), "Blacklisted", AND(P44>=100000, Q44>=4, O44<=0.1, V44="Completed"), "Platinum", AND(P44>=50000, P44<=99999, Q44>=3, V44="Completed"), "Gold", AND(Q44<50000, V44="Completed"), "Silver", V44="Pending", "Pending")} -> Blacklisted
A45: ORD10044 | B45: C001 | C45: P303 | D45: 30/03/2025 | E45: 31/03/2025 | F45: Amit Sharma | G45: Male | H45: 09/08/1991 | I45: Pune | J45: West | K45: Stationery | L45: Marker | M45: 8 | N45: 45 | O45: 15 | P45: 306 | Q45: 2 | R45: Card | S45: Aisha | T45: amit.sharma@company.com | U45: 9357133880 | V45: Completed | W45: {=_xlfn.IFS(OR(V45="Cancelled", Q45<=2), "Blacklisted", AND(P45>=100000, Q45>=4, O45<=0.1, V45="Completed"), "Platinum", AND(P45>=50000, P45<=99999, Q45>=3, V45="Completed"), "Gold", AND(Q45<50000, V45="Completed"), "Silver", V45="Pending", "Pending")} -> Blacklisted
A46: ORD10045 | B46: C006 | C46: P202 | D46: 25/04/2025 | E46: 28/04/2025 | F46: Sneha Joshi | G46: Female | H46: 21/10/1988 | I46: Pune | J46: West | K46: Home Appliances | L46: Iron | M46: 16 | N46: 2200 | O46: 5 | P46: 33440 | Q46: 5 | R46: Card | S46: Aisha | T46: sneha.joshi@company.com | U46: 9575210324 | V46: Cancelled | W46: {=_xlfn.IFS(OR(V46="Cancelled", Q46<=2), "Blacklisted", AND(P46>=100000, Q46>=4, O46<=0.1, V46="Completed"), "Platinum", AND(P46>=50000, P46<=99999, Q46>=3, V46="Completed"), "Gold", AND(Q46<50000, V46="Completed"), "Silver", V46="Pending", "Pending")} -> Blacklisted
A47: ORD10046 | B47: C009 | C47: P201 | D47: 13/10/2025 | E47: 23/10/2025 | F47: Mohit Verma | G47: Male | H47: 19/11/2002 | I47: Bengaluru | J47: South | K47: Home Appliances | L47: Mixer | M47: 19 | N47: 3500 | O47: 20 | P47: 53200 | Q47: 3 | R47: Cash | S47: Karan | T47: mohit.verma@company.com | U47: 9276080204 | V47: Cancelled | W47: {=_xlfn.IFS(OR(V47="Cancelled", Q47<=2), "Blacklisted", AND(P47>=100000, Q47>=4, O47<=0.1, V47="Completed"), "Platinum", AND(P47>=50000, P47<=99999, Q47>=3, V47="Completed"), "Gold", AND(Q47<50000, V47="Completed"), "Silver", V47="Pending", "Pending")} -> Blacklisted
A48: ORD10047 | B48: C006 | C48: P102 | D48: 11/10/2025 | E48: 14/10/2025 | F48: Sneha Joshi | G48: Female | H48: 06/07/2000 | I48: Pune | J48: West | K48: Electronics | L48: Mouse | M48: 15 | N48: 700 | O48: 15 | P48: 8925 | Q48: 4 | R48: UPI | S48: Neha | T48: sneha.joshicompany.com | U48: 9856624471 | V48: Completed | W48: {=_xlfn.IFS(OR(V48="Cancelled", Q48<=2), "Blacklisted", AND(P48>=100000, Q48>=4, O48<=0.1, V48="Completed"), "Platinum", AND(P48>=50000, P48<=99999, Q48>=3, V48="Completed"), "Gold", AND(Q48<50000, V48="Completed"), "Silver", V48="Pending", "Pending")} -> Silver
A49: ORD10048 | B49: C006 | C49: P102 | D49: 27/11/2025 | E49: 03/12/2025 | F49: Sneha Joshi | G49: Female | H49: 26/11/1998 | I49: Jaipur | J49: North | K49: Electronics | L49: Mouse | M49: 19 | N49: 700 | O49: 20 | P49: 10640 | Q49: 1 | R49: Cash | S49: Neha | T49: sneha.joshi@company.com | U49: 9238141322 | V49: Completed | W49: {=_xlfn.IFS(OR(V49="Cancelled", Q49<=2), "Blacklisted", AND(P49>=100000, Q49>=4, O49<=0.1, V49="Completed"), "Platinum", AND(P49>=50000, P49<=99999, Q49>=3, V49="Completed"), "Gold", AND(Q49<50000, V49="Completed"), "Silver", V49="Pending", "Pending")} -> Blacklisted
A50: ORD10049 | B50: C009 | C50: P104 | D50: 19/04/2026 | E50: Not Available | F50: Mohit Verma | G50: Male | H50: 03/06/1996 | I50: Delhi | J50: North | K50: Electronics | L50: Monitor | M50: 19 | N50: 12000 | O50: 0 | P50: 228000 | Q50: 1 | R50: NetBanking | S50: Aisha | T50: mohit.verma@company.com | U50: 9890380030 | V50: Completed | W50: {=_xlfn.IFS(OR(V50="Cancelled", Q50<=2), "Blacklisted", AND(P50>=100000, Q50>=4, O50<=0.1, V50="Completed"), "Platinum", AND(P50>=50000, P50<=99999, Q50>=3, V50="Completed"), "Gold", AND(Q50<50000, V50="Completed"), "Silver", V50="Pending", "Pending")} -> Blacklisted
A51: ORD10050 | B51: C004 | C51: P103 | D51: 19/04/2026 | E51: 21/04/2026 | F51: Anita Gupta | G51: Female | H51: 15/03/1987 | I51: Pune | J51: West | K51: Electronics | L51: Keyboard | M51: 6 | N51: 1200 | O51: 5 | P51: 6840 | Q51: 2 | R51: Cash | S51: Ritika | T51: anita.gupta@company.com | U51: 9495893170 | V51: Pending | W51: {=_xlfn.IFS(OR(V51="Cancelled", Q51<=2), "Blacklisted", AND(P51>=100000, Q51>=4, O51<=0.1, V51="Completed"), "Platinum", AND(P51>=50000, P51<=99999, Q51>=3, V51="Completed"), "Gold", AND(Q51<50000, V51="Completed"), "Silver", V51="Pending", "Pending")} -> Blacklisted
A52: ORD10051 | B52: C010 | C52: P202 | D52: 28/03/2025 | E52: 07/04/2025 | F52: Pooja Shah | G52: Female | H52: 20/02/1979 | I52: Bengaluru | J52: South | K52: Home Appliances | L52: Iron | M52: 7 | N52: 2200 | O52: 15 | P52: 13090 | Q52: 1 | R52: UPI | S52: Aisha | T52: pooja.shah@company.com | U52: 9485166307 | V52: Completed | W52: {=_xlfn.IFS(OR(V52="Cancelled", Q52<=2), "Blacklisted", AND(P52>=100000, Q52>=4, O52<=0.1, V52="Completed"), "Platinum", AND(P52>=50000, P52<=99999, Q52>=3, V52="Completed"), "Gold", AND(Q52<50000, V52="Completed"), "Silver", V52="Pending", "Pending")} -> Blacklisted
... A501: ORD10500 | B501: C002 | C501: P201 | D501: 16/09/2025 | E501: 23/09/2025 | F501: Priya Patel | G501: Female | H501: 24/11/1976 | I501: Bengaluru | J501: South | K501: Home Appliances | L501: Mixer | M501: 20 | N501: 3500 | O501: 0 | P501: 70000 | Q501: 1 | R501: NetBanking | S501: Karan | T501: priya.patel@company.com | U501: 9810334941 | V501: Pending | W501: {=_xlfn.IFS(OR(V501="Cancelled", Q501<=2), "Blacklisted", AND(P501>=100000, Q501>=4, O501<=0.1, V501="Completed"), "Platinum", AND(P501>=50000, P501<=99999, Q501>=3, V501="Completed"), "Gold", AND(Q501<50000, V501="Completed"), "Silver", V501="Pending", "Pending")} -> Blacklisted

Sheet Q2
A1: Order_ID | B1: Customer_ID | C1: Product_ID | D1: Order_Date | E1: Delivery_Date | F1: Customer_Name | G1: Gender | H1: DOB | I1: City | J1: Region | K1: Category | L1: Product_Name | M1: Quantity | N1: Unit_Price | O1: Discount_% | P1: Sales | Q1: Rating | R1: Payment_Mode | S1: Salesperson | T1: Email | U1: Phone | V1: Order_Status | W1: Customer Code
A2: ORD10001 | B2: C008 | C2: P202 | D2: 18/09/2025 | E2: 22/09/2025 | F2: Kavya Nair | G2: Female | H2: 01/08/1976 | I2: Hyderabad | J2: South | K2: Home Appliances | L2: Iron | M2: 4 | N2: 2200 | O2: 10 | P2: 7920 | Q2: 4 | R2: Cash | S2: Ritika | T2: kavya.nair@company.com | U2: 9431429797 | V2: Completed | W2: =LEFT(F2, 3) & RIGHT(B2,3) & LEFT(I2,2) -> Kav008Hy
A3: ORD10002 | B3: C008 | C3: P104 | D3: 27/04/2025 | E3: 04/05/2025 | F3: Kavya Nair | G3: Female | H3: 16/10/2000 | I3: Delhi | J3: North | K3: Electronics | L3: Monitor | M3: 17 | N3: 12000 | O3: 10 | P3: 183600 | Q3: 1 | R3: NetBanking | S3: Rahul | T3: kavya.nair@company.com | U3: 9129865339 | V3: Completed | W3: =LEFT(F3, 3) & RIGHT(B3,3) & LEFT(I3,2) -> Kav008De
A4: ORD10003 | B4: C010 | C4: P101 | D4: 03/09/2025 | E4: 14/09/2025 | F4: Pooja Shah | G4: Female | H4: 16/09/1994 | I4: Bengaluru | J4: South | K4: Electronics | L4: Laptop | M4: 5 | N4: 55000 | O4: 5 | P4: 261250 | Q4: 3 | R4: NetBanking | S4: Aisha | T4: pooja.shah@company.com | U4: 9380975626 | V4: Pending | W4: =LEFT(F4, 3) & RIGHT(B4,3) & LEFT(I4,2) -> Poo010Be
A5: ORD10002 | B5: C008 | C5: P202 | D5: 21/03/2026 | E5: 02/04/2026 | F5: Kavya Nair | G5: Female | H5: 07/03/2004 | I5: Bengaluru | J5: South | K5: Home Appliances | L5: Iron | M5: 5 | N5: 2200 | O5: 5 | P5: 10450 | Q5: 5 | R5: NetBanking | S5: Aisha | T5: kavya.nair@company.com | U5: 9600261125 | V5: Cancelled | W5: =LEFT(F5, 3) & RIGHT(B5,3) & LEFT(I5,2) -> Kav008Be
A6: ORD10005 | B6: C009 | C6: P103 | D6: 27/09/2025 | E6: 07/10/2025 | F6: Mohit Verma | G6: Male | H6: 13/04/1976 | I6: Delhi | J6: North | K6: Electronics | L6: Keyboard | M6: 8 | N6: 1200 | O6: 5 | P6: 9120 | Q6: 2 | R6: Card | S6: Aisha | T6: mohit.verma@company.com | U6: 9724635978 | V6: Pending | W6: =LEFT(F6, 3) & RIGHT(B6,3) & LEFT(I6,2) -> Moh009De
A7: ORD10006 | B7: C007 | C7: P202 | D7: 04/01/2026 | E7: 12/01/2026 | F7: Arjun Rao | G7: Male | H7: 07/02/1988 | I7: Hyderabad | J7: South | K7: Home Appliances | L7: Iron | M7: 4 | N7: 2200 | O7: 0 | P7: 8800 | Q7: 1 | R7: UPI | S7: Ritika | T7: arjun.rao@company.com | U7: 9780584905 | V7: Completed | W7: =LEFT(F7, 3) & RIGHT(B7,3) & LEFT(I7,2) -> Arj007Hy
A8: ORD10007 | B8: C008 | C8: P201 | D8: 31/02/2025 | E8: 25/02/2026 | F8: Kavya Nair | G8: Female | H8: 20/03/2003 | I8: Hyderabad | J8: South | K8: Home Appliances | L8: Mixer | M8: 2 | N8: 3500 | O8: 5 | P8: 6650 | Q8: 1 | R8: UPI | S8: Ritika | T8: kavya.nair@company.com | U8: 9958252176 | V8: Completed | W8: =LEFT(F8, 3) & RIGHT(B8,3) & LEFT(I8,2) -> Kav008Hy
A9: ORD10008 | B9: C002 | C9: P104 | D9: 13/04/2025 | E9: 19/04/2025 | F9: Priya Patel | G9: Female | H9: 07/03/1995 | I9: Mumbai | J9: West | K9: Electronics | L9: Monitor | M9: 14 | N9: 12000 | O9: 15 | P9: 142800 | Q9: 4 | R9: NetBanking | S9: Ritika | T9: priya.patel@company.com | U9: 9705521654 | V9: Completed | W9: =LEFT(F9, 3) & RIGHT(B9,3) & LEFT(I9,2) -> Pri002Mu
A10: ORD10009 | B10: C008 | C10: P104 | D10: 31/01/2026 | E10: 02/02/2026 | F10: Kavya Nair | G10: Female | H10: 06/04/1997 | I10: Pune | J10: West | K10: Electronics | L10: Monitor | M10: 4 | N10: 12000 | O10: 15 | P10: 40800 | Q10: 4 | R10: UPI | S10: Neha | T10: kavya.nair@company.com | U10: 9588041011 | V10: Completed | W10: =LEFT(F10, 3) & RIGHT(B10,3) & LEFT(I10,2) -> Kav008Pu
A11: ORD10010 | B11: C002 | C11: P301 | D11: 25/03/2025 | E11: 27/03/2025 | F11: Priya Patel | G11: Female | H11: 07/01/1990 | I11: Mumbai | J11: West | K11: Stationery | L11: Notebook | M11: 6 | N11: 60 | O11: 0 | P11: 360 | Q11: 4 | R11: Card | S11: Neha | T11: priya.patel@company.com | U11: 9340540608 | V11: Completed | W11: =LEFT(F11, 3) & RIGHT(B11,3) & LEFT(I11,2) -> Pri002Mu
A12: ORD10011 | B12: C003 | C12: P202 | D12: 19/09/2025 | E12: 23/09/2025 | F12: Rohit Singh | G12: Male | H12: 10/05/1982 | I12: Delhi | J12: North | K12: Home Appliances | L12: Iron | M12: -3 | N12: 2200 | O12: 0 | P12: 35200 | Q12: 2 | R12: Card | S12: Rahul | T12: rohit.singh@company.com | U12: 9521710321 | V12: Pending | W12: =LEFT(F12, 3) & RIGHT(B12,3) & LEFT(I12,2) -> Roh003De
A13: ORD10012 | B13: C008 | C13: P201 | D13: 08/03/2025 | E13: 15/03/2025 | F13: Kavya Nair | G13: Female | H13: 23/01/1982 | I13: Ahmedabad | J13: West | K13: Home Appliances | L13: Mixer | M13: 10 | N13: 3500 | O13: 5 | P13: 33250 | Q13: 5 | R13: Card | S13: Aisha | T13: kavya.nair@company.com | U13: 9123535241 | V13: Cancelled | W13: =LEFT(F13, 3) & RIGHT(B13,3) & LEFT(I13,2) -> Kav008Ah
... A39: ORD10038 | B39: C006 | C39: P201 | D39: 08/03/2026 | E39: 20/03/2026 | F39: Sneha Joshi | G39: Female | H39: 21/06/1980 | I39: Delhi | J39: North | K39: Home Appliances | L39: Mixer | M39: 20 | N39: 3500 | O39: 10 | P39: 63000 | Q39: 3 | R39: Card | S39: Rahul | T39: sneha.joshi@company.com | U39: 9283578533 | V39: Cancelled | W39: =LEFT(F39, 3) & RIGHT(B39,3) & LEFT(I39,2) -> Sne006De
A40: ORD10039 | B40: C008 | C40: P302 | D40: 13/02/2025 | E40: 19/02/2025 | F40: Kavya Nair | G40: Female | H40: 17/06/1979 | I40: Pune | J40: West | K40: Stationery | L40: Pen | M40: 5 | N40: 1200 | O40: 0 | P40: 100 | Q40: 1 | R40: Cash | S40: Rahul | T40: kavya.nair@company.com | U40: 9963005771 | V40: Cancelled | W40: =LEFT(F40, 3) & RIGHT(B40,3) & LEFT(I40,2) -> Kav008Pu
A41: ORD10040 | B41: C010 | C41: P203 | D41: 05/10/2025 | E41: 15/10/2025 | F41: Pooja Shah | G41: Female | H41: 18/06/1992 | I41: Mumbai | J41: West | K41: Home Appliances | L41: Microwave | M41: 20 | N41: 8500 | O41: 0 | P41: 170000 | Q41: 1 | R41: UPI | S41: Neha | T41: pooja.shah@company.com | U41: 9484632635 | V41: Cancelled | W41: =LEFT(F41, 3) & RIGHT(B41,3) & LEFT(I41,2) -> Poo010Mu
A42: ORD10041 | B42: C007 | C42: P301 | D42: 10/02/2026 | E42: 12/02/2026 | F42: Arjun Rao | G42: Male | H42: 06/06/1994 | I42: Bengaluru | J42: South | K42: Stationery | L42: Notebook | M42: 8 | N42: 60 | O42: 15 | P42: 408 | Q42: 5 | R42: UPI | S42: Rahul | T42: arjun.rao@company.com | U42: 9276319484 | V42: Pending | W42: =LEFT(F42, 3) & RIGHT(B42,3) & LEFT(I42,2) -> Arj007Be
A43: ORD10042 | B43: C010 | C43: P201 | D43: 04/06/2025 | E43: 16/06/2025 | F43: Pooja Shah | G43: Female | H43: 22/09/1988 | I43: Pune | J43: West | K43: Home Appliances | L43: Mixer | M43: 8 | N43: 3500 | O43: 5 | P43: 26600 | Q43: 1 | R43: Card | S43: Neha | T43: pooja.shah@company.com | U43: 9619034852 | V43: Pending | W43: =LEFT(F43, 3) & RIGHT(B43,3) & LEFT(I43,2) -> Poo010Pu
A44: ORD10043 | B44: C009 | C44: P203 | D44: 08/02/2026 | E44: 14/02/2026 | F44: Mohit Verma | G44: Male | H44: 14/07/2001 | I44: Jaipur | J44: North | K44: Home Appliances | L44: Microwave | M44: 1 | N44: 8500 | O44: 0 | P44: 8500 | Q44: 2 | R44: Card | S44: Neha | T44: mohit.verma@company.com | U44: 9636416962 | V44: Pending | W44: =LEFT(F44, 3) & RIGHT(B44,3) & LEFT(I44,2) -> Moh009Ja
A45: ORD10044 | B45: C001 | C45: P303 | D45: 30/03/2025 | E45: 31/03/2025 | F45: Amit Sharma | G45: Male | H45: 09/08/1991 | I45: Pune | J45: West | K45: Stationery | L45: Marker | M45: 8 | N45: 45 | O45: 15 | P45: 306 | Q45: 2 | R45: Card | S45: Aisha | T45: amit.sharma@company.com | U45: 9357133880 | V45: Completed | W45: =LEFT(F45, 3) & RIGHT(B45,3) & LEFT(I45,2) -> Ami001Pu
A46: ORD10045 | B46: C006 | C46: P202 | D46: 25/04/2025 | E46: 28/04/2025 | F46: Sneha Joshi | G46: Female | H46: 21/10/1988 | I46: Pune | J46: West | K46: Home Appliances | L46: Iron | M46: 16 | N46: 2200 | O46: 5 | P46: 33440 | Q46: 5 | R46: Card | S46: Aisha | T46: sneha.joshi@company.com | U46: 9575210324 | V46: Cancelled | W46: =LEFT(F46, 3) & RIGHT(B46,3) & LEFT(I46,2) -> Sne006Pu
A47: ORD10046 | B47: C009 | C47: P201 | D47: 13/10/2025 | E47: 23/10/2025 | F47: Mohit Verma | G47: Male | H47: 19/11/2002 | I47: Bengaluru | J47: South | K47: Home Appliances | L47: Mixer | M47: 19 | N47: 3500 | O47: 20 | P47: 53200 | Q47: 3 | R47: Cash | S47: Karan | T47: mohit.verma@company.com | U47: 9276080204 | V47: Cancelled | W47: =LEFT(F47, 3) & RIGHT(B47,3) & LEFT(I47,2) -> Moh009Be
A48: ORD10047 | B48: C006 | C48: P102 | D48: 11/10/2025 | E48: 14/10/2025 | F48: Sneha Joshi | G48: Female | H48: 06/07/2000 | I48: Pune | J48: West | K48: Electronics | L48: Mouse | M48: 15 | N48: 700 | O48: 15 | P48: 8925 | Q48: 4 | R48: UPI | S48: Neha | T48: Invalid Email | U48: 9856624471 | V48: Completed | W48: =LEFT(F48, 3) & RIGHT(B48,3) & LEFT(I48,2) -> Sne006Pu
A49: ORD10048 | B49: C006 | C49: P102 | D49: 27/11/2025 | E49: 03/12/2025 | F49: Sneha Joshi | G49: Female | H49: 26/11/1998 | I49: Jaipur | J49: North | K49: Electronics | L49: Mouse | M49: 19 | N49: 700 | O49: 20 | P49: 10640 | Q49: 1 | R49: Cash | S49: Neha | T49: sneha.joshi@company.com | U49: 9238141322 | V49: Completed | W49: =LEFT(F49, 3) & RIGHT(B49,3) & LEFT(I49,2) -> Sne006Ja
A50: ORD10049 | B50: C009 | C50: P104 | D50: 19/04/2026 | E50: Not Available | F50: Mohit Verma | G50: Male | H50: 03/06/1996 | I50: Delhi | J50: North | K50: Electronics | L50: Monitor | M50: 19 | N50: 12000 | O50: 0 | P50: 228000 | Q50: 1 | R50: NetBanking | S50: Aisha | T50: mohit.verma@company.com | U50: 9890380030 | V50: Completed | W50: =LEFT(F50, 3) & RIGHT(B50,3) & LEFT(I50,2) -> Moh009De
A51: ORD10050 | B51: C004 | C51: P103 | D51: 19/04/2026 | E51: 21/04/2026 | F51: Anita Gupta | G51: Female | H51: 15/03/1987 | I51: Pune | J51: West | K51: Electronics | L51: Keyboard | M51: 6 | N51: 1200 | O51: 5 | P51: 6840 | Q51: 2 | R51: Cash | S51: Ritika | T51: anita.gupta@company.com | U51: 9495893170 | V51: Pending | W51: =LEFT(F51, 3) & RIGHT(B51,3) & LEFT(I51,2) -> Ani004Pu
A52: ORD10051 | B52: C010 | C52: P202 | D52: 28/03/2025 | E52: 07/04/2025 | F52: Pooja Shah | G52: Female | H52: 20/02/1979 | I52: Bengaluru | J52: South | K52: Home Appliances | L52: Iron | M52: 7 | N52: 2200 | O52: 15 | P52: 13090 | Q52: 1 | R52: UPI | S52: Aisha | T52: pooja.shah@company.com | U52: 9485166307 | V52: Completed | W52: =LEFT(F52, 3) & RIGHT(B52,3) & LEFT(I52,2) -> Poo010Be
... A119: ORD10118 | B119: C001 | C119: P303 | D119: 31/05/2025 | E119: 11/06/2025 | F119: Amit Sharma | G119: Male | H119: 07/09/1995 | I119: Pune | J119: West | K119: Stationery | L119: Marker | M119: 16 | N119: 45 | O119: 0 | P119: 720 | Q119: 1 | R119: NetBanking | S119: Aisha | T119: amit.sharma@company.com | U119: 9807154421 | V119: Completed | W119: =LEFT(F119, 3) & RIGHT(B119,3) & LEFT(I119,2) -> Ami001Pu
A120: ORD10119 | B120: C009 | C120: P103 | D120: 30/05/2025 | E120: 02/06/2025 | F120: Mohit Verma | G120: Male | H120: 08/03/1988 | I120: Ahmedabad | J120: West | K120: Electronics | L120: Keyboard | M120: Ten | N120: 1200 | O120: 15 | P120: 7140 | Q120: 4 | R120: UPI | S120: Karan | T120: mohit.verma@company.com | U120: 9919834000 | V120: Pending | W120: =LEFT(F120, 3) & RIGHT(B120,3) & LEFT(I120,2) -> Moh009Ah
A121: ORD10120 | B121: C002 | C121: P104 | D121: 19/08/2025 | E121: 30/08/2025 | F121: Priya Patel | G121: Female | H121: 07/07/1989 | I121: Jaipur | J121: North | K121: Electronics | L121: Monitor | M121: 14 | N121: 12000 | O121: 15 | P121: 142800 | Q121: 2 | R121: NetBanking | S121: Aisha | T121: priya.patel@company.com | U121: 9739798818 | V121: Pending | W121: =LEFT(F121, 3) & RIGHT(B121,3) & LEFT(I121,2) -> Pri002Ja
A122: ORD10121 | B122: C003 | C122: P203 | D122: 14/12/2025 | E122: 16/12/2025 | F122: Rohit Singh | G122: Male | H122: 11/11/1993 | I122: Pune | J122: West | K122: Home Appliances | L122: Microwave | M122: 8 | N122: 8500 | O122: 20 | P122: 54400 | Q122: 3 | R122: Card | S122: Rahul | T122: rohit.singh@company.com | U122: 9208625306 | V122: Completed | W122: =LEFT(F122, 3) & RIGHT(B122,3) & LEFT(I122,2) -> Roh003Pu
A123: ORD10122 | B123: C007 | C123: P303 | D123: 31/01/2026 | E123: 10/02/2026 | F123: Arjun Rao | G123: Male | H123: 01/02/2000 | I123: Bengaluru | J123: South | K123: Stationery | L123: Marker | M123: 3 | N123: 45 | O123: 0 | P123: 135 | Q123: 4 | R123: UPI | S123: Aisha | T123: arjun.rao@company.com | U123: 9970178536 | V123: Cancelled | W123: =LEFT(F123, 3) & RIGHT(B123,3) & LEFT(I123,2) -> Arj007Be
A124: ORD10123 | B124: C001 | C124: P102 | D124: 03/01/2026 | E124: 04/01/2026 | F124: Amit Sharma | G124: Male | H124: 22/06/1986 | I124: Jaipur | J124: North | K124: Electronics | L124: Mouse | M124: 13 | N124: 700 | O124: 5 | P124: 8645 | Q124: 3 | R124: Card | S124: Neha | T124: amit.sharma@company.com | U124: 9633745195 | V124: Pending | W124: =LEFT(F124, 3) & RIGHT(B124,3) & LEFT(I124,2) -> Ami001Ja
A125: ORD10124 | B125: C004 | C125: P103 | D125: 20/10/2025 | E125: 26/10/2025 | F125: Anita Gupta | G125: Female | H125: 16/02/1986 | I125: Mumbai | J125: West | K125: Electronics | L125: Keyboard | M125: 14 | N125: 1200 | O125: 20 | P125: 13440 | Q125: 5 | R125: NetBanking | S125: Aisha | T125: anita.gupta@company.com | U125: 9922102053 | V125: Completed | W125: =LEFT(F125, 3) & RIGHT(B125,3) & LEFT(I125,2) -> Ani004Mu
A126: ORD10125 | B126: C002 | C126: P303 | D126: 11/05/2025 | E126: 21/05/2025 | F126: Priya Patel | G126: Female | H126: 18/09/1991 | I126: Delhi | J126: North | K126: Stationery | L126: Marker | M126: 2 | N126: 45 | O126: 5 | P126: 85.5 | Q126: 3 | R126: UPI | S126: Ritika | T126: priya.patel@company.com | U126: 9135963930 | V126: Cancelled | W126: =LEFT(F126, 3) & RIGHT(B126,3) & LEFT(I126,2) -> Pri002De
A127: ORD10126 | B127: C004 | C127: P103 | D127: 02/01/2026 | E127: 06/01/2026 | F127: Anita Gupta | G127: Female | H127: 04/01/1981 | I127: Bengaluru | J127: South | K127: Electronics | L127: Keyboard | M127: 2 | N127: 1200 | O127: 20 | P127: 1920 | Q127: 3 | R127: Card | S127: Neha | T127: anita.gupta@company.com | U127: 9429405275 | V127: Completed | W127: =LEFT(F127, 3) & RIGHT(B127,3) & LEFT(I127,2) -> Ani004Be
A128: ORD10127 | B128: C003 | C128: P101 | D128: 20/04/2026 | E128: 26/04/2026 | F128: Rohit Singh | G128: Male | H128: 12/10/2004 | I128: Bengaluru | J128: South | K128: Electronics | L128: Laptop | M128: 10 | N128: 55000 | O128: 5 | P128: 522500 | Q128: 5 | R128: UPI | S128: Aisha | T128: rohit.singh@company.com | U128: 9521757571 | V128: Pending | W128: =LEFT(F128, 3) & RIGHT(B128,3) & LEFT(I128,2) -> Roh003Be
A129: ORD10128 | B129: C006 | C129: P201 | D129: 04/08/2025 | E129: 05/08/2025 | F129: Sneha Joshi | G129: Female | H129: 25/03/1984 | I129: Jaipur | J129: North | K129: Home Appliances | L129: Mixer | M129: 15 | N129: 3500 | O129: 10 | P129: 47250 | Q129: 3 | R129: NetBanking | S129: Neha | T129: sneha.joshi@company.com | U129: 9467375455 | V129: Completed | W129: =LEFT(F129, 3) & RIGHT(B129,3) & LEFT(I129,2) -> Sne006Ja
A130: ORD10129 | B130: C002 | C130: P202 | D130: 13/08/2025 | E130: 18/08/2025 | F130: Priya Patel | G130: Female | H130: 09/09/1982 | I130: Bengaluru | J130: South | K130: Home Appliances | L130: Iron | M130: 10 | N130: 2200 | O130: 15 | P130: 18700 | Q130: 4 | R130: Card | S130: Rahul | T130: priya.patel@company.com | U130: 9838809695 | V130: Pending | W130: =LEFT(F130, 3) & RIGHT(B130,3) & LEFT(I130,2) -> Pri002Be
A131: ORD10130 | B131: C006 | C131: P201 | D131: 16/06/2025 | E131: 24/06/2025 | F131: Sneha Joshi | G131: Female | H131: 15/02/1993 | I131: Pune | J131: West | K131: Home Appliances | L131: Mixer | M131: 11 | N131: 3500 | O131: 5 | P131: 36575 | Q131: 5 | R131: Cash | S131: Ritika | T131: sneha.joshi@company.com | U131: 9296609782 | V131: Cancelled | W131: =LEFT(F131, 3) & RIGHT(B131,3) & LEFT(I131,2) -> Sne006Pu
A132: ORD10131 | B132: C004 | C132: P103 | D132: 27/04/2026 | E132: 30/04/2026 | F132: Anita Gupta | G132: Female | H132: 08/04/2003 | I132: Bengaluru | J132: South | K132: Electronics | L132: Keyboard | M132: 14 | N132: 1200 | O132: 0 | P132: 16800 | Q132: 5 | R132: Cash | S132: Rahul | T132: anita.gupta@company.com | U132: 9848259992 | V132: Cancelled | W132: =LEFT(F132, 3) & RIGHT(B132,3) & LEFT(I132,2) -> Ani004Be
... A501: ORD10500 | B501: C002 | C501: P201 | D501: 16/09/2025 | E501: 23/09/2025 | F501: Priya Patel | G501: Female | H501: 24/11/1976 | I501: Bengaluru | J501: South | K501: Home Appliances | L501: Mixer | M501: 20 | N501: 3500 | O501: 0 | P501: 70000 | Q501: 1 | R501: NetBanking | S501: Karan | T501: priya.patel@company.com | U501: 9810334941 | V501: Pending | W501: =LEFT(F501, 3) & RIGHT(B501,3) & LEFT(I501,2) -> Pri002Be

Sheet Q3
A1: Order_ID | B1: Customer_ID | C1: Product_ID | D1: Order_Date | E1: Delivery_Date | F1: Customer_Name | G1: Gender | H1: DOB | I1: City | J1: Region | K1: Category | L1: Product_Name | M1: Quantity | N1: Unit_Price | O1: Discount_% | P1: Sales | Q1: Rating | R1: Payment_Mode | S1: Salesperson | T1: Email | U1: Phone | V1: Order_Status | W1: Customer Age | X1: Delivery Time (Days) | Y1: Delivery Status
A2: ORD10001 | B2: C008 | C2: P202 | D2: 45918 | E2: 45922 | F2: Kavya Nair | G2: Female | H2: 27973 | I2: Hyderabad | J2: South | K2: Home Appliances | L2: Iron | M2: 4 | N2: 2200 | O2: 10 | P2: 7920 | Q2: 4 | R2: Cash | S2: Ritika | T2: kavya.nair@company.com | U2: 9431429797 | V2: Completed | W2: =DATEDIF(H2, TODAY(), "y") -> 50 | X2: =IF(OR(ISBLANK(D2), ISBLANK(E2)), "Not Available", E2-D2) -> 4 | Y2: =IF(ISBLANK(E2), "Pending", IF(E2-D2<=5, "On Time ", "Delayed")) -> On Time
A3: ORD10002 | B3: C008 | C3: P104 | D3: 45774 | E3: 45781 | F3: Kavya Nair | G3: Female | H3: 36815 | I3: Delhi | J3: North | K3: Electronics | L3: Monitor | M3: 17 | N3: 12000 | O3: 10 | P3: 183600 | Q3: 1 | R3: NetBanking | S3: Rahul | T3: kavya.nair@company.com | U3: 9129865339 | V3: Completed | W3: =DATEDIF(H3, TODAY(), "y") -> 25 | X3: =IF(OR(ISBLANK(D3), ISBLANK(E3)), "Not Available", E3-D3) -> 7 | Y3: =IF(ISBLANK(E3), "Pending", IF(E3-D3<=5, "On Time ", "Delayed")) -> Delayed
A4: ORD10003 | B4: C010 | C4: P101 | D4: 45903 | E4: 45914 | F4: Pooja Shah | G4: Female | H4: 34593 | I4: Bengaluru | J4: South | K4: Electronics | L4: Laptop | M4: 5 | N4: 55000 | O4: 5 | P4: 261250 | Q4: 3 | R4: NetBanking | S4: Aisha | T4: pooja.shah@company.com | U4: 9380975626 | V4: Pending | W4: =DATEDIF(H4, TODAY(), "y") -> 32 | X4: =IF(OR(ISBLANK(D4), ISBLANK(E4)), "Not Available", E4-D4) -> 11 | Y4: =IF(ISBLANK(E4), "Pending", IF(E4-D4<=5, "On Time ", "Delayed")) -> Delayed
A5: ORD10002 | B5: C008 | C5: P202 | D5: 46102 | E5: 46114 | F5: Kavya Nair | G5: Female | H5: 38053 | I5: Bengaluru | J5: South | K5: Home Appliances | L5: Iron | M5: 5 | N5: 2200 | O5: 5 | P5: 10450 | Q5: 5 | R5: NetBanking | S5: Aisha | T5: kavya.nair@company.com | U5: 9600261125 | V5: Cancelled | W5: =DATEDIF(H5, TODAY(), "y") -> 22 | X5: =IF(OR(ISBLANK(D5), ISBLANK(E5)), "Not Available", E5-D5) -> 12 | Y5: =IF(ISBLANK(E5), "Pending", IF(E5-D5<=5, "On Time ", "Delayed")) -> Delayed
A6: ORD10005 | B6: C009 | C6: P103 | D6: 45927 | E6: 45937 | F6: Mohit Verma | G6: Male | H6: 27863 | I6: Delhi | J6: North | K6: Electronics | L6: Keyboard | M6: 8 | N6: 1200 | O6: 5 | P6: 9120 | Q6: 2 | R6: Card | S6: Aisha | T6: mohit.verma@company.com | U6: 9724635978 | V6: Pending | W6: =DATEDIF(H6, TODAY(), "y") -> 50 | X6: =IF(OR(ISBLANK(D6), ISBLANK(E6)), "Not Available", E6-D6) -> 10 | Y6: =IF(ISBLANK(E6), "Pending", IF(E6-D6<=5, "On Time ", "Delayed")) -> Delayed
A7: ORD10006 | B7: C007 | C7: P202 | D7: 46026 | E7: 46034 | F7: Arjun Rao | G7: Male | H7: 32180 | I7: Hyderabad | J7: South | K7: Home Appliances | L7: Iron | M7: 4 | N7: 2200 | O7: 0 | P7: 8800 | Q7: 1 | R7: UPI | S7: Ritika | T7: arjun.rao@company.com | U7: 9780584905 | V7: Completed | W7: =DATEDIF(H7, TODAY(), "y") -> 38 | X7: =IF(OR(ISBLANK(D7), ISBLANK(E7)), "Not Available", E7-D7) -> 8 | Y7: =IF(ISBLANK(E7), "Pending", IF(E7-D7<=5, "On Time ", "Delayed")) -> Delayed
A8: ORD10007 | B8: C008 | C8: P201 | E8: 46078 | F8: Kavya Nair | G8: Female | H8: 37700 | I8: Hyderabad | J8: South | K8: Home Appliances | L8: Mixer | M8: 2 | N8: 3500 | O8: 5 | P8: 6650 | Q8: 1 | R8: UPI | S8: Ritika | T8: kavya.nair@company.com | U8: 9958252176 | V8: Completed | W8: =DATEDIF(H8, TODAY(), "y") -> 23 | X8: =IF(OR(ISBLANK(D8), ISBLANK(E8)), "Not Available", E8-D8) -> Not Available | Y8: =IF(ISBLANK(E8), "Pending", IF(E8-D8<=5, "On Time ", "Delayed")) -> Delayed
A9: ORD10008 | B9: C002 | C9: P104 | D9: 45760 | E9: 45766 | F9: Priya Patel | G9: Female | H9: 34765 | I9: Mumbai | J9: West | K9: Electronics | L9: Monitor | M9: 14 | N9: 12000 | O9: 15 | P9: 142800 | Q9: 4 | R9: NetBanking | S9: Ritika | T9: priya.patel@company.com | U9: 9705521654 | V9: Completed | W9: =DATEDIF(H9, TODAY(), "y") -> 31 | X9: =IF(OR(ISBLANK(D9), ISBLANK(E9)), "Not Available", E9-D9) -> 6 | Y9: =IF(ISBLANK(E9), "Pending", IF(E9-D9<=5, "On Time ", "Delayed")) -> Delayed
A10: ORD10009 | B10: C008 | C10: P104 | D10: 46053 | E10: 46055 | F10: Kavya Nair | G10: Female | H10: 35526 | I10: Pune | J10: West | K10: Electronics | L10: Monitor | M10: 4 | N10: 12000 | O10: 15 | P10: 40800 | Q10: 4 | R10: UPI | S10: Neha | T10: kavya.nair@company.com | U10: 9588041011 | V10: Completed | W10: =DATEDIF(H10, TODAY(), "y") -> 29 | X10: =IF(OR(ISBLANK(D10), ISBLANK(E10)), "Not Available", E10-D10) -> 2 | Y10: =IF(ISBLANK(E10), "Pending", IF(E10-D10<=5, "On Time ", "Delayed")) -> On Time
A11: ORD10010 | B11: C002 | C11: P301 | D11: 45741 | E11: 45743 | F11: Priya Patel | G11: Female | H11: 32880 | I11: Mumbai | J11: West | K11: Stationery | L11: Notebook | M11: 6 | N11: 60 | O11: 0 | P11: 360 | Q11: 4 | R11: Card | S11: Neha | T11: priya.patel@company.com | U11: 9340540608 | V11: Completed | W11: =DATEDIF(H11, TODAY(), "y") -> 36 | X11: =IF(OR(ISBLANK(D11), ISBLANK(E11)), "Not Available", E11-D11) -> 2 | Y11: =IF(ISBLANK(E11), "Pending", IF(E11-D11<=5, "On Time ", "Delayed")) -> On Time
A12: ORD10011 | B12: C003 | C12: P202 | D12: 45919 | E12: 45923 | F12: Rohit Singh | G12: Male | H12: 30081 | I12: Delhi | J12: North | K12: Home Appliances | L12: Iron | M12: -3 | N12: 2200 | O12: 0 | P12: 35200 | Q12: 2 | R12: Card | S12: Rahul | T12: rohit.singh@company.com | U12: 9521710321 | V12: Pending | W12: =DATEDIF(H12, TODAY(), "y") -> 44 | X12: =IF(OR(ISBLANK(D12), ISBLANK(E12)), "Not Available", E12-D12) -> 4 | Y12: =IF(ISBLANK(E12), "Pending", IF(E12-D12<=5, "On Time ", "Delayed")) -> On Time
A13: ORD10012 | B13: C008 | C13: P201 | D13: 45724 | E13: 45731 | F13: Kavya Nair | G13: Female | H13: 29974 | I13: Ahmedabad | J13: West | K13: Home Appliances | L13: Mixer | M13: 10 | N13: 3500 | O13: 5 | P13: 33250 | Q13: 5 | R13: Card | S13: Aisha | T13: kavya.nair@company.com | U13: 9123535241 | V13: Cancelled | W13: =DATEDIF(H13, TODAY(), "y") -> 44 | X13: =IF(OR(ISBLANK(D13), ISBLANK(E13)), "Not Available", E13-D13) -> 7 | Y13: =IF(ISBLANK(E13), "Pending", IF(E13-D13<=5, "On Time ", "Delayed")) -> Delayed
A14: ORD10013 | B14: C002 | C14: P202 | D14: 45667 | E14: 45672 | F14: Priya Patel | G14: Female | H14: 33791 | I14: Pune | J14: West | K14: Home Appliances | L14: Iron | M14: 15 | N14: 2200 | O14: 10 | P14: 29700 | Q14: 1 | R14: UPI | S14: Neha | T14: priya.patel@company.com | U14: 9367316892 | V14: Pending | W14: =DATEDIF(H14, TODAY(), "y") -> 34 | X14: =IF(OR(ISBLANK(D14), ISBLANK(E14)), "Not Available", E14-D14) -> 5 | Y14: =IF(ISBLANK(E14), "Pending", IF(E14-D14<=5, "On Time ", "Delayed")) -> On Time
A15: ORD10014 | B15: C003 | C15: P202 | D15: 45725 | E15: 45729 | F15: Rohit Singh | G15: Male | H15: 37334 | I15: Mumbai | J15: West | K15: Home Appliances | L15: Iron | M15: 17 | N15: 2200 | O15: 5 | P15: 35530 | Q15: 1 | R15: Cash | S15: Karan | T15: rohit.singh@company.com | U15: 9778489803 | V15: Completed | W15: =DATEDIF(H15, TODAY(), "y") -> 24 | X15: =IF(OR(ISBLANK(D15), ISBLANK(E15)), "Not Available", E15-D15) -> 4 | Y15: =IF(ISBLANK(E15), "Pending", IF(E15-D15<=5, "On Time ", "Delayed")) -> On Time
A16: ORD10015 | B16: C008 | C16: P201 | D16: 45864 | E16: 45876 | F16: Kavya Nair | G16: Female | H16: 36908 | I16: Mumbai | J16: West | K16: Home Appliances | L16: Mixer | M16: 15 | N16: 3500 | O16: 15 | P16: 44625 | Q16: 2 | R16: Cash | S16: Neha | T16: kavya.nair@company.com | U16: 9582960180 | V16: Cancelled | W16: =DATEDIF(H16, TODAY(), "y") -> 25 | X16: =IF(OR(ISBLANK(D16), ISBLANK(E16)), "Not Available", E16-D16) -> 12 | Y16: =IF(ISBLANK(E16), "Pending", IF(E16-D16<=5, "On Time ", "Delayed")) -> Delayed
A17: ORD10016 | B17: C010 | C17: P103 | D17: 46120 | E17: 46123 | F17: Pooja Shah | G17: Female | H17: 37357 | I17: Hyderabad | J17: South | K17: Electronics | L17: Keyboard | M17: 3 | N17: 1200 | O17: 5 | P17: 3420 | Q17: 5 | R17: UPI | S17: Ritika | T17: Invalid Email | U17: 9611394005 | V17: Completed | W17: =DATEDIF(H17, TODAY(), "y") -> 24 | X17: =IF(OR(ISBLANK(D17), ISBLANK(E17)), "Not Available", E17-D17) -> 3 | Y17: =IF(ISBLANK(E17), "Pending", IF(E17-D17<=5, "On Time ", "Delayed")) -> On Time
A18: ORD10017 | B18: C004 | C18: P203 | D18: 46075 | E18: 46084 | F18: Amit Sharma | G18: Female | H18: 37272 | I18: Pune | J18: West | K18: Home Appliances | L18: Microwave | M18: 13 | N18: 8500 | O18: 20 | P18: 88400 | Q18: 4 | R18: Card | S18: Rahul | T18: anita.gupta@company.com | U18: 9692599404 | V18: Pending | W18: =DATEDIF(H18, TODAY(), "y") -> 24 | X18: =IF(OR(ISBLANK(D18), ISBLANK(E18)), "Not Available", E18-D18) -> 9 | Y18: =IF(ISBLANK(E18), "Pending", IF(E18-D18<=5, "On Time ", "Delayed")) -> Delayed
A19: ORD10018 | B19: C007 | C19: P203 | D19: 46081 | E19: 46086 | F19: Arjun Rao | G19: Male | H19: 32790 | I19: Ahmedabad | J19: West | K19: Home Appliances | L19: Microwave | M19: 4 | N19: 8500 | O19: 20 | P19: 27200 | Q19: 5 | R19: Card | S19: Aisha | T19: arjun.rao@company.com | U19: 9426119622 | V19: Pending | W19: =DATEDIF(H19, TODAY(), "y") -> 37 | X19: =IF(OR(ISBLANK(D19), ISBLANK(E19)), "Not Available", E19-D19) -> 5 | Y19: =IF(ISBLANK(E19), "Pending", IF(E19-D19<=5, "On Time ", "Delayed")) -> On Time
A20: ORD10019 | B20: C007 | C20: P102 | D20: 45992 | E20: 45995 | F20: Arjun Rao | G20: Male | H20: 33539 | I20: Mumbai | J20: West | K20: Electronics | L20: Mouse | M20: 9 | N20: 700 | O20: 5 | P20: 5985 | Q20: 3 | R20: UPI | S20: Ritika | T20: arjun.rao@company.com | U20: 9184436009 | V20: Pending | W20: =DATEDIF(H20, TODAY(), "y") -> 34 | X20: =IF(OR(ISBLANK(D20), ISBLANK(E20)), "Not Available", E20-D20) -> 3 | Y20: =IF(ISBLANK(E20), "Pending", IF(E20-D20<=5, "On Time ", "Delayed")) -> On Time
... A39: ORD10038 | B39: C006 | C39: P201 | D39: 46089 | E39: 46101 | F39: Sneha Joshi | G39: Female | H39: 29393 | I39: Delhi | J39: North | K39: Home Appliances | L39: Mixer | M39: 20 | N39: 3500 | O39: 10 | P39: 63000 | Q39: 3 | R39: Card | S39: Rahul | T39: sneha.joshi@company.com | U39: 9283578533 | V39: Cancelled | W39: =DATEDIF(H39, TODAY(), "y") -> 46 | X39: =IF(OR(ISBLANK(D39), ISBLANK(E39)), "Not Available", E39-D39) -> 12 | Y39: =IF(ISBLANK(E39), "Pending", IF(E39-D39<=5, "On Time ", "Delayed")) -> Delayed
A40: ORD10039 | B40: C008 | C40: P302 | D40: 45701 | E40: 45707 | F40: Kavya Nair | G40: Female | H40: 29023 | I40: Pune | J40: West | K40: Stationery | L40: Pen | M40: 5 | N40: 1200 | O40: 0 | P40: 100 | Q40: 1 | R40: Cash | S40: Rahul | T40: kavya.nair@company.com | U40: 9963005771 | V40: Cancelled | W40: =DATEDIF(H40, TODAY(), "y") -> 47 | X40: =IF(OR(ISBLANK(D40), ISBLANK(E40)), "Not Available", E40-D40) -> 6 | Y40: =IF(ISBLANK(E40), "Pending", IF(E40-D40<=5, "On Time ", "Delayed")) -> Delayed
A41: ORD10040 | B41: C010 | C41: P203 | D41: 45935 | E41: 45945 | F41: Pooja Shah | G41: Female | H41: 33773 | I41: Mumbai | J41: West | K41: Home Appliances | L41: Microwave | M41: 20 | N41: 8500 | O41: 0 | P41: 170000 | Q41: 1 | R41: UPI | S41: Neha | T41: pooja.shah@company.com | U41: 9484632635 | V41: Cancelled | W41: =DATEDIF(H41, TODAY(), "y") -> 34 | X41: =IF(OR(ISBLANK(D41), ISBLANK(E41)), "Not Available", E41-D41) -> 10 | Y41: =IF(ISBLANK(E41), "Pending", IF(E41-D41<=5, "On Time ", "Delayed")) -> Delayed
A42: ORD10041 | B42: C007 | C42: P301 | D42: 46063 | E42: 46065 | F42: Arjun Rao | G42: Male | H42: 34491 | I42: Bengaluru | J42: South | K42: Stationery | L42: Notebook | M42: 8 | N42: 60 | O42: 15 | P42: 408 | Q42: 5 | R42: UPI | S42: Rahul | T42: arjun.rao@company.com | U42: 9276319484 | V42: Pending | W42: =DATEDIF(H42, TODAY(), "y") -> 32 | X42: =IF(OR(ISBLANK(D42), ISBLANK(E42)), "Not Available", E42-D42) -> 2 | Y42: =IF(ISBLANK(E42), "Pending", IF(E42-D42<=5, "On Time ", "Delayed")) -> On Time
A43: ORD10042 | B43: C010 | C43: P201 | D43: 45812 | E43: 45824 | F43: Pooja Shah | G43: Female | H43: 32408 | I43: Pune | J43: West | K43: Home Appliances | L43: Mixer | M43: 8 | N43: 3500 | O43: 5 | P43: 26600 | Q43: 1 | R43: Card | S43: Neha | T43: pooja.shah@company.com | U43: 9619034852 | V43: Pending | W43: =DATEDIF(H43, TODAY(), "y") -> 38 | X43: =IF(OR(ISBLANK(D43), ISBLANK(E43)), "Not Available", E43-D43) -> 12 | Y43: =IF(ISBLANK(E43), "Pending", IF(E43-D43<=5, "On Time ", "Delayed")) -> Delayed
A44: ORD10043 | B44: C009 | C44: P203 | D44: 46061 | E44: 46067 | F44: Mohit Verma | G44: Male | H44: 37086 | I44: Jaipur | J44: North | K44: Home Appliances | L44: Microwave | M44: 1 | N44: 8500 | O44: 0 | P44: 8500 | Q44: 2 | R44: Card | S44: Neha | T44: mohit.verma@company.com | U44: 9636416962 | V44: Pending | W44: =DATEDIF(H44, TODAY(), "y") -> 25 | X44: =IF(OR(ISBLANK(D44), ISBLANK(E44)), "Not Available", E44-D44) -> 6 | Y44: =IF(ISBLANK(E44), "Pending", IF(E44-D44<=5, "On Time ", "Delayed")) -> Delayed
A45: ORD10044 | B45: C001 | C45: P303 | D45: 45746 | E45: 45747 | F45: Amit Sharma | G45: Male | H45: 33459 | I45: Pune | J45: West | K45: Stationery | L45: Marker | M45: 8 | N45: 45 | O45: 15 | P45: 306 | Q45: 2 | R45: Card | S45: Aisha | T45: amit.sharma@company.com | U45: 9357133880 | V45: Completed | W45: =DATEDIF(H45, TODAY(), "y") -> 35 | X45: =IF(OR(ISBLANK(D45), ISBLANK(E45)), "Not Available", E45-D45) -> 1 | Y45: =IF(ISBLANK(E45), "Pending", IF(E45-D45<=5, "On Time ", "Delayed")) -> On Time
A46: ORD10045 | B46: C006 | C46: P202 | D46: 45772 | E46: 45775 | F46: Sneha Joshi | G46: Female | H46: 32437 | I46: Pune | J46: West | K46: Home Appliances | L46: Iron | M46: 16 | N46: 2200 | O46: 5 | P46: 33440 | Q46: 5 | R46: Card | S46: Aisha | T46: sneha.joshi@company.com | U46: 9575210324 | V46: Cancelled | W46: =DATEDIF(H46, TODAY(), "y") -> 37 | X46: =IF(OR(ISBLANK(D46), ISBLANK(E46)), "Not Available", E46-D46) -> 3 | Y46: =IF(ISBLANK(E46), "Pending", IF(E46-D46<=5, "On Time ", "Delayed")) -> On Time
A47: ORD10046 | B47: C009 | C47: P201 | D47: 45943 | E47: 45953 | F47: Mohit Verma | G47: Male | H47: 37579 | I47: Bengaluru | J47: South | K47: Home Appliances | L47: Mixer | M47: 19 | N47: 3500 | O47: 20 | P47: 53200 | Q47: 3 | R47: Cash | S47: Karan | T47: mohit.verma@company.com | U47: 9276080204 | V47: Cancelled | W47: =DATEDIF(H47, TODAY(), "y") -> 23 | X47: =IF(OR(ISBLANK(D47), ISBLANK(E47)), "Not Available", E47-D47) -> 10 | Y47: =IF(ISBLANK(E47), "Pending", IF(E47-D47<=5, "On Time ", "Delayed")) -> Delayed
A48: ORD10047 | B48: C006 | C48: P102 | D48: 45941 | E48: 45944 | F48: Sneha Joshi | G48: Female | H48: 36713 | I48: Pune | J48: West | K48: Electronics | L48: Mouse | M48: 15 | N48: 700 | O48: 15 | P48: 8925 | Q48: 4 | R48: UPI | S48: Neha | T48: Invalid Email | U48: 9856624471 | V48: Completed | W48: =DATEDIF(H48, TODAY(), "y") -> 26 | X48: =IF(OR(ISBLANK(D48), ISBLANK(E48)), "Not Available", E48-D48) -> 3 | Y48: =IF(ISBLANK(E48), "Pending", IF(E48-D48<=5, "On Time ", "Delayed")) -> On Time
A49: ORD10048 | B49: C006 | C49: P102 | D49: 45988 | E49: 45994 | F49: Sneha Joshi | G49: Female | H49: 36125 | I49: Jaipur | J49: North | K49: Electronics | L49: Mouse | M49: 19 | N49: 700 | O49: 20 | P49: 10640 | Q49: 1 | R49: Cash | S49: Neha | T49: sneha.joshi@company.com | U49: 9238141322 | V49: Completed | W49: =DATEDIF(H49, TODAY(), "y") -> 27 | X49: =IF(OR(ISBLANK(D49), ISBLANK(E49)), "Not Available", E49-D49) -> 6 | Y49: =IF(ISBLANK(E49), "Pending", IF(E49-D49<=5, "On Time ", "Delayed")) -> Delayed
A50: ORD10049 | B50: C009 | C50: P104 | D50: 46131 | F50: Mohit Verma | G50: Male | H50: 35219 | I50: Delhi | J50: North | K50: Electronics | L50: Monitor | M50: 19 | N50: 12000 | O50: 0 | P50: 228000 | Q50: 1 | R50: NetBanking | S50: Aisha | T50: mohit.verma@company.com | U50: 9890380030 | V50: Completed | W50: =DATEDIF(H50, TODAY(), "y") -> 30 | X50: =IF(OR(ISBLANK(D50), ISBLANK(E50)), "Not Available", E50-D50) -> Not Available | Y50: =IF(ISBLANK(E50), "Pending", IF(E50-D50<=5, "On Time ", "Delayed")) -> Pending
A51: ORD10050 | B51: C004 | C51: P103 | D51: 46131 | E51: 46133 | F51: Anita Gupta | G51: Female | H51: 31851 | I51: Pune | J51: West | K51: Electronics | L51: Keyboard | M51: 6 | N51: 1200 | O51: 5 | P51: 6840 | Q51: 2 | R51: Cash | S51: Ritika | T51: anita.gupta@company.com | U51: 9495893170 | V51: Pending | W51: =DATEDIF(H51, TODAY(), "y") -> 39 | X51: =IF(OR(ISBLANK(D51), ISBLANK(E51)), "Not Available", E51-D51) -> 2 | Y51: =IF(ISBLANK(E51), "Pending", IF(E51-D51<=5, "On Time ", "Delayed")) -> On Time
A52: ORD10051 | B52: C010 | C52: P202 | D52: 45744 | E52: 45754 | F52: Pooja Shah | G52: Female | H52: 28906 | I52: Bengaluru | J52: South | K52: Home Appliances | L52: Iron | M52: 7 | N52: 2200 | O52: 15 | P52: 13090 | Q52: 1 | R52: UPI | S52: Aisha | T52: pooja.shah@company.com | U52: 9485166307 | V52: Completed | W52: =DATEDIF(H52, TODAY(), "y") -> 47 | X52: =IF(OR(ISBLANK(D52), ISBLANK(E52)), "Not Available", E52-D52) -> 10 | Y52: =IF(ISBLANK(E52), "Pending", IF(E52-D52<=5, "On Time ", "Delayed")) -> Delayed
A53: ORD10052 | B53: C002 | C53: P301 | D53: 45894 | E53: 45897 | F53: Priya Patel | G53: Female | H53: 36747 | I53: Jaipur | J53: North | K53: Stationery | L53: Notebook | M53: 8 | N53: 60 | O53: 10 | P53: 432 | Q53: 5 | R53: Card | S53: Aisha | T53: priya.patel@company.com | U53: 9924709648 | V53: Cancelled | W53: =DATEDIF(H53, TODAY(), "y") -> 26 | X53: =IF(OR(ISBLANK(D53), ISBLANK(E53)), "Not Available", E53-D53) -> 3 | Y53: =IF(ISBLANK(E53), "Pending", IF(E53-D53<=5, "On Time ", "Delayed")) -> On Time
A54: ORD10053 | B54: C005 | C54: P101 | D54: 45888 | E54: 45892 | F54: Vikas Mehta | G54: Male | H54: 27776 | I54: Kolkata | J54: East | K54: Electronics | L54: Laptop | M54: 12 | N54: 55000 | O54: 5 | P54: 627000 | Q54: 2 | R54: UPI | S54: Rahul | T54: vikas.mehta@company.com | U54: 9350554626 | V54: Pending | W54: =DATEDIF(H54, TODAY(), "y") -> 50 | X54: =IF(OR(ISBLANK(D54), ISBLANK(E54)), "Not Available", E54-D54) -> 4 | Y54: =IF(ISBLANK(E54), "Pending", IF(E54-D54<=5, "On Time ", "Delayed")) -> On Time
A55: ORD10054 | B55: C008 | C55: P102 | D55: 45865 | E55: 45874 | F55: Kavya Nair | G55: Female | H55: 27488 | I55: Jaipur | J55: North | K55: Electronics | L55: Mouse | M55: 3 | N55: 700 | O55: 0 | P55: 2100 | Q55: 3 | R55: Card | S55: Karan | T55: kavya.nair@company.com | U55: 9743295580 | V55: Cancelled | W55: =DATEDIF(H55, TODAY(), "y") -> 51 | X55: =IF(OR(ISBLANK(D55), ISBLANK(E55)), "Not Available", E55-D55) -> 9 | Y55: =IF(ISBLANK(E55), "Pending", IF(E55-D55<=5, "On Time ", "Delayed")) -> Delayed
A56: ORD10055 | B56: C003 | C56: P301 | D56: 45709 | E56: 45714 | F56: Rohit Singh | G56: Male | H56: 28105 | I56: Ahmedabad | J56: West | K56: Stationery | L56: Notebook | M56: 19 | N56: 60 | O56: 15 | P56: 969 | Q56: 4 | R56: Card | S56: Rahul | T56: rohit.singh@company.com | U56: 9822926495 | V56: Cancelled | W56: =DATEDIF(H56, TODAY(), "y") -> 49 | X56: =IF(OR(ISBLANK(D56), ISBLANK(E56)), "Not Available", E56-D56) -> 5 | Y56: =IF(ISBLANK(E56), "Pending", IF(E56-D56<=5, "On Time ", "Delayed")) -> On Time
A57: ORD10056 | B57: C001 | C57: P301 | D57: 45879 | E57: 45880 | F57: Amit Sharma | G57: Male | H57: 29192 | I57: Jaipur | J57: North | K57: Stationery | L57: Notebook | M57: 9 | N57: 60 | O57: 20 | P57: 432 | Q57: 1 | R57: NetBanking | S57: Neha | T57: amit.sharma@company.com | U57: 9518298190 | V57: Pending | W57: =DATEDIF(H57, TODAY(), "y") -> 46 | X57: =IF(OR(ISBLANK(D57), ISBLANK(E57)), "Not Available", E57-D57) -> 1 | Y57: =IF(ISBLANK(E57), "Pending", IF(E57-D57<=5, "On Time ", "Delayed")) -> On Time
A58: ORD10057 | B58: C001 | C58: P102 | D58: 46105 | E58: 46111 | F58: Amit Sharma | G58: Male | H58: 28851 | I58: Bengaluru | J58: South | K58: Electronics | L58: Mouse | M58: 6 | N58: 700 | O58: 0 | P58: 4200 | Q58: 4 | R58: UPI | S58: Rahul | T58: Invalid Email | U58: 9366223547 | V58: Cancelled | W58: =DATEDIF(H58, TODAY(), "y") -> 47 | X58: =IF(OR(ISBLANK(D58), ISBLANK(E58)), "Not Available", E58-D58) -> 6 | Y58: =IF(ISBLANK(E58), "Pending", IF(E58-D58<=5, "On Time ", "Delayed")) -> Delayed
A59: ORD10058 | B59: C003 | C59: P303 | D59: 46094 | E59: 46100 | F59: Rohit Singh | G59: Male | H59: 27499 | I59: Delhi | J59: North | K59: Stationery | L59: Marker | M59: 18 | N59: 45 | O59: 5 | P59: 769.5 | Q59: 1 | R59: Card | S59: Aisha | T59: rohit.singh@company.com | U59: 9701988524 | V59: Pending | W59: =DATEDIF(H59, TODAY(), "y") -> 51 | X59: =IF(OR(ISBLANK(D59), ISBLANK(E59)), "Not Available", E59-D59) -> 6 | Y59: =IF(ISBLANK(E59), "Pending", IF(E59-D59<=5, "On Time ", "Delayed")) -> Delayed
A60: ORD10059 | B60: C007 | C60: P302 | D60: 45823 | E60: 45834 | F60: Arjun Rao | G60: Male | H60: 32496 | I60: Jaipur | J60: North | K60: Stationery | L60: Pen | M60: 8 | N60: 20 | O60: 5 | P60: 152 | Q60: 1 | R60: Card | S60: Ritika | T60: arjun.rao@company.com | U60: 9836327649 | V60: completed | W60: =DATEDIF(H60, TODAY(), "y") -> 37 | X60: =IF(OR(ISBLANK(D60), ISBLANK(E60)), "Not Available", E60-D60) -> 11 | Y60: =IF(ISBLANK(E60), "Pending", IF(E60-D60<=5, "On Time ", "Delayed")) -> Delayed
A61: ORD10060 | B61: C005 | C61: P102 | D61: 45721 | E61: 45722 | F61: Vikas Mehta | G61: Male | H61: 28921 | I61: Jaipur | J61: North | K61: Electronics | L61: Mouse | M61: 8 | N61: 700 | O61: 10 | P61: 5040 | Q61: 1 | R61: NetBanking | S61: Aisha | T61: vikas.mehta@company.com | U61: 9261800516 | V61: Cancelled | W61: =DATEDIF(H61, TODAY(), "y") -> 47 | X61: =IF(OR(ISBLANK(D61), ISBLANK(E61)), "Not Available", E61-D61) -> 1 | Y61: =IF(ISBLANK(E61), "Pending", IF(E61-D61<=5, "On Time ", "Delayed")) -> On Time
A62: ORD10061 | B62: C008 | C62: P302 | D62: 46121 | E62: 46131 | F62: Kavya Nair | G62: Female | H62: 37972 | I62: Delhi | J62: North | K62: Stationery | L62: Pen | M62: 7 | N62: 20 | O62: 15 | P62: 119 | Q62: 5 | R62: Card | S62: Rahul | T62: kavya.nair@company.com | U62: 9950802015 | V62: Completed | W62: =DATEDIF(H62, TODAY(), "y") -> 22 | X62: =IF(OR(ISBLANK(D62), ISBLANK(E62)), "Not Available", E62-D62) -> 10 | Y62: =IF(ISBLANK(E62), "Pending", IF(E62-D62<=5, "On Time ", "Delayed")) -> Delayed
... A74: ORD10073 | B74: C008 | C74: P103 | D74: 46004 | E74: 46014 | F74: Kavya Nair | G74: Female | H74: 29851 | I74: Jaipur | J74: North | K74: Electronics | L74: Keyboard | M74: 1 | N74: 1200 | O74: 5 | P74: 1140 | Q74: 3 | R74: UPI | S74: Aisha | T74: kavya.nair@company.com | U74: 9808988530 | V74: Cancelled | W74: =DATEDIF(H74, TODAY(), "y") -> 45 | X74: =IF(OR(ISBLANK(D74), ISBLANK(E74)), "Not Available", E74-D74) -> 10 | Y74: =IF(ISBLANK(E74), "Pending", IF(E74-D74<=5, "On Time ", "Delayed")) -> Delayed
A75: ORD10074 | B75: C010 | C75: P202 | D75: 46057 | E75: 46069 | F75: Pooja Shah | G75: Female | H75: 29392 | J75: South | K75: Home Appliances | L75: Iron | M75: 1 | N75: 2200 | O75: 15 | P75: 1870 | Q75: 4 | R75: Card | S75: Aisha | T75: pooja.shah@company.com | U75: 9286410494 | V75: Completed | W75: =DATEDIF(H75, TODAY(), "y") -> 46 | X75: =IF(OR(ISBLANK(D75), ISBLANK(E75)), "Not Available", E75-D75) -> 12 | Y75: =IF(ISBLANK(E75), "Pending", IF(E75-D75<=5, "On Time ", "Delayed")) -> Delayed
A76: ORD10075 | B76: C003 | C76: P103 | D76: 46048 | E76: 46050 | F76: Rohit Singh | G76: Male | H76: 30257 | I76: Pune | J76: West | K76: Electronics | L76: Keyboard | M76: 3 | N76: 1200 | O76: 10 | P76: 3240 | Q76: 5 | R76: Cash | S76: Rahul | T76: rohit.singh@company.com | U76: 9311555196 | V76: Completed | W76: =DATEDIF(H76, TODAY(), "y") -> 43 | X76: =IF(OR(ISBLANK(D76), ISBLANK(E76)), "Not Available", E76-D76) -> 2 | Y76: =IF(ISBLANK(E76), "Pending", IF(E76-D76<=5, "On Time ", "Delayed")) -> On Time
A77: ORD10076 | B77: C008 | C77: P201 | D77: 45835 | E77: 45845 | F77: Kavya Nair | G77: Female | H77: 29230 | I77: Bengaluru | J77: South | K77: Home Appliances | L77: Mixer | M77: 10 | N77: 3500 | O77: 20 | P77: 28000 | Q77: 5 | R77: Card | S77: Ritika | T77: kavya.nair@company.com | U77: 9101810266 | V77: Completed | W77: =DATEDIF(H77, TODAY(), "y") -> 46 | X77: =IF(OR(ISBLANK(D77), ISBLANK(E77)), "Not Available", E77-D77) -> 10 | Y77: =IF(ISBLANK(E77), "Pending", IF(E77-D77<=5, "On Time ", "Delayed")) -> Delayed
A78: ORD10077 | B78: C007 | C78: P102 | D78: 46098 | E78: 46100 | F78: Arjun Rao | G78: Male | H78: 29703 | I78: Delhi | J78: North | K78: Electronics | L78: Mouse | M78: 18 | N78: 700 | O78: 5 | P78: 11970 | Q78: 3 | R78: Card | S78: Neha | T78: arjun.rao@company.com | U78: 9464556593 | V78: Cancelled | W78: =DATEDIF(H78, TODAY(), "y") -> 45 | X78: =IF(OR(ISBLANK(D78), ISBLANK(E78)), "Not Available", E78-D78) -> 2 | Y78: =IF(ISBLANK(E78), "Pending", IF(E78-D78<=5, "On Time ", "Delayed")) -> On Time
A79: ORD10078 | B79: C005 | C79: P102 | D79: 45817 | E79: 45826 | F79: Vikas Mehta | G79: Male | H79: 31118 | I79: Bengaluru | J79: South | K79: Electronics | L79: Mouse | M79: 12 | N79: 700 | O79: 15 | P79: 7140 | Q79: 2 | R79: UPI | S79: Rahul | T79: vikas.mehta@company.com | U79: 9338278358 | V79: Completed | W79: =DATEDIF(H79, TODAY(), "y") -> 41 | X79: =IF(OR(ISBLANK(D79), ISBLANK(E79)), "Not Available", E79-D79) -> 9 | Y79: =IF(ISBLANK(E79), "Pending", IF(E79-D79<=5, "On Time ", "Delayed")) -> Delayed
A80: ORD10079 | B80: C009 | C80: P103 | D80: 45976 | E80: 45977 | F80: Mohit Verma | G80: Male | H80: 36234 | I80: Mumbai | J80: West | K80: Electronics | L80: Keyboard | M80: 8 | N80: 1200 | O80: 0 | P80: 9600 | Q80: 4 | R80: Card | S80: Rahul | T80: mohit.verma@company.com | U80: 9621410770 | V80: Pending | W80: =DATEDIF(H80, TODAY(), "y") -> 27 | X80: =IF(OR(ISBLANK(D80), ISBLANK(E80)), "Not Available", E80-D80) -> 1 | Y80: =IF(ISBLANK(E80), "Pending", IF(E80-D80<=5, "On Time ", "Delayed")) -> On Time
A81: ORD10080 | B81: C003 | C81: P301 | D81: 45967 | E81: 45971 | F81: Rohit Singh | G81: Male | H81: 30504 | I81: Pune | J81: West | K81: Stationery | L81: Notebook | M81: 2 | N81: 60 | O81: 0 | P81: 120 | Q81: 2 | R81: UPI | S81: Rahul | T81: rohit.singh@company.com | U81: 9981333189 | V81: Completed | W81: =DATEDIF(H81, TODAY(), "y") -> 43 | X81: =IF(OR(ISBLANK(D81), ISBLANK(E81)), "Not Available", E81-D81) -> 4 | Y81: =IF(ISBLANK(E81), "Pending", IF(E81-D81<=5, "On Time ", "Delayed")) -> On Time
A82: ORD10081 | B82: C001 | C82: P303 | D82: 45658 | E82: 45664 | F82: Amit Sharma | G82: Male | H82: 32573 | I82: Pune | J82: West | K82: Stationery | L82: Marker | M82: 10 | N82: 45 | O82: 15 | P82: 382.5 | Q82: 3 | R82: NetBanking | S82: Ritika | T82: amit.sharma@company.com | U82: 9723450355 | V82: Cancelled | W82: =DATEDIF(H82, TODAY(), "y") -> 37 | X82: =IF(OR(ISBLANK(D82), ISBLANK(E82)), "Not Available", E82-D82) -> 6 | Y82: =IF(ISBLANK(E82), "Pending", IF(E82-D82<=5, "On Time ", "Delayed")) -> Delayed
A83: ORD10082 | B83: C005 | C83: P201 | D83: 46137 | E83: 46145 | F83: Vikas Mehta | G83: Male | H83: 30122 | I83: Kolkata | J83: East | K83: Home Appliances | L83: Mixer | M83: 12 | N83: 3500 | O83: 5 | P83: 39900 | Q83: 3 | R83: NetBanking | S83: Aisha | T83: vikas.mehta@company.com | U83: 9886243907 | V83: Pending | W83: =DATEDIF(H83, TODAY(), "y") -> 44 | X83: =IF(OR(ISBLANK(D83), ISBLANK(E83)), "Not Available", E83-D83) -> 8 | Y83: =IF(ISBLANK(E83), "Pending", IF(E83-D83<=5, "On Time ", "Delayed")) -> Delayed
A84: ORD10083 | B84: C003 | C84: P301 | D84: 45919 | E84: 45927 | F84: Rohit Singh | G84: Male | H84: 37065 | I84: Mumbai | J84: West | K84: Stationery | L84: Notebook | M84: 2 | N84: 60 | O84: 15 | P84: 102 | Q84: 1 | R84: UPI | S84: Neha | T84: rohit.singh@company.com | U84: 9473931904 | V84: Completed | W84: =DATEDIF(H84, TODAY(), "y") -> 25 | X84: =IF(OR(ISBLANK(D84), ISBLANK(E84)), "Not Available", E84-D84) -> 8 | Y84: =IF(ISBLANK(E84), "Pending", IF(E84-D84<=5, "On Time ", "Delayed")) -> Delayed
A85: ORD10084 | B85: C003 | C85: P103 | D85: 45734 | E85: 45737 | F85: Rohit Singh | G85: Male | H85: 30516 | I85: Hyderabad | J85: South | K85: Electronics | L85: Keyboard | M85: 18 | N85: 1200 | O85: 15 | P85: 18360 | Q85: 3 | R85: Card | S85: Neha | T85: rohit.singh@company.com | U85: 9287159610 | V85: Pending | W85: =DATEDIF(H85, TODAY(), "y") -> 43 | X85: =IF(OR(ISBLANK(D85), ISBLANK(E85)), "Not Available", E85-D85) -> 3 | Y85: =IF(ISBLANK(E85), "Pending", IF(E85-D85<=5, "On Time ", "Delayed")) -> On Time
A86: ORD10085 | B86: C008 | C86: P104 | D86: 45960 | E86: 45961 | F86: Kavya Nair | G86: Female | H86: 34052 | I86: Mumbai | J86: West | K86: Electronics | L86: Monitor | M86: 18 | N86: 12000 | O86: 15 | P86: 183600 | Q86: 2 | R86: Cash | S86: Rahul | T86: kavya.nair@company.com | U86: 9876513858 | V86: Completed | W86: =DATEDIF(H86, TODAY(), "y") -> 33 | X86: =IF(OR(ISBLANK(D86), ISBLANK(E86)), "Not Available", E86-D86) -> 1 | Y86: =IF(ISBLANK(E86), "Pending", IF(E86-D86<=5, "On Time ", "Delayed")) -> On Time
A87: ORD10086 | B87: C007 | C87: P302 | D87: 45961 | E87: 45972 | F87: Arjun Rao | G87: Male | H87: 34829 | I87: Ahmedabad | J87: West | K87: Stationery | L87: Pen | M87: 7 | N87: 20 | O87: 0 | P87: 140 | Q87: 2 | R87: Card | S87: Ritika | T87: arjun.rao@company.com | U87: 9237400853 | V87: Cancelled | W87: =DATEDIF(H87, TODAY(), "y") -> 31 | X87: =IF(OR(ISBLANK(D87), ISBLANK(E87)), "Not Available", E87-D87) -> 11 | Y87: =IF(ISBLANK(E87), "Pending", IF(E87-D87<=5, "On Time ", "Delayed")) -> Delayed
... A119: ORD10118 | B119: C001 | C119: P303 | D119: 45808 | E119: 45819 | F119: Amit Sharma | G119: Male | H119: 34949 | I119: Pune | J119: West | K119: Stationery | L119: Marker | M119: 16 | N119: 45 | O119: 0 | P119: 720 | Q119: 1 | R119: NetBanking | S119: Aisha | T119: amit.sharma@company.com | U119: 9807154421 | V119: Completed | W119: =DATEDIF(H119, TODAY(), "y") -> 31 | X119: =IF(OR(ISBLANK(D119), ISBLANK(E119)), "Not Available", E119-D119) -> 11 | Y119: =IF(ISBLANK(E119), "Pending", IF(E119-D119<=5, "On Time ", "Delayed")) -> Delayed
A120: ORD10119 | B120: C009 | C120: P103 | D120: 45807 | E120: 45810 | F120: Mohit Verma | G120: Male | H120: 32210 | I120: Ahmedabad | J120: West | K120: Electronics | L120: Keyboard | M120: Ten | N120: 1200 | O120: 15 | P120: 7140 | Q120: 4 | R120: UPI | S120: Karan | T120: mohit.verma@company.com | U120: 9919834000 | V120: Pending | W120: =DATEDIF(H120, TODAY(), "y") -> 38 | X120: =IF(OR(ISBLANK(D120), ISBLANK(E120)), "Not Available", E120-D120) -> 3 | Y120: =IF(ISBLANK(E120), "Pending", IF(E120-D120<=5, "On Time ", "Delayed")) -> On Time
A121: ORD10120 | B121: C002 | C121: P104 | D121: 45888 | E121: 45899 | F121: Priya Patel | G121: Female | H121: 32696 | I121: Jaipur | J121: North | K121: Electronics | L121: Monitor | M121: 14 | N121: 12000 | O121: 15 | P121: 142800 | Q121: 2 | R121: NetBanking | S121: Aisha | T121: priya.patel@company.com | U121: 9739798818 | V121: Pending | W121: =DATEDIF(H121, TODAY(), "y") -> 37 | X121: =IF(OR(ISBLANK(D121), ISBLANK(E121)), "Not Available", E121-D121) -> 11 | Y121: =IF(ISBLANK(E121), "Pending", IF(E121-D121<=5, "On Time ", "Delayed")) -> Delayed
A122: ORD10121 | B122: C003 | C122: P203 | D122: 46005 | E122: 46007 | F122: Rohit Singh | G122: Male | H122: 34284 | I122: Pune | J122: West | K122: Home Appliances | L122: Microwave | M122: 8 | N122: 8500 | O122: 20 | P122: 54400 | Q122: 3 | R122: Card | S122: Rahul | T122: rohit.singh@company.com | U122: 9208625306 | V122: Completed | W122: =DATEDIF(H122, TODAY(), "y") -> 32 | X122: =IF(OR(ISBLANK(D122), ISBLANK(E122)), "Not Available", E122-D122) -> 2 | Y122: =IF(ISBLANK(E122), "Pending", IF(E122-D122<=5, "On Time ", "Delayed")) -> On Time
A123: ORD10122 | B123: C007 | C123: P303 | D123: 46053 | E123: 46063 | F123: Arjun Rao | G123: Male | H123: 36557 | I123: Bengaluru | J123: South | K123: Stationery | L123: Marker | M123: 3 | N123: 45 | O123: 0 | P123: 135 | Q123: 4 | R123: UPI | S123: Aisha | T123: arjun.rao@company.com | U123: 9970178536 | V123: Cancelled | W123: =DATEDIF(H123, TODAY(), "y") -> 26 | X123: =IF(OR(ISBLANK(D123), ISBLANK(E123)), "Not Available", E123-D123) -> 10 | Y123: =IF(ISBLANK(E123), "Pending", IF(E123-D123<=5, "On Time ", "Delayed")) -> Delayed
A124: ORD10123 | B124: C001 | C124: P102 | D124: 46025 | E124: 46026 | F124: Amit Sharma | G124: Male | H124: 31585 | I124: Jaipur | J124: North | K124: Electronics | L124: Mouse | M124: 13 | N124: 700 | O124: 5 | P124: 8645 | Q124: 3 | R124: Card | S124: Neha | T124: amit.sharma@company.com | U124: 9633745195 | V124: Pending | W124: =DATEDIF(H124, TODAY(), "y") -> 40 | X124: =IF(OR(ISBLANK(D124), ISBLANK(E124)), "Not Available", E124-D124) -> 1 | Y124: =IF(ISBLANK(E124), "Pending", IF(E124-D124<=5, "On Time ", "Delayed")) -> On Time
A125: ORD10124 | B125: C004 | C125: P103 | D125: 45950 | E125: 45956 | F125: Anita Gupta | G125: Female | H125: 31459 | I125: Mumbai | J125: West | K125: Electronics | L125: Keyboard | M125: 14 | N125: 1200 | O125: 20 | P125: 13440 | Q125: 5 | R125: NetBanking | S125: Aisha | T125: anita.gupta@company.com | U125: 9922102053 | V125: Completed | W125: =DATEDIF(H125, TODAY(), "y") -> 40 | X125: =IF(OR(ISBLANK(D125), ISBLANK(E125)), "Not Available", E125-D125) -> 6 | Y125: =IF(ISBLANK(E125), "Pending", IF(E125-D125<=5, "On Time ", "Delayed")) -> Delayed
A126: ORD10125 | B126: C002 | C126: P303 | D126: 45788 | E126: 45798 | F126: Priya Patel | G126: Female | H126: 33499 | I126: Delhi | J126: North | K126: Stationery | L126: Marker | M126: 2 | N126: 45 | O126: 5 | P126: 85.5 | Q126: 3 | R126: UPI | S126: Ritika | T126: priya.patel@company.com | U126: 9135963930 | V126: Cancelled | W126: =DATEDIF(H126, TODAY(), "y") -> 35 | X126: =IF(OR(ISBLANK(D126), ISBLANK(E126)), "Not Available", E126-D126) -> 10 | Y126: =IF(ISBLANK(E126), "Pending", IF(E126-D126<=5, "On Time ", "Delayed")) -> Delayed
A127: ORD10126 | B127: C004 | C127: P103 | D127: 46024 | E127: 46028 | F127: Anita Gupta | G127: Female | H127: 29590 | I127: Bengaluru | J127: South | K127: Electronics | L127: Keyboard | M127: 2 | N127: 1200 | O127: 20 | P127: 1920 | Q127: 3 | R127: Card | S127: Neha | T127: anita.gupta@company.com | U127: 9429405275 | V127: Completed | W127: =DATEDIF(H127, TODAY(), "y") -> 45 | X127: =IF(OR(ISBLANK(D127), ISBLANK(E127)), "Not Available", E127-D127) -> 4 | Y127: =IF(ISBLANK(E127), "Pending", IF(E127-D127<=5, "On Time ", "Delayed")) -> On Time
A128: ORD10127 | B128: C003 | C128: P101 | D128: 46132 | E128: 46138 | F128: Rohit Singh | G128: Male | H128: 38272 | I128: Bengaluru | J128: South | K128: Electronics | L128: Laptop | M128: 10 | N128: 55000 | O128: 5 | P128: 522500 | Q128: 5 | R128: UPI | S128: Aisha | T128: rohit.singh@company.com | U128: 9521757571 | V128: Pending | W128: =DATEDIF(H128, TODAY(), "y") -> 22 | X128: =IF(OR(ISBLANK(D128), ISBLANK(E128)), "Not Available", E128-D128) -> 6 | Y128: =IF(ISBLANK(E128), "Pending", IF(E128-D128<=5, "On Time ", "Delayed")) -> Delayed
A129: ORD10128 | B129: C006 | C129: P201 | D129: 45873 | E129: 45874 | F129: Sneha Joshi | G129: Female | H129: 30766 | I129: Jaipur | J129: North | K129: Home Appliances | L129: Mixer | M129: 15 | N129: 3500 | O129: 10 | P129: 47250 | Q129: 3 | R129: NetBanking | S129: Neha | T129: sneha.joshi@company.com | U129: 9467375455 | V129: Completed | W129: =DATEDIF(H129, TODAY(), "y") -> 42 | X129: =IF(OR(ISBLANK(D129), ISBLANK(E129)), "Not Available", E129-D129) -> 1 | Y129: =IF(ISBLANK(E129), "Pending", IF(E129-D129<=5, "On Time ", "Delayed")) -> On Time
A130: ORD10129 | B130: C002 | C130: P202 | D130: 45882 | E130: 45887 | F130: Priya Patel | G130: Female | H130: 30203 | I130: Bengaluru | J130: South | K130: Home Appliances | L130: Iron | M130: 10 | N130: 2200 | O130: 15 | P130: 18700 | Q130: 4 | R130: Card | S130: Rahul | T130: priya.patel@company.com | U130: 9838809695 | V130: Pending | W130: =DATEDIF(H130, TODAY(), "y") -> 44 | X130: =IF(OR(ISBLANK(D130), ISBLANK(E130)), "Not Available", E130-D130) -> 5 | Y130: =IF(ISBLANK(E130), "Pending", IF(E130-D130<=5, "On Time ", "Delayed")) -> On Time
A131: ORD10130 | B131: C006 | C131: P201 | D131: 45824 | E131: 45832 | F131: Sneha Joshi | G131: Female | H131: 34015 | I131: Pune | J131: West | K131: Home Appliances | L131: Mixer | M131: 11 | N131: 3500 | O131: 5 | P131: 36575 | Q131: 5 | R131: Cash | S131: Ritika | T131: sneha.joshi@company.com | U131: 9296609782 | V131: Cancelled | W131: =DATEDIF(H131, TODAY(), "y") -> 33 | X131: =IF(OR(ISBLANK(D131), ISBLANK(E131)), "Not Available", E131-D131) -> 8 | Y131: =IF(ISBLANK(E131), "Pending", IF(E131-D131<=5, "On Time ", "Delayed")) -> Delayed
A132: ORD10131 | B132: C004 | C132: P103 | D132: 46139 | E132: 46142 | F132: Anita Gupta | G132: Female | H132: 37719 | I132: Bengaluru | J132: South | K132: Electronics | L132: Keyboard | M132: 14 | N132: 1200 | O132: 0 | P132: 16800 | Q132: 5 | R132: Cash | S132: Rahul | T132: anita.gupta@company.com | U132: 9848259992 | V132: Cancelled | W132: =DATEDIF(H132, TODAY(), "y") -> 23 | X132: =IF(OR(ISBLANK(D132), ISBLANK(E132)), "Not Available", E132-D132) -> 3 | Y132: =IF(ISBLANK(E132), "Pending", IF(E132-D132<=5, "On Time ", "Delayed")) -> On Time
... A299: ORD10298 | B299: C003 | C299: P101 | D299: 45670 | E299: 45673 | F299: Rohit Singh | G299: Male | H299: 37989 | I299: Hyderabad | J299: South | K299: Electronics | L299: Laptop | M299: 11 | N299: 55000 | O299: 5 | P299: 574750 | Q299: 1 | R299: UPI | S299: Ritika | T299: rohit.singh@company.com | U299: 9482699727 | V299: Cancelled | W299: =DATEDIF(H299, TODAY(), "y") -> 22 | X299: =IF(OR(ISBLANK(D299), ISBLANK(E299)), "Not Available", E299-D299) -> 3 | Y299: =IF(ISBLANK(E299), "Pending", IF(E299-D299<=5, "On Time ", "Delayed")) -> On Time
A300: ORD10299 | B300: C007 | C300: P201 | D300: 45935 | E300: 45947 | F300: Arjun Rao | G300: Male | H300: 33726 | I300: Jaipur | J300: North | K300: Home Appliances | L300: Mixer | M300: 12 | N300: 3500 | O300: 0 | P300: 42000 | Q300: 2 | R300: NetBanking | T300: arjun.rao@company.com | U300: 9332473934 | V300: Pending | W300: =DATEDIF(H300, TODAY(), "y") -> 34 | X300: =IF(OR(ISBLANK(D300), ISBLANK(E300)), "Not Available", E300-D300) -> 12 | Y300: =IF(ISBLANK(E300), "Pending", IF(E300-D300<=5, "On Time ", "Delayed")) -> Delayed
A301: ORD10300 | B301: C009 | C301: P303 | D301: 46078 | E301: 46089 | F301: Mohit Verma | G301: Male | H301: 37647 | I301: Hyderabad | J301: South | K301: Stationery | L301: Marker | M301: 15 | N301: 45 | O301: 10 | P301: 607.5 | Q301: 2 | R301: Cash | S301: Karan | T301: mohit.verma@company.com | U301: 9647657382 | V301: Pending | W301: =DATEDIF(H301, TODAY(), "y") -> 23 | X301: =IF(OR(ISBLANK(D301), ISBLANK(E301)), "Not Available", E301-D301) -> 11 | Y301: =IF(ISBLANK(E301), "Pending", IF(E301-D301<=5, "On Time ", "Delayed")) -> Delayed
A302: ORD10301 | B302: C001 | C302: P303 | D302: 45793 | E302: 45803 | F302: Amit Sharma | G302: Male | H302: 31917 | I302: Bengaluru | J302: South | K302: Stationery | L302: Marker | M302: 13 | N302: 45 | O302: 0 | P302: 585 | Q302: 5 | R302: NetBanking | S302: Rahul | T302: amit.sharma@company.com | U302: 9736797776 | V302: Pending | W302: =DATEDIF(H302, TODAY(), "y") -> 39 | X302: =IF(OR(ISBLANK(D302), ISBLANK(E302)), "Not Available", E302-D302) -> 10 | Y302: =IF(ISBLANK(E302), "Pending", IF(E302-D302<=5, "On Time ", "Delayed")) -> Delayed
A303: ORD10302 | B303: C003 | C303: P101 | D303: 46024 | E303: 46027 | F303: Rohit Singh | G303: Male | H303: 27644 | I303: Bengaluru | J303: South | K303: Electronics | L303: Laptop | M303: 8 | N303: 55000 | O303: 0 | P303: 440000 | Q303: 2 | R303: UPI | S303: Karan | T303: rohit.singh@company.com | U303: 9745773533 | V303: Cancelled | W303: =DATEDIF(H303, TODAY(), "y") -> 51 | X303: =IF(OR(ISBLANK(D303), ISBLANK(E303)), "Not Available", E303-D303) -> 3 | Y303: =IF(ISBLANK(E303), "Pending", IF(E303-D303<=5, "On Time ", "Delayed")) -> On Time
A304: ORD10303 | B304: C006 | C304: P101 | D304: 45861 | E304: 45865 | F304: Sneha Joshi | G304: Female | H304: 29443 | I304: Delhi | J304: North | K304: Electronics | L304: Laptop | M304: 4 | N304: 55000 | O304: 20 | P304: 176000 | Q304: 5 | R304: Cash | S304: Rahul | T304: sneha.joshi@company.com | U304: 9246715757 | V304: Pending | W304: =DATEDIF(H304, TODAY(), "y") -> 46 | X304: =IF(OR(ISBLANK(D304), ISBLANK(E304)), "Not Available", E304-D304) -> 4 | Y304: =IF(ISBLANK(E304), "Pending", IF(E304-D304<=5, "On Time ", "Delayed")) -> On Time
A305: ORD10304 | B305: C008 | C305: P201 | D305: 46135 | E305: 46138 | F305: Kavya Nair | G305: Female | H305: 32605 | I305: Ahmedabad | J305: West | K305: Home Appliances | L305: Mixer | M305: 19 | N305: 3500 | O305: 5 | P305: 63175 | Q305: 1 | R305: Card | S305: Neha | T305: kavya.nair@company.com | U305: 9904065774 | V305: Completed | W305: =DATEDIF(H305, TODAY(), "y") -> 37 | X305: =IF(OR(ISBLANK(D305), ISBLANK(E305)), "Not Available", E305-D305) -> 3 | Y305: =IF(ISBLANK(E305), "Pending", IF(E305-D305<=5, "On Time ", "Delayed")) -> On Time
A306: ORD10305 | B306: C005 | C306: P103 | D306: 45718 | E306: 45722 | F306: Vikas Mehta | G306: Male | H306: 36027 | I306: Jaipur | J306: North | K306: Electronics | L306: Keyboard | M306: 17 | N306: 1200 | O306: 15 | P306: 17340 | Q306: 2 | R306: NetBanking | S306: Rahul | T306: vikas.mehta@company.com | U306: 9652985385 | V306: Completed | W306: =DATEDIF(H306, TODAY(), "y") -> 28 | X306: =IF(OR(ISBLANK(D306), ISBLANK(E306)), "Not Available", E306-D306) -> 4 | Y306: =IF(ISBLANK(E306), "Pending", IF(E306-D306<=5, "On Time ", "Delayed")) -> On Time
A307: ORD10306 | B307: C008 | C307: P202 | D307: 46062 | E307: 46070 | F307: Kavya Nair | G307: Female | H307: 36984 | I307: Hyderabad | J307: South | K307: Home Appliances | L307: Iron | M307: 8 | N307: 2200 | O307: 5 | P307: 16720 | Q307: 3 | R307: Card | S307: Neha | T307: kavya.nair@company.com | U307: 9427001508 | V307: Pending | W307: =DATEDIF(H307, TODAY(), "y") -> 25 | X307: =IF(OR(ISBLANK(D307), ISBLANK(E307)), "Not Available", E307-D307) -> 8 | Y307: =IF(ISBLANK(E307), "Pending", IF(E307-D307<=5, "On Time ", "Delayed")) -> Delayed
A308: ORD10307 | B308: C006 | C308: P102 | D308: 45704 | E308: 45714 | F308: Sneha Joshi | G308: Female | H308: 33668 | I308: Mumbai | J308: West | K308: Electronics | L308: Mouse | M308: 17 | N308: 700 | O308: 20 | P308: 9520 | Q308: 4 | R308: NetBanking | S308: Neha | T308: sneha.joshi@company.com | U308: 9666803655 | V308: Completed | W308: =DATEDIF(H308, TODAY(), "y") -> 34 | X308: =IF(OR(ISBLANK(D308), ISBLANK(E308)), "Not Available", E308-D308) -> 10 | Y308: =IF(ISBLANK(E308), "Pending", IF(E308-D308<=5, "On Time ", "Delayed")) -> Delayed
A309: ORD10308 | B309: C006 | C309: P203 | D309: 45897 | E309: 45908 | F309: Sneha Joshi | G309: Female | H309: 28122 | I309: Pune | J309: West | K309: Home Appliances | L309: Microwave | M309: 6 | N309: 8500 | O309: 15 | P309: 43350 | Q309: 1 | R309: Cash | S309: Aisha | T309: sneha.joshi@company.com | U309: 9134878547 | V309: Completed | W309: =DATEDIF(H309, TODAY(), "y") -> 49 | X309: =IF(OR(ISBLANK(D309), ISBLANK(E309)), "Not Available", E309-D309) -> 11 | Y309: =IF(ISBLANK(E309), "Pending", IF(E309-D309<=5, "On Time ", "Delayed")) -> Delayed
A310: ORD10309 | B310: C010 | C310: P201 | D310: 45936 | E310: 45941 | F310: Pooja Shah | G310: Female | H310: 31659 | I310: Hyderabad | J310: South | K310: Home Appliances | L310: Mixer | M310: 3 | N310: 3500 | O310: 10 | P310: 9450 | Q310: 1 | R310: NetBanking | S310: Rahul | T310: pooja.shah@company.com | U310: 9253593557 | V310: Completed | W310: =DATEDIF(H310, TODAY(), "y") -> 40 | X310: =IF(OR(ISBLANK(D310), ISBLANK(E310)), "Not Available", E310-D310) -> 5 | Y310: =IF(ISBLANK(E310), "Pending", IF(E310-D310<=5, "On Time ", "Delayed")) -> On Time
A311: ORD10310 | B311: C009 | C311: P104 | D311: 45674 | E311: 45686 | F311: Mohit Verma | G311: Male | H311: 32734 | I311: Ahmedabad | J311: West | K311: Electronics | L311: Monitor | M311: 2 | N311: 12000 | O311: 20 | P311: 19200 | Q311: 1 | R311: Card | S311: Aisha | T311: mohit.verma@company.com | U311: 9183094051 | V311: Completed | W311: =DATEDIF(H311, TODAY(), "y") -> 37 | X311: =IF(OR(ISBLANK(D311), ISBLANK(E311)), "Not Available", E311-D311) -> 12 | Y311: =IF(ISBLANK(E311), "Pending", IF(E311-D311<=5, "On Time ", "Delayed")) -> Delayed
A312: ORD10311 | B312: C005 | C312: P302 | D312: 45943 | E312: 45946 | F312: Vikas Mehta | G312: Male | H312: 33299 | I312: Delhi | J312: North | K312: Stationery | L312: Pen | M312: 12 | N312: 20 | O312: 20 | P312: 192 | Q312: 2 | R312: Card | S312: Rahul | T312: vikas.mehta@company.com | U312: 9293147620 | V312: Completed | W312: =DATEDIF(H312, TODAY(), "y") -> 35 | X312: =IF(OR(ISBLANK(D312), ISBLANK(E312)), "Not Available", E312-D312) -> 3 | Y312: =IF(ISBLANK(E312), "Pending", IF(E312-D312<=5, "On Time ", "Delayed")) -> On Time
... A357: ORD10356 | B357: C008 | C357: P303 | D357: 45941 | E357: 45951 | F357: Kavya Nair | G357: Female | H357: 33746 | I357: Jaipur | J357: North | K357: Stationery | L357: Marker | M357: 5 | N357: 45 | O357: 5 | P357: 213.75 | Q357: 1 | R357: Card | S357: Neha | T357: kavya.nair@company.com | U357: 9810433484 | V357: Completed | W357: =DATEDIF(H357, TODAY(), "y") -> 34 | X357: =IF(OR(ISBLANK(D357), ISBLANK(E357)), "Not Available", E357-D357) -> 10 | Y357: =IF(ISBLANK(E357), "Pending", IF(E357-D357<=5, "On Time ", "Delayed")) -> Delayed
A358: ORD10357 | B358: C006 | C358: P102 | E358: 45699 | F358: Sneha Joshi | G358: Female | H358: 32822 | I358: Mumbai | J358: West | K358: Electronics | L358: Mouse | M358: 3 | N358: 700 | O358: 15 | P358: 1785 | Q358: 4 | R358: Cash | S358: Karan | T358: sneha.joshi@company.com | U358: 9990243436 | V358: Completed | W358: =DATEDIF(H358, TODAY(), "y") -> 36 | X358: =IF(OR(ISBLANK(D358), ISBLANK(E358)), "Not Available", E358-D358) -> Not Available | Y358: =IF(ISBLANK(E358), "Pending", IF(E358-D358<=5, "On Time ", "Delayed")) -> Delayed
A359: ORD10358 | B359: C009 | C359: P203 | D359: 46005 | E359: 46017 | F359: Mohit Verma | G359: Male | H359: 29467 | I359: Jaipur | J359: North | K359: Home Appliances | L359: Microwave | M359: 12 | N359: 8500 | O359: 5 | P359: 96900 | Q359: 3 | R359: Card | S359: Aisha | T359: mohit.verma@company.com | U359: 9396678031 | V359: Pending | W359: =DATEDIF(H359, TODAY(), "y") -> 46 | X359: =IF(OR(ISBLANK(D359), ISBLANK(E359)), "Not Available", E359-D359) -> 12 | Y359: =IF(ISBLANK(E359), "Pending", IF(E359-D359<=5, "On Time ", "Delayed")) -> Delayed
A360: ORD10359 | B360: C006 | C360: P203 | D360: 46123 | E360: 46131 | F360: Sneha Joshi | G360: Female | H360: 28920 | I360: Pune | J360: West | K360: Home Appliances | L360: Microwave | M360: 4 | N360: 8500 | O360: 15 | P360: 28900 | Q360: 4 | R360: NetBanking | S360: Aisha | T360: sneha.joshi@company.com | U360: 9818591245 | V360: Pending | W360: =DATEDIF(H360, TODAY(), "y") -> 47 | X360: =IF(OR(ISBLANK(D360), ISBLANK(E360)), "Not Available", E360-D360) -> 8 | Y360: =IF(ISBLANK(E360), "Pending", IF(E360-D360<=5, "On Time ", "Delayed")) -> Delayed
A361: ORD10360 | B361: C003 | C361: P302 | D361: 45766 | E361: 45769 | F361: Rohit Singh | G361: Male | H361: 35312 | I361: Jaipur | J361: North | K361: Stationery | L361: Pen | M361: 16 | N361: 20 | O361: 10 | P361: 288 | Q361: 4 | R361: Cash | S361: Neha | T361: rohit.singh@company.com | U361: 9505550047 | V361: Cancelled | W361: =DATEDIF(H361, TODAY(), "y") -> 30 | X361: =IF(OR(ISBLANK(D361), ISBLANK(E361)), "Not Available", E361-D361) -> 3 | Y361: =IF(ISBLANK(E361), "Pending", IF(E361-D361<=5, "On Time ", "Delayed")) -> On Time
A362: ORD10361 | B362: C003 | C362: P301 | D362: 46152 | E362: 46160 | F362: Rohit Singh | G362: Male | H362: 36233 | I362: Mumbai | J362: West | K362: Stationery | L362: Notebook | M362: 3 | N362: 60 | O362: 20 | P362: 144 | Q362: 4 | R362: UPI | S362: Karan | T362: rohit.singh@company.com | U362: 9469828772 | V362: Pending | W362: =DATEDIF(H362, TODAY(), "y") -> 27 | X362: =IF(OR(ISBLANK(D362), ISBLANK(E362)), "Not Available", E362-D362) -> 8 | Y362: =IF(ISBLANK(E362), "Pending", IF(E362-D362<=5, "On Time ", "Delayed")) -> Delayed
A363: ORD10362 | B363: C009 | C363: P202 | D363: 45858 | E363: 45864 | F363: Mohit Verma | G363: Male | H363: 30958 | I363: Mumbai | J363: West | K363: Home Appliances | L363: Iron | M363: 19 | N363: 2200 | O363: 10 | P363: 37620 | Q363: 2 | R363: Cash | S363: Karan | T363: mohit.verma@company.com | U363: 9885092680 | V363: Pending | W363: =DATEDIF(H363, TODAY(), "y") -> 42 | X363: =IF(OR(ISBLANK(D363), ISBLANK(E363)), "Not Available", E363-D363) -> 6 | Y363: =IF(ISBLANK(E363), "Pending", IF(E363-D363<=5, "On Time ", "Delayed")) -> Delayed
A364: ORD10363 | B364: C009 | C364: P103 | D364: 46045 | E364: 46049 | F364: Mohit Verma | G364: Male | H364: 30872 | I364: Hyderabad | J364: South | K364: Electronics | L364: Keyboard | M364: 7 | N364: 1200 | O364: 20 | P364: 6720 | Q364: 3 | R364: Card | S364: Neha | T364: mohit.verma@company.com | U364: 9362319457 | V364: Cancelled | W364: =DATEDIF(H364, TODAY(), "y") -> 42 | X364: =IF(OR(ISBLANK(D364), ISBLANK(E364)), "Not Available", E364-D364) -> 4 | Y364: =IF(ISBLANK(E364), "Pending", IF(E364-D364<=5, "On Time ", "Delayed")) -> On Time
A365: ORD10364 | B365: C010 | C365: P302 | D365: 46097 | E365: 46102 | F365: Pooja Shah | G365: Female | H365: 32577 | I365: Bengaluru | J365: South | K365: Stationery | L365: Pen | M365: 20 | N365: 20 | O365: 20 | P365: 320 | Q365: 5 | R365: Card | S365: Neha | T365: pooja.shah@company.com | U365: 9223945130 | V365: Pending | W365: =DATEDIF(H365, TODAY(), "y") -> 37 | X365: =IF(OR(ISBLANK(D365), ISBLANK(E365)), "Not Available", E365-D365) -> 5 | Y365: =IF(ISBLANK(E365), "Pending", IF(E365-D365<=5, "On Time ", "Delayed")) -> On Time
A366: ORD10365 | B366: C002 | C366: P103 | D366: 45777 | E366: 45784 | F366: Priya Patel | G366: Female | H366: 31156 | I366: Hyderabad | J366: South | K366: Electronics | L366: Keyboard | M366: 19 | N366: 1200 | O366: 5 | P366: 21660 | Q366: 3 | R366: Card | S366: Ritika | T366: priya.patel@company.com | U366: 9910804926 | V366: Pending | W366: =DATEDIF(H366, TODAY(), "y") -> 41 | X366: =IF(OR(ISBLANK(D366), ISBLANK(E366)), "Not Available", E366-D366) -> 7 | Y366: =IF(ISBLANK(E366), "Pending", IF(E366-D366<=5, "On Time ", "Delayed")) -> Delayed
A367: ORD10366 | B367: C010 | C367: P302 | D367: 45691 | E367: 45701 | F367: Pooja Shah | G367: Female | H367: 37846 | I367: Hyderabad | J367: South | K367: Stationery | L367: Pen | M367: 5 | N367: 20 | O367: 0 | P367: 100 | Q367: 2 | R367: UPI | S367: Rahul | T367: pooja.shah@company.com | U367: 9274269744 | V367: Pending | W367: =DATEDIF(H367, TODAY(), "y") -> 23 | X367: =IF(OR(ISBLANK(D367), ISBLANK(E367)), "Not Available", E367-D367) -> 10 | Y367: =IF(ISBLANK(E367), "Pending", IF(E367-D367<=5, "On Time ", "Delayed")) -> Delayed
A368: ORD10367 | B368: C002 | C368: P303 | D368: 46088 | E368: 46097 | F368: Priya Patel | G368: Female | H368: 30570 | I368: Jaipur | J368: North | K368: Stationery | L368: Marker | M368: 16 | N368: 45 | O368: 15 | P368: 612 | Q368: 5 | R368: Cash | S368: Aisha | T368: priya.patel@company.com | U368: 9223196101 | V368: Cancelled | W368: =DATEDIF(H368, TODAY(), "y") -> 43 | X368: =IF(OR(ISBLANK(D368), ISBLANK(E368)), "Not Available", E368-D368) -> 9 | Y368: =IF(ISBLANK(E368), "Pending", IF(E368-D368<=5, "On Time ", "Delayed")) -> Delayed
A369: ORD10368 | B369: C008 | C369: P202 | D369: 45780 | E369: 45792 | F369: Kavya Nair | G369: Female | H369: 27922 | I369: Jaipur | J369: North | K369: Home Appliances | L369: Iron | M369: 1 | N369: 2200 | O369: 10 | P369: 1980 | Q369: 5 | R369: Card | S369: Rahul | T369: kavya.nair@company.com | U369: 9888477457 | V369: Completed | W369: =DATEDIF(H369, TODAY(), "y") -> 50 | X369: =IF(OR(ISBLANK(D369), ISBLANK(E369)), "Not Available", E369-D369) -> 12 | Y369: =IF(ISBLANK(E369), "Pending", IF(E369-D369<=5, "On Time ", "Delayed")) -> Delayed
A370: ORD10369 | B370: C010 | C370: P301 | D370: 46113 | E370: 46117 | F370: Pooja Shah | G370: Female | H370: 31781 | I370: Hyderabad | J370: South | K370: Stationery | L370: Notebook | M370: 19 | N370: 60 | O370: 15 | P370: 969 | Q370: 4 | R370: NetBanking | S370: Neha | T370: pooja.shah@company.com | U370: 9435947486 | V370: Cancelled | W370: =DATEDIF(H370, TODAY(), "y") -> 39 | X370: =IF(OR(ISBLANK(D370), ISBLANK(E370)), "Not Available", E370-D370) -> 4 | Y370: =IF(ISBLANK(E370), "Pending", IF(E370-D370<=5, "On Time ", "Delayed")) -> On Time
...

Sheet Product_Lookup_Report
B2: Interactive Product Lookup System
B4: Enter Product ID: | E4: P101
B7: Details | D7: Information
B8: Product Name | D8: =IFERROR(_xlfn.XLOOKUP($E$4,Sales_data!C:C,Sales_data!L:L), "Product Not Found") -> Laptop
B9: Category | D9: =IFERROR(_xlfn.XLOOKUP($E$4,Product_master!A:A,Product_master!C:C),"Product Not Found") -> Electronics
B10: Supplier | D10: =IFERROR(VLOOKUP($E$4,Product_master!$A$1:$F$11, 4, FALSE), "Product Not Found" ) -> TechHub
B11: Cost Price | D11: =IFERROR(VLOOKUP($E$4,Product_master!A1:F11,5,FALSE), "Product Not Found") -> 41250
B12: Warranty (Months) | D12: =IFERROR(_xlfn.XLOOKUP($E$4,Product_master!A:A,Product_master!F:F), "Product Not Found") -> 12

Sheet Sales Summary Report
B1: Sales Performance Summary Report
B3: Description | E3: Performance Value
B4: Electronics Sales (Completed Orders) | E4: =SUMIFS(Sales_data!P:P,Sales_data!K:K,"Electronics",Sales_data!V:V,"Completed") -> 7222090
B5: Salesperson Neha Sales (North Region) | E5: =SUMIFS(Sales_data!P:P,Sales_data!S:S, "Neha",Sales_data!J:J,"North") -> 1550369.2
B6: Orders with 15%+ Discount & UPI Payment | E6: =COUNTIFS(Sales_data!O:O,">=15",Sales_data!R:R, "UPI") -> 45
B7: Completed Orders with 5-Star Rating | E7: =COUNTIFS(Sales_data!Q:Q,"=5",Sales_data!V:V,"Completed") -> 27
B8: Average Sales (West Region, Qty > 5) | E8: =AVERAGEIFS(Sales_data!P:P,Sales_data!J:J,"West",Sales_data!M:M, ">5") -> 82824.451

Sheet Sales Statistics Report
C2: Sales Statistics Report
B3: Statistical Metric | F3: Value
B4: Average Sales Amount. | F4: =AVERAGE(Sales_data!P:P) -> 69531.875
B5: Median Sales Amount. | F5: =MEDIAN(Sales_data!P:P) -> 10475
B6: Highest Sales Amount | F6: =MAX(Sales_data!P2:P501) -> 1045000
B7: Lowest Sales Amount | F7: =MIN(Sales_data!P2:P501) -> 19
B8: Standard Deviation | F8: =_xlfn.STDEV.S(Sales_data!P2:P501) -> 167151.45
B9: 90th Percentile | F9: =_xlfn.PERCENTILE.INC(Sales_data!P:P, 0.9) -> 163880
B11: Note: The 90th percentile value (₹163,880.00) indicates that 90% of the company's
B12: orders are less than or equal to this amount, and only 10% of orders exceed it.

Sheet Product Performance
B1: Product Performance Report
B2: Description | F2: Amount
B3: Calculated Total Revenue | F3: =SUMPRODUCT(Sales_data!M:M, Sales_data!N:N) -> 36604875
B4: Weighted Average Unit Price | F4: =SUMPRODUCT(Sales_data!N:N, Sales_data!M:M) / SUM(Sales_data!M:M) -> 6989.6649
B5: Revenue Difference Check | F5: =SUM(Sales_data!P:P)- F3 -> -1838937.5
B6: Total Discounted Amount | F6: =SUMPRODUCT('Q1'!M:M,'Q1'!N:N,'Q1'!O:O)/100 -> 2919951.5

Sheet Financial Analysis Report
A1: Financial Investment & Loan Analysis Report
A4: Description Column | D4: Calculated Values Column
A5: Future Value of Investment | D5: =ROUND(FV(10%/12, 5*12, -50000, 0), 2) -> 3871853.6
A6: Monthly Investment Required for Target | D6: =ROUND(PMT(10%/12, 5*12, 0, -5000000), 2) -> 64568.56
A7: Monthly Loan EMI | D7: =ROUND(PMT(9%/12, 12*5, -1000000 ), 0) -> 20758

Sheet Cleaned_Data
A1: Order_ID | B1: Customer_ID | C1: Product_ID | D1: Order_Date | E1: Delivery_Date | F1: Customer_Name | G1: Gender | H1: DOB | I1: City | J1: Region | K1: Category | L1: Product_Name | M1: Quantity | N1: Unit_Price | O1: Discount_% | P1: Sales | Q1: Rating | R1: Cash | S1: Salesperson | T1: Email | U1: Phone | V1: Order_Status | AQ1: Dashboard_Order_Date
A2: ORD10001 | B2: C008 | C2: P202 | D2: 45918 | E2: 22/09/2025 | F2: Kavya Nair | G2: Female | H2: 01/08/1976 | I2: Hyderabad | J2: South | K2: Home Appliances | L2: Iron | M2: 4 | N2: 2200 | O2: 0.1 | P2: 7920 | Q2: 4 | R2: Cash | S2: Ritika | T2: kavya.nair@company.com | U2: 9431429797 | V2: Completed | AQ2: 45918
A3: ORD10002 | B3: C008 | C3: P104 | D3: 45774 | E3: 04/05/2025 | F3: Kavya Nair | G3: Female | H3: 16/10/2000 | I3: Delhi | J3: North | K3: Electronics | L3: Monitor | M3: 17 | N3: 12000 | O3: 0.1 | P3: 183600 | Q3: 1 | R3: NetBanking | S3: Rahul | T3: kavya.nair@company.com | U3: 9129865339 | V3: Completed | AQ3: 45774
A4: ORD10003 | B4: C010 | C4: P101 | D4: 45903 | E4: 14/09/2025 | F4: Pooja Shah | G4: Female | H4: 16/09/1994 | I4: Bengaluru | J4: South | K4: Electronics | L4: Laptop | M4: 5 | N4: 55000 | O4: 0.05 | P4: 261250 | Q4: 3 | R4: NetBanking | S4: Aisha | T4: pooja.shah@company.com | U4: 9380975626 | V4: Pending | AQ4: 45725
A5: ORD10002 | B5: C008 | C5: P202 | D5: 46102 | E5: 02/04/2026 | F5: Kavya Nair | G5: Female | H5: 07/03/2004 | I5: Bengaluru | J5: South | K5: Home Appliances | L5: Iron | M5: 5 | N5: 2200 | O5: 0.05 | P5: 10450 | Q5: 5 | R5: NetBanking | S5: Aisha | T5: kavya.nair@company.com | U5: 9600261125 | V5: Cancelled | AQ5: 46102
A6: ORD10005 | B6: C009 | C6: P103 | D6: 45927 | E6: 07/10/2025 | F6: Mohit Verma | G6: Male | H6: 13/04/1976 | I6: Delhi | J6: North | K6: Electronics | L6: Keyboard | M6: 8 | N6: 1200 | O6: 0.05 | P6: 9120 | Q6: 2 | R6: Card | S6: Aisha | T6: mohit.verma@company.com | U6: 9724635978 | V6: Pending | AQ6: 45927
A7: ORD10006 | B7: C007 | C7: P202 | D7: 46026 | E7: 12/01/2026 | F7: Arjun Rao | G7: Male | H7: 07/02/1988 | I7: Hyderabad | J7: South | K7: Home Appliances | L7: Iron | M7: 4 | N7: 2200 | O7: 0 | P7: 8800 | Q7: 1 | R7: UPI | S7: Ritika | T7: arjun.rao@company.com | U7: 9780584905 | V7: Completed | AQ7: 46113
A8: ORD10007 | B8: C008 | C8: P201 | D8: 28/02/2025 | E8: 46078 | F8: Kavya Nair | G8: Female | H8: 20/03/2003 | I8: Hyderabad | J8: South | K8: Home Appliances | L8: Mixer | M8: 2 | N8: 3500 | O8: 0.05 | P8: 6650 | Q8: 1 | R8: UPI | S8: Ritika | T8: kavya.nair@company.com | U8: 9958252176 | V8: Completed | AQ8: 45716
A9: ORD10008 | B9: C002 | C9: P104 | D9: 45760 | E9: 19/04/2025 | F9: Priya Patel | G9: Female | H9: 07/03/1995 | I9: Mumbai | J9: West | K9: Electronics | L9: Monitor | M9: 14 | N9: 12000 | O9: 0.15 | P9: 142800 | Q9: 4 | R9: NetBanking | S9: Ritika | T9: priya.patel@company.com | U9: 9705521654 | V9: Completed | AQ9: 45760
A10: ORD10009 | B10: C008 | C10: P104 | D10: 46053 | E10: 02/02/2026 | F10: Kavya Nair | G10: Female | H10: 06/04/1997 | I10: Pune | J10: West | K10: Electronics | L10: Monitor | M10: 4 | N10: 12000 | O10: 0.15 | P10: 40800 | Q10: 4 | R10: UPI | S10: Neha | T10: kavya.nair@company.com | U10: 9588041011 | V10: Completed | AQ10: 46053
A11: ORD10010 | B11: C002 | C11: P301 | D11: 45741 | E11: 27/03/2025 | F11: Priya Patel | G11: Female | H11: 07/01/1990 | I11: Mumbai | J11: West | K11: Stationery | L11: Notebook | M11: 6 | N11: 60 | O11: 0 | P11: 360 | Q11: 4 | R11: Card | S11: Neha | T11: priya.patel@company.com | U11: 9340540608 | V11: Completed | AQ11: 45741
A12: ORD10011 | B12: C003 | C12: P202 | D12: 45919 | E12: 23/09/2025 | F12: Rohit Singh | G12: Male | H12: 10/05/1982 | I12: Delhi | J12: North | K12: Home Appliances | L12: Iron | M12: 3 | N12: 2200 | O12: 0 | P12: 35200 | Q12: 2 | R12: Card | S12: Rahul | T12: rohit.singh@company.com | U12: 9521710321 | V12: Pending | AQ12: 45919
A13: ORD10012 | B13: C008 | C13: P201 | D13: 45724 | E13: 15/03/2025 | F13: Kavya Nair | G13: Female | H13: 23/01/1982 | I13: Ahmedabad | J13: West | K13: Home Appliances | L13: Mixer | M13: 10 | N13: 3500 | O13: 0.05 | P13: 33250 | Q13: 5 | R13: Card | S13: Aisha | T13: kavya.nair@company.com | U13: 9123535241 | V13: Cancelled | AQ13: 45872
A14: ORD10013 | B14: C002 | C14: P202 | D14: 45667 | E14: 15/01/2025 | F14: Priya Patel | G14: Female | H14: 06/07/1992 | I14: Pune | J14: West | K14: Home Appliances | L14: Iron | M14: 15 | N14: 2200 | O14: 0.1 | P14: 29700 | Q14: 1 | R14: UPI | S14: Neha | T14: priya.patel@company.com | U14: 9367316892 | V14: Pending | AQ14: 45931
A15: ORD10014 | B15: C003 | C15: P202 | D15: 45725 | E15: 13/03/2025 | F15: Rohit Singh | G15: Male | H15: 19/03/2002 | I15: Mumbai | J15: West | K15: Home Appliances | L15: Iron | M15: 17 | N15: 2200 | O15: 0.05 | P15: 35530 | Q15: 1 | R15: Cash | S15: Karan | T15: rohit.singh@company.com | U15: 9778489803 | V15: Completed | AQ15: 45903
A16: ORD10015 | B16: C008 | C16: P201 | D16: 45864 | E16: 07/08/2025 | F16: Kavya Nair | G16: Female | H16: 17/01/2001 | I16: Mumbai | J16: West | K16: Home Appliances | L16: Mixer | M16: 15 | N16: 3500 | O16: 0.15 | P16: 44625 | Q16: 2 | R16: Cash | S16: Neha | T16: kavya.nair@company.com | U16: 9582960180 | V16: Cancelled | AQ16: 45864
A17: ORD10016 | B17: C010 | C17: P103 | D17: 46120 | E17: 11/04/2026 | F17: Pooja Shah | G17: Female | H17: 11/04/2002 | I17: Hyderabad | J17: South | K17: Electronics | L17: Keyboard | M17: 3 | N17: 1200 | O17: 0.05 | P17: 3420 | Q17: 5 | R17: UPI | S17: Ritika | T17: pooja.shahcompany.com | U17: 9611394005 | V17: Completed | AQ17: 46238
A18: ORD10017 | B18: C004 | C18: P203 | D18: 46075 | E18: 03/03/2026 | F18: Amit Sharma | G18: Female | H18: 16/01/2002 | I18: Pune | J18: West | K18: Home Appliances | L18: Microwave | M18: 13 | N18: 8500 | O18: 0.2 | P18: 88400 | Q18: 4 | R18: Card | S18: Rahul | T18: anita.gupta@company.com | U18: 9692599404 | V18: Pending | AQ18: 46075
A19: ORD10018 | B19: C007 | C19: P203 | D19: 46081 | E19: 05/03/2026 | F19: Arjun Rao | G19: Male | H19: 09/10/1989 | I19: Ahmedabad | J19: West | K19: Home Appliances | L19: Microwave | M19: 4 | N19: 8500 | O19: 0.2 | P19: 27200 | Q19: 5 | R19: Card | S19: Aisha | T19: arjun.rao@company.com | U19: 9426119622 | V19: Pending | AQ19: 46081
A20: ORD10019 | B20: C007 | C20: P102 | D20: 45992 | E20: 04/12/2025 | F20: Arjun Rao | G20: Male | H20: 28/10/1991 | I20: Mumbai | J20: West | K20: Electronics | L20: Mouse | M20: 9 | N20: 700 | O20: 0.05 | P20: 5985 | Q20: 3 | R20: UPI | S20: Ritika | T20: arjun.rao@company.com | U20: 9184436009 | V20: Pending | AQ20: 45669
... A36: ORD10035 | B36: C003 | C36: P303 | D36: 45939 | E36: 19/10/2025 | F36: Rohit Singh | G36: Male | H36: 22/04/1996 | I36: Pune | J36: West | K36: Stationery | L36: Marker | M36: 18 | N36: 45 | O36: 0.2 | P36: 648 | Q36: 4 | R36: NetBanking | S36: Ritika | T36: rohit.singh@company.com | U36: 9762437243 | V36: Cancelled | AQ36: 45910
A37: ORD10036 | B37: C003 | C37: P103 | D37: 45980 | E37: 26/11/2025 | F37: Rohit Singh | G37: Male | H37: 07/07/1979 | I37: Bengaluru | J37: South | K37: Electronics | L37: Keyboard | M37: 4 | N37: 1200 | O37: 0.2 | P37: 3840P14 | Q37: 3 | R37: NetBanking | S37: Aisha | T37: rohit.singh@company.com | U37: 9149046970 | V37: Completed | AQ37: 45980
A38: ORD10037 | B38: C009 | C38: P101 | D38: 45966 | E38: 14/11/2025 | F38: Mohit Verma | G38: Male | H38: 27/09/1980 | I38: Kolkata | J38: East | K38: Electronics | L38: Laptop | M38: 10 | N38: 55000 | O38: 0 | P38: 550000 | Q38: 1 | R38: UPI | S38: Rahul | T38: mohit.verma@company.com | U38: 9869182901 | V38: Cancelled | AQ38: 45788
A39: ORD10038 | B39: C006 | C39: P201 | D39: 46089 | E39: 20/03/2026 | F39: Sneha Joshi | G39: Female | H39: 21/06/1980 | I39: Delhi | J39: North | K39: Home Appliances | L39: Mixer | M39: 20 | N39: 3500 | O39: 0.1 | P39: 63000 | Q39: 3 | R39: Card | S39: Rahul | T39: sneha.joshi@company.com | U39: 9283578533 | V39: Cancelled | AQ39: 46237
A40: ORD10039 | B40: C008 | C40: P302 | D40: 45701 | E40: 19/02/2025 | F40: Kavya Nair | G40: Female | H40: 17/06/1979 | I40: Pune | J40: West | K40: Stationery | L40: Pen | M40: 5 | N40: 1200 | O40: 0 | P40: 100 | Q40: 1 | R40: Cash | S40: Rahul | T40: kavya.nair@company.com | U40: 9963005771 | V40: Cancelled | AQ40: 45701
A41: ORD10040 | B41: C010 | C41: P203 | D41: 45935 | E41: 15/10/2025 | F41: Pooja Shah | G41: Female | H41: 18/06/1992 | I41: Mumbai | J41: West | K41: Home Appliances | L41: Microwave | M41: 20 | N41: 8500 | O41: 0 | P41: 170000 | Q41: 1 | R41: UPI | S41: Neha | T41: pooja.shah@company.com | U41: 9484632635 | V41: Cancelled | AQ41: 45787
A42: ORD10041 | B42: C007 | C42: P301 | D42: 46063 | E42: 12/02/2026 | F42: Arjun Rao | G42: Male | H42: 06/06/1994 | I42: Bengaluru | J42: South | K42: Stationery | L42: Notebook | M42: 8 | N42: 60 | O42: 0.15 | P42: 408 | Q42: 5 | R42: UPI | S42: Rahul | T42: arjun.rao@company.com | U42: 9276319484 | V42: Pending | AQ42: 46297
A43: ORD10042 | B43: C010 | C43: P201 | D43: 45812 | E43: 16/06/2025 | F43: Pooja Shah | G43: Female | H43: 22/09/1988 | I43: Pune | J43: West | K43: Home Appliances | L43: Mixer | M43: 8 | N43: 3500 | O43: 0.05 | P43: 26600 | Q43: 1 | R43: Card | S43: Neha | T43: pooja.shah@company.com | U43: 9619034852 | V43: Pending | AQ43: 45753
A44: ORD10043 | B44: C009 | C44: P203 | D44: 46061 | E44: 14/02/2026 | F44: Mohit Verma | G44: Male | H44: 14/07/2001 | I44: Jaipur | J44: North | K44: Home Appliances | L44: Microwave | M44: 1 | N44: 8500 | O44: 0 | P44: 8500 | Q44: 2 | R44: Card | S44: Neha | T44: mohit.verma@company.com | U44: 9636416962 | V44: Pending | AQ44: 46236
A45: ORD10044 | B45: C001 | C45: P303 | D45: 45746 | E45: 31/03/2025 | F45: Amit Sharma | G45: Male | H45: 09/08/1991 | I45: Pune | J45: West | K45: Stationery | L45: Marker | M45: 8 | N45: 45 | O45: 0.15 | P45: 306 | Q45: 2 | R45: Card | S45: Aisha | T45: amit.sharma@company.com | U45: 9357133880 | V45: Completed | AQ45: 45746
A46: ORD10045 | B46: C006 | C46: P202 | D46: 45772 | E46: 28/04/2025 | F46: Sneha Joshi | G46: Female | H46: 21/10/1988 | I46: Pune | J46: West | K46: Home Appliances | L46: Iron | M46: 16 | N46: 2200 | O46: 0.05 | P46: 33440 | Q46: 5 | R46: Card | S46: Aisha | T46: sneha.joshi@company.com | U46: 9575210324 | V46: Cancelled | AQ46: 45772
A47: ORD10046 | B47: C009 | C47: P201 | D47: 45943 | E47: 23/10/2025 | F47: Mohit Verma | G47: Male | H47: 19/11/2002 | I47: Bengaluru | J47: South | K47: Home Appliances | L47: Mixer | M47: 19 | N47: 3500 | O47: 0.2 | P47: 53200 | Q47: 3 | R47: Cash | S47: Karan | T47: mohit.verma@company.com | U47: 9276080204 | V47: Cancelled | AQ47: 45943
A48: ORD10047 | B48: C006 | C48: P102 | D48: 45941 | E48: 14/10/2025 | F48: Sneha Joshi | G48: Female | H48: 06/07/2000 | I48: Pune | J48: West | K48: Electronics | L48: Mouse | M48: 15 | N48: 700 | O48: 0.15 | P48: 8925 | Q48: 4 | R48: UPI | S48: Neha | T48: sneha.joshicompany.com | U48: 9856624471 | V48: Completed | AQ48: 45971
A49: ORD10048 | B49: C006 | C49: P102 | D49: 45988 | E49: 03/12/2025 | F49: Sneha Joshi | G49: Female | H49: 26/11/1998 | I49: Jaipur | J49: North | K49: Electronics | L49: Mouse | M49: 19 | N49: 700 | O49: 0.2 | P49: 10640 | Q49: 1 | R49: Cash | S49: Neha | T49: sneha.joshi@company.com | U49: 9238141322 | V49: Completed | AQ49: 45988
A50: ORD10049 | B50: C009 | C50: P104 | D50: 46131 | F50: Mohit Verma | G50: Male | H50: 03/06/1996 | I50: Delhi | J50: North | K50: Electronics | L50: Monitor | M50: 19 | N50: 12000 | O50: 0 | P50: 228000 | Q50: 1 | R50: NetBanking | S50: Aisha | T50: mohit.verma@company.com | U50: 9890380030 | V50: Completed | AQ50: 46131
A51: ORD10050 | B51: C004 | C51: P103 | D51: 46131 | E51: 21/04/2026 | F51: Anita Gupta | G51: Female | H51: 15/03/1987 | I51: Pune | J51: West | K51: Electronics | L51: Keyboard | M51: 6 | N51: 1200 | O51: 0.05 | P51: 6840 | Q51: 2 | R51: Cash | S51: Ritika | T51: anita.gupta@company.com | U51: 9495893170 | V51: Pending | AQ51: 46131
A52: ORD10051 | B52: C010 | C52: P202 | D52: 45744 | E52: 07/04/2025 | F52: Pooja Shah | G52: Female | H52: 20/02/1979 | I52: Bengaluru | J52: South | K52: Home Appliances | L52: Iron | M52: 7 | N52: 2200 | O52: 0.15 | P52: 13090 | Q52: 1 | R52: UPI | S52: Aisha | T52: pooja.shah@company.com | U52: 9485166307 | V52: Completed | AQ52: 45744
A53: ORD10052 | B53: C002 | C53: P301 | D53: 45894 | E53: 28/08/2025 | F53: Priya Patel | G53: Female | H53: 09/08/2000 | I53: Jaipur | J53: North | K53: Stationery | L53: Notebook | M53: 8 | N53: 60 | O53: 0.1 | P53: 432 | Q53: 5 | R53: Card | S53: Aisha | T53: priya.patel@company.com | U53: 9924709648 | V53: Cancelled | AQ53: 45894
A54: ORD10053 | B54: C005 | C54: P101 | D54: 45888 | E54: 23/08/2025 | F54: Vikas Mehta | G54: Male | H54: 17/01/1976 | I54: Kolkata | J54: East | K54: Electronics | L54: Laptop | M54: 12 | N54: 55000 | O54: 0.05 | P54: 627000 | Q54: 2 | R54: UPI | S54: Rahul | T54: vikas.mehta@company.com | U54: 9350554626 | V54: Pending | AQ54: 45888
A55: ORD10054 | B55: C008 | C55: P102 | D55: 45865 | E55: 05/08/2025 | F55: Kavya Nair | G55: Female | H55: 04/04/1975 | I55: Jaipur | J55: North | K55: Electronics | L55: Mouse | M55: 3 | N55: 700 | O55: 0 | P55: 2100 | Q55: 3 | R55: Card | S55: Karan | T55: kavya.nair@company.com | U55: 9743295580 | V55: Cancelled | AQ55: 45865
A56: ORD10055 | B56: C003 | C56: P301 | D56: 45709 | E56: 26/02/2025 | F56: Rohit Singh | G56: Male | H56: 11/12/1976 | I56: Ahmedabad | J56: West | K56: Stationery | L56: Notebook | M56: 19 | N56: 60 | O56: 0.15 | P56: 969 | Q56: 4 | R56: Card | S56: Rahul | T56: rohit.singh@company.com | U56: 9822926495 | V56: Cancelled | AQ56: 45709
A57: ORD10056 | B57: C001 | C57: P301 | D57: 45879 | E57: 11/08/2025 | F57: Amit Sharma | G57: Male | H57: 03/12/1979 | I57: Jaipur | J57: North | K57: Stationery | L57: Notebook | M57: 9 | N57: 60 | O57: 0.2 | P57: 432 | Q57: 1 | R57: NetBanking | S57: Neha | T57: amit.sharma@company.com | U57: 9518298190 | V57: Pending | AQ57: 45938
A58: ORD10057 | B58: C001 | C58: P102 | D58: 46105 | E58: 30/03/2026 | F58: Amit Sharma | G58: Male | H58: 27/12/1978 | I58: Bengaluru | J58: South | K58: Electronics | L58: Mouse | M58: 6 | N58: 700 | O58: 0 | P58: 4200 | Q58: 4 | R58: UPI | S58: Rahul | T58: amit.sharmcompany.com | U58: 9366223547 | V58: Cancelled | AQ58: 46105
A59: ORD10058 | B59: C003 | C59: P303 | D59: 46094 | E59: 19/03/2026 | F59: Rohit Singh | G59: Male | H59: 15/04/1975 | I59: Delhi | J59: North | K59: Stationery | L59: Marker | M59: 18 | N59: 45 | O59: 0.05 | P59: 769.5 | Q59: 1 | R59: Card | S59: Aisha | T59: rohit.singh@company.com | U59: 9701988524 | V59: Pending | AQ59: 46094
A60: ORD10059 | B60: C007 | C60: P302 | D60: 45823 | E60: 26/06/2025 | F60: Arjun Rao | G60: Male | H60: 19/12/1988 | I60: Jaipur | J60: North | K60: Stationery | L60: Pen | M60: 8 | N60: 20 | O60: 0.05 | P60: 152 | Q60: 1 | R60: Card | S60: Ritika | T60: arjun.rao@company.com | U60: 9836327649 | V60: completed | AQ60: 45823
A61: ORD10060 | B61: C005 | C61: P102 | D61: 45721 | E61: 06/03/2025 | F61: Vikas Mehta | G61: Male | H61: 07/03/1979 | I61: Jaipur | J61: North | K61: Electronics | L61: Mouse | M61: 8 | N61: 700 | O61: 0.1 | P61: 5040 | Q61: 1 | R61: NetBanking | S61: Aisha | T61: vikas.mehta@company.com | U61: 9261800516 | V61: Cancelled | AQ61: 45780
A62: ORD10061 | B62: C008 | C62: P302 | D62: 46121 | E62: 19/04/2026 | F62: Kavya Nair | G62: Female | H62: 17/12/2003 | I62: Delhi | J62: North | K62: Stationery | L62: Pen | M62: 7 | N62: 20 | O62: 0.15 | P62: 119 | Q62: 5 | R62: Card | S62: Rahul | T62: kavya.nair@company.com | U62: 9950802015 | V62: Completed | AQ62: 46269
... A74: ORD10073 | B74: C008 | C74: P103 | D74: 46004 | E74: 23/12/2025 | F74: Kavya Nair | G74: Female | H74: 22/09/1981 | I74: Jaipur | J74: North | K74: Electronics | L74: Keyboard | M74: 1 | N74: 1200 | O74: 0.05 | P74: 1140 | Q74: 3 | R74: UPI | S74: Aisha | T74: kavya.nair@company.com | U74: 9808988530 | V74: Cancelled | AQ74: 46004
A75: ORD10074 | B75: C010 | C75: P202 | D75: 46057 | E75: 16/02/2026 | F75: Pooja Shah | G75: Female | H75: 20/06/1980 | J75: South | K75: Home Appliances | L75: Iron | M75: 1 | N75: 2200 | O75: 0.15 | P75: 1870 | Q75: 4 | R75: Card | S75: Aisha | T75: pooja.shah@company.com | U75: 9286410494 | V75: Completed | AQ75: 46114
A76: ORD10075 | B76: C003 | C76: P103 | D76: 46048 | E76: 28/01/2026 | F76: Rohit Singh | G76: Male | H76: 02/11/1982 | I76: Pune | J76: West | K76: Electronics | L76: Keyboard | M76: 3 | N76: 1200 | O76: 0.1 | P76: 3240 | Q76: 5 | R76: Cash | S76: Rahul | T76: rohit.singh@company.com | U76: 9311555196 | V76: Completed | AQ76: 46048
A77: ORD10076 | B77: C008 | C77: P201 | D77: 45835 | E77: 07/07/2025 | F77: Kavya Nair | G77: Female | H77: 10/01/1980 | I77: Bengaluru | J77: South | K77: Home Appliances | L77: Mixer | M77: 10 | N77: 3500 | O77: 0.2 | P77: 28000 | Q77: 5 | R77: Card | S77: Ritika | T77: kavya.nair@company.com | U77: 9101810266 | V77: Completed | AQ77: 45835
A78: ORD10077 | B78: C007 | C78: P102 | D78: 46098 | E78: 19/03/2026 | F78: Arjun Rao | G78: Male | H78: 27/04/1981 | I78: Delhi | J78: North | K78: Electronics | L78: Mouse | M78: 18 | N78: 700 | O78: 0.05 | P78: 11970 | Q78: 3 | R78: Card | S78: Neha | T78: arjun.rao@company.com | U78: 9464556593 | V78: Cancelled | AQ78: 46098
A79: ORD10078 | B79: C005 | C79: P102 | D79: 45817 | E79: 18/06/2025 | F79: Vikas Mehta | G79: Male | H79: 12/03/1985 | I79: Bengaluru | J79: South | K79: Electronics | L79: Mouse | M79: 12 | N79: 700 | O79: 0.15 | P79: 7140 | Q79: 2 | R79: UPI | S79: Rahul | T79: vikas.mehta@company.com | U79: 9338278358 | V79: Completed | AQ79: 45906
A80: ORD10079 | B80: C009 | C80: P103 | D80: 45976 | E80: 16/11/2025 | F80: Mohit Verma | G80: Male | H80: 15/03/1999 | I80: Mumbai | J80: West | K80: Electronics | L80: Keyboard | M80: 8 | N80: 1200 | O80: 0 | P80: 9600 | Q80: 4 | R80: Card | S80: Rahul | T80: mohit.verma@company.com | U80: 9621410770 | V80: Pending | AQ80: 45976
A81: ORD10080 | B81: C003 | C81: P301 | D81: 45967 | E81: 10/11/2025 | F81: Rohit Singh | G81: Male | H81: 07/07/1983 | I81: Pune | J81: West | K81: Stationery | L81: Notebook | M81: 2 | N81: 60 | O81: 0 | P81: 120 | Q81: 2 | R81: UPI | S81: Rahul | T81: rohit.singh@company.com | U81: 9981333189 | V81: Completed | AQ81: 45819
A82: ORD10081 | B82: C001 | C82: P303 | D82: 45658 | E82: 07/01/2025 | F82: Amit Sharma | G82: Male | H82: 06/03/1989 | I82: Pune | J82: West | K82: Stationery | L82: Marker | M82: 10 | N82: 45 | O82: 0.15 | P82: 382.5 | Q82: 3 | R82: NetBanking | S82: Ritika | T82: amit.sharma@company.com | U82: 9723450355 | V82: Cancelled | AQ82: 45658
A83: ORD10082 | B83: C005 | C83: P201 | D83: 46137 | E83: 03/05/2026 | F83: Vikas Mehta | G83: Male | H83: 20/06/1982 | I83: Kolkata | J83: East | K83: Home Appliances | L83: Mixer | M83: 12 | N83: 3500 | O83: 0.05 | P83: 39900 | Q83: 3 | R83: NetBanking | S83: Aisha | T83: vikas.mehta@company.com | U83: 9886243907 | V83: Pending | AQ83: 46137
A84: ORD10083 | B84: C003 | C84: P301 | D84: 45919 | E84: 27/09/2025 | F84: Rohit Singh | G84: Male | H84: 23/06/2001 | I84: Mumbai | J84: West | K84: Stationery | L84: Notebook | M84: 2 | N84: 60 | O84: 0.15 | P84: 102 | Q84: 1 | R84: UPI | S84: Neha | T84: rohit.singh@company.com | U84: 9473931904 | V84: Completed | AQ84: 45919
A85: ORD10084 | B85: C003 | C85: P103 | D85: 45734 | E85: 21/03/2025 | F85: Rohit Singh | G85: Male | H85: 19/07/1983 | I85: Hyderabad | J85: South | K85: Electronics | L85: Keyboard | M85: 18 | N85: 1200 | O85: 0.15 | P85: 18360 | Q85: 3 | R85: Card | S85: Neha | T85: rohit.singh@company.com | U85: 9287159610 | V85: Pending | AQ85: 45734
A86: ORD10085 | B86: C008 | C86: P104 | D86: 45960 | E86: 31/10/2025 | F86: Kavya Nair | G86: Female | H86: 24/03/1993 | I86: Mumbai | J86: West | K86: Electronics | L86: Monitor | M86: 18 | N86: 12000 | O86: 0.15 | P86: 183600 | Q86: 2 | R86: Cash | S86: Rahul | T86: kavya.nair@company.com | U86: 9876513858 | V86: Completed | AQ86: 45960
A87: ORD10086 | B87: C007 | C87: P302 | D87: 45961 | E87: 11/11/2025 | F87: Arjun Rao | G87: Male | H87: 10/05/1995 | I87: Ahmedabad | J87: West | K87: Stationery | L87: Pen | M87: 7 | N87: 20 | O87: 0 | P87: 140 | Q87: 2 | R87: Card | S87: Ritika | T87: arjun.rao@company.com | U87: 9237400853 | V87: Cancelled | AQ87: 45961
... A119: ORD10118 | B119: C001 | C119: P303 | D119: 45808 | E119: 11/06/2025 | F119: Amit Sharma | G119: Male | H119: 07/09/1995 | I119: Pune | J119: West | K119: Stationery | L119: Marker | M119: 16 | N119: 45 | O119: 0 | P119: 720 | Q119: 1 | R119: NetBanking | S119: Aisha | T119: amit.sharma@company.com | U119: 9807154421 | V119: Completed | AQ119: 45808
A120: ORD10119 | B120: C009 | C120: P103 | D120: 45807 | E120: 02/06/2025 | F120: Mohit Verma | G120: Male | H120: 08/03/1988 | I120: Ahmedabad | J120: West | K120: Electronics | L120: Keyboard | N120: 1200 | O120: 0.15 | P120: 7140 | Q120: 4 | R120: UPI | S120: Karan | T120: mohit.verma@company.com | U120: 9919834000 | V120: Pending | AQ120: 45807
A121: ORD10120 | B121: C002 | C121: P104 | D121: 45888 | E121: 30/08/2025 | F121: Priya Patel | G121: Female | H121: 07/07/1989 | I121: Jaipur | J121: North | K121: Electronics | L121: Monitor | M121: 14 | N121: 12000 | O121: 0.15 | P121: 142800 | Q121: 2 | R121: NetBanking | S121: Aisha | T121: priya.patel@company.com | U121: 9739798818 | V121: Pending | AQ121: 45888
A122: ORD10121 | B122: C003 | C122: P203 | D122: 46005 | E122: 16/12/2025 | F122: Rohit Singh | G122: Male | H122: 11/11/1993 | I122: Pune | J122: West | K122: Home Appliances | L122: Microwave | M122: 8 | N122: 8500 | O122: 0.2 | P122: 54400 | Q122: 3 | R122: Card | S122: Rahul | T122: rohit.singh@company.com | U122: 9208625306 | V122: Completed | AQ122: 46005
A123: ORD10122 | B123: C007 | C123: P303 | D123: 46053 | E123: 10/02/2026 | F123: Arjun Rao | G123: Male | H123: 01/02/2000 | I123: Bengaluru | J123: South | K123: Stationery | L123: Marker | M123: 3 | N123: 45 | O123: 0 | P123: 135 | Q123: 4 | R123: UPI | S123: Aisha | T123: arjun.rao@company.com | U123: 9970178536 | V123: Cancelled | AQ123: 46053
A124: ORD10123 | B124: C001 | C124: P102 | D124: 46025 | E124: 04/01/2026 | F124: Amit Sharma | G124: Male | H124: 22/06/1986 | I124: Jaipur | J124: North | K124: Electronics | L124: Mouse | M124: 13 | N124: 700 | O124: 0.05 | P124: 8645 | Q124: 3 | R124: Card | S124: Neha | T124: amit.sharma@company.com | U124: 9633745195 | V124: Pending | AQ124: 46082
A125: ORD10124 | B125: C004 | C125: P103 | D125: 45950 | E125: 26/10/2025 | F125: Anita Gupta | G125: Female | H125: 16/02/1986 | I125: Mumbai | J125: West | K125: Electronics | L125: Keyboard | M125: 14 | N125: 1200 | O125: 0.2 | P125: 13440 | Q125: 5 | R125: NetBanking | S125: Aisha | T125: anita.gupta@company.com | U125: 9922102053 | V125: Completed | AQ125: 45950
A126: ORD10125 | B126: C002 | C126: P303 | D126: 45788 | E126: 21/05/2025 | F126: Priya Patel | G126: Female | H126: 18/09/1991 | I126: Delhi | J126: North | K126: Stationery | L126: Marker | M126: 2 | N126: 45 | O126: 0.05 | P126: 85.5 | Q126: 3 | R126: UPI | S126: Ritika | T126: priya.patel@company.com | U126: 9135963930 | V126: Cancelled | AQ126: 45966
A127: ORD10126 | B127: C004 | C127: P103 | D127: 46024 | E127: 06/01/2026 | F127: Anita Gupta | G127: Female | H127: 04/01/1981 | I127: Bengaluru | J127: South | K127: Electronics | L127: Keyboard | M127: 2 | N127: 1200 | O127: 0.2 | P127: 1920 | Q127: 3 | R127: Card | S127: Neha | T127: anita.gupta@company.com | U127: 9429405275 | V127: Completed | AQ127: 46054
A128: ORD10127 | B128: C003 | C128: P101 | D128: 46132 | E128: 26/04/2026 | F128: Rohit Singh | G128: Male | H128: 12/10/2004 | I128: Bengaluru | J128: South | K128: Electronics | L128: Laptop | M128: 10 | N128: 55000 | O128: 0.05 | P128: 522500 | Q128: 5 | R128: UPI | S128: Aisha | T128: rohit.singh@company.com | U128: 9521757571 | V128: Pending | AQ128: 46132
A129: ORD10128 | B129: C006 | C129: P201 | D129: 45873 | E129: 05/08/2025 | F129: Sneha Joshi | G129: Female | H129: 25/03/1984 | I129: Jaipur | J129: North | K129: Home Appliances | L129: Mixer | M129: 15 | N129: 3500 | O129: 0.1 | P129: 47250 | Q129: 3 | R129: NetBanking | S129: Neha | T129: sneha.joshi@company.com | U129: 9467375455 | V129: Completed | AQ129: 45755
A130: ORD10129 | B130: C002 | C130: P202 | D130: 45882 | E130: 18/08/2025 | F130: Priya Patel | G130: Female | H130: 09/09/1982 | I130: Bengaluru | J130: South | K130: Home Appliances | L130: Iron | M130: 10 | N130: 2200 | O130: 0.15 | P130: 18700 | Q130: 4 | R130: Card | S130: Rahul | T130: priya.patel@company.com | U130: 9838809695 | V130: Pending | AQ130: 45882
A131: ORD10130 | B131: C006 | C131: P201 | D131: 45824 | E131: 24/06/2025 | F131: Sneha Joshi | G131: Female | H131: 15/02/1993 | I131: Pune | J131: West | K131: Home Appliances | L131: Mixer | M131: 11 | N131: 3500 | O131: 0.05 | P131: 36575 | Q131: 5 | R131: Cash | S131: Ritika | T131: sneha.joshi@company.com | U131: 9296609782 | V131: Cancelled | AQ131: 45824
A132: ORD10131 | B132: C004 | C132: P103 | D132: 46139 | E132: 30/04/2026 | F132: Anita Gupta | G132: Female | H132: 08/04/2003 | I132: Bengaluru | J132: South | K132: Electronics | L132: Keyboard | M132: 14 | N132: 1200 | O132: 0 | P132: 16800 | Q132: 5 | R132: Cash | S132: Rahul | T132: anita.gupta@company.com | U132: 9848259992 | V132: Cancelled | AQ132: 46139
... A357: ORD10356 | B357: C008 | C357: P303 | D357: 45941 | E357: 21/10/2025 | F357: Kavya Nair | G357: Female | H357: 22/05/1992 | I357: Jaipur | J357: North | K357: Stationery | L357: Marker | M357: 5 | N357: 45 | O357: 0.05 | P357: 213.75 | Q357: 1 | R357: Card | S357: Neha | T357: kavya.nair@company.com | U357: 9810433484 | V357: Completed | AQ357: 45971
A358: ORD10357 | B358: C006 | C358: P102 | D358: Pending | E358: 11/02/2025 | F358: Sneha Joshi | G358: Female | H358: 10/11/1989 | I358: Mumbai | J358: West | K358: Electronics | L358: Mouse | M358: 3 | N358: 700 | O358: 0.15 | P358: 1785 | Q358: 4 | R358: Cash | S358: Karan | T358: sneha.joshi@company.com | U358: 9990243436 | V358: Completed | AQ358: 45658
A359: ORD10358 | B359: C009 | C359: P203 | D359: 46005 | E359: 26/12/2025 | F359: Mohit Verma | G359: Male | H359: 03/09/1980 | I359: Jaipur | J359: North | K359: Home Appliances | L359: Microwave | M359: 12 | N359: 8500 | O359: 0.05 | P359: 96900 | Q359: 3 | R359: Card | S359: Aisha | T359: mohit.verma@company.com | U359: 9396678031 | V359: Pending | AQ359: 46005
A360: ORD10359 | B360: C006 | C360: P203 | D360: 46123 | E360: 19/04/2026 | F360: Sneha Joshi | G360: Female | H360: 06/03/1979 | I360: Pune | J360: West | K360: Home Appliances | L360: Microwave | M360: 4 | N360: 8500 | O360: 0.15 | P360: 28900 | Q360: 4 | R360: NetBanking | S360: Aisha | T360: sneha.joshi@company.com | U360: 9818591245 | V360: Pending | AQ360: 46330
A361: ORD10360 | B361: C003 | C361: P302 | D361: 45766 | E361: 22/04/2025 | F361: Rohit Singh | G361: Male | H361: 04/09/1996 | I361: Jaipur | J361: North | K361: Stationery | L361: Pen | M361: 16 | N361: 20 | O361: 0.1 | P361: 288 | Q361: 4 | R361: Cash | S361: Neha | T361: rohit.singh@company.com | U361: 9505550047 | V361: Cancelled | AQ361: 45766
A362: ORD10361 | B362: C003 | C362: P301 | D362: 46152 | E362: 18/05/2026 | F362: Rohit Singh | G362: Male | H362: 14/03/1999 | I362: Mumbai | J362: West | K362: Stationery | L362: Notebook | M362: 3 | N362: 60 | O362: 0.2 | P362: 144 | Q362: 4 | R362: UPI | S362: Karan | T362: rohit.singh@company.com | U362: 9469828772 | V362: Pending | AQ362: 46300
A363: ORD10362 | B363: C009 | C363: P202 | D363: 45858 | E363: 26/07/2025 | F363: Mohit Verma | G363: Male | H363: 03/10/1984 | I363: Mumbai | J363: West | K363: Home Appliances | L363: Iron | M363: 19 | N363: 2200 | O363: 0.1 | P363: 37620 | Q363: 2 | R363: Cash | S363: Karan | T363: mohit.verma@company.com | U363: 9885092680 | V363: Pending | AQ363: 45858
A364: ORD10363 | B364: C009 | C364: P103 | D364: 46045 | E364: 27/01/2026 | F364: Mohit Verma | G364: Male | H364: 09/07/1984 | I364: Hyderabad | J364: South | K364: Electronics | L364: Keyboard | M364: 7 | N364: 1200 | O364: 0.2 | P364: 6720 | Q364: 3 | R364: Card | S364: Neha | T364: mohit.verma@company.com | U364: 9362319457 | V364: Cancelled | AQ364: 46045
A365: ORD10364 | B365: C010 | C365: P302 | D365: 46097 | E365: 21/03/2026 | F365: Pooja Shah | G365: Female | H365: 10/03/1989 | I365: Bengaluru | J365: South | K365: Stationery | L365: Pen | M365: 20 | N365: 20 | O365: 0.2 | P365: 320 | Q365: 5 | R365: Card | S365: Neha | T365: pooja.shah@company.com | U365: 9223945130 | V365: Pending | AQ365: 46097
A366: ORD10365 | B366: C002 | C366: P103 | D366: 45777 | E366: 07/05/2025 | F366: Priya Patel | G366: Female | H366: 19/04/1985 | I366: Hyderabad | J366: South | K366: Electronics | L366: Keyboard | M366: 19 | N366: 1200 | O366: 0.05 | P366: 21660 | Q366: 3 | R366: Card | S366: Ritika | T366: priya.patel@company.com | U366: 9910804926 | V366: Pending | AQ366: 45777
A367: ORD10366 | B367: C010 | C367: P302 | D367: 45691 | E367: 13/02/2025 | F367: Pooja Shah | G367: Female | H367: 13/08/2003 | I367: Hyderabad | J367: South | K367: Stationery | L367: Pen | M367: 5 | N367: 20 | O367: 0 | P367: 100 | Q367: 2 | R367: UPI | S367: Rahul | T367: pooja.shah@company.com | U367: 9274269744 | V367: Pending | AQ367: 45718
A368: ORD10367 | B368: C002 | C368: P303 | D368: 46088 | E368: 16/03/2026 | F368: Priya Patel | G368: Female | H368: 11/09/1983 | I368: Jaipur | J368: North | K368: Stationery | L368: Marker | M368: 16 | N368: 45 | O368: 0.15 | P368: 612 | Q368: 5 | R368: Cash | S368: Aisha | T368: priya.patel@company.com | U368: 9223196101 | V368: Cancelled | AQ368: 46206
A369: ORD10368 | B369: C008 | C369: P202 | D369: 45780 | E369: 15/05/2025 | F369: Kavya Nair | G369: Female | H369: 11/06/1976 | I369: Jaipur | J369: North | K369: Home Appliances | L369: Iron | M369: 1 | N369: 2200 | O369: 0.1 | P369: 1980 | Q369: 5 | R369: Card | S369: Rahul | T369: kavya.nair@company.com | U369: 9888477457 | V369: Completed | AQ369: 45721
A370: ORD10369 | B370: C010 | C370: P301 | D370: 46113 | E370: 05/04/2026 | F370: Pooja Shah | G370: Female | H370: 04/01/1987 | I370: Hyderabad | J370: South | K370: Stationery | L370: Notebook | M370: 19 | N370: 60 | O370: 0.15 | P370: 969 | Q370: 4 | R370: NetBanking | S370: Neha | T370: pooja.shah@company.com | U370: 9435947486 | V370: Cancelled | AQ370: 46026
A371: ORD10370 | B371: C001 | C371: P101 | D371: Pending | E371: 02/02/2025 | F371: Amit Sharma | G371: Male | H371: 14/05/1992 | I371: Delhi | J371: North | K371: Electronics | L371: Laptop | M371: 15 | N371: 55000 | O371: 0 | P371: 825000 | Q371: 5 | R371: Card | S371: Neha | T371: amit.sharma@company.com | U371: 9411668831 | V371: Cancelled | AQ371: 45658
A372: ORD10371 | B372: C009 | C372: P303 | D372: 45936 | E372: 08/10/2025 | F372: Mohit Verma | G372: Male | H372: 03/05/1989 | I372: Bengaluru | J372: South | K372: Stationery | L372: Marker | M372: 11 | N372: 45 | O372: 0.05 | P372: 470.25 | Q372: 5 | R372: NetBanking | S372: Karan | T372: mohit.verma@company.com | U372: 9523682403 | V372: Completed | AQ372: 45818
A373: ORD10372 | B373: C006 | C373: P302 | D373: 45820 | E373: 17/06/2025 | F373: Sneha Joshi | G373: Female | H373: 19/12/1990 | I373: Jaipur | J373: North | K373: Stationery | L373: Pen | M373: 9 | N373: 20 | O373: 0.1 | P373: 162 | Q373: 1 | R373: Card | S373: Rahul | T373: sneha.joshi@company.com | U373: 9652936744 | V373: Cancelled | AQ373: 45997
A374: ORD10373 | B374: C004 | C374: P303 | D374: 45979 | E374: 20/11/2025 | F374: Anita Gupta | G374: Female | H374: 09/07/1995 | I374: Bengaluru | J374: South | K374: Stationery | L374: Marker | M374: 5 | N374: 45 | O374: 0.05 | P374: 213.75 | Q374: 3 | R374: Card | S374: Neha | T374: anita.gupta@company.com | U374: 9726464733 | V374: Pending | AQ374: 45979
A375: ORD10374 | B375: C007 | C375: P102 | D375: 45962 | E375: 02/11/2025 | F375: Arjun Rao | G375: Male | H375: 23/12/1998 | I375: Hyderabad | J375: South | K375: Electronics | L375: Mouse | M375: 5 | N375: 700 | O375: 0.1 | P375: 3150 | Q375: 2 | R375: UPI | S375: Rahul | T375: arjun.rao@company.com | U375: 9273520544 | V375: Completed | AQ375: 45668
A376: ORD10375 | B376: C005 | C376: P102 | D376: 45681 | E376: 31/01/2025 | F376: Vikas Mehta | G376: Male | H376: 23/12/1979 | I376: Kolkata | J376: East | K376: Electronics | L376: Mouse | M376: 1 | N376: 700 | O376: 0 | P376: 700 | Q376: 1 | R376: UPI | S376: Karan | T376: vikas.mehta@company.com | U376: 9374259988 | V376: Completed | AQ376: 45681
A377: ORD10376 | B377: C008 | C377: P102 | D377: 46066 | E377: 21/02/2026 | F377: Kavya Nair | G377: Female | H377: 15/12/1975 | I377: Mumbai | J377: West | K377: Electronics | L377: Mouse | M377: 13 | N377: 700 | O377: 0.2 | P377: 7280 | Q377: 2 | R377: Card | S377: Ritika | T377: kavya.nair@company.com | U377: 9538129419 | V377: Completed | AQ377: 46066
A378: ORD10377 | B378: C009 | C378: P104 | D378: 45696 | E378: 19/02/2025 | F378: Mohit Verma | G378: Male | H378: 17/05/1993 | I378: Pune | J378: West | K378: Electronics | L378: Monitor | M378: 20 | N378: 12000 | O378: 0 | P378: 240000 | Q378: 2 | R378: Card | S378: Neha | T378: mohit.verma@company.com | U378: 9382815686 | V378: Completed | AQ378: 45871
A379: ORD10378 | B379: C007 | C379: P103 | D379: 46019 | E379: 06/01/2026 | F379: Arjun Rao | G379: Male | H379: 17/09/1976 | I379: Kolkata | J379: East | K379: Electronics | L379: Keyboard | M379: 9 | N379: 1200 | O379: 0.15 | P379: 9180 | Q379: 1 | R379: UPI | S379: Ritika | T379: arjun.rao@company.com | U379: 9450746157 | V379: Pending | AQ379: 46019
A380: ORD10379 | B380: C007 | C380: P302 | D380: 45931 | E380: 03/10/2025 | F380: Arjun Rao | G380: Male | H380: 22/12/1996 | I380: Jaipur | J380: North | K380: Stationery | L380: Pen | M380: 3 | N380: 20 | O380: 0.15 | P380: 51 | Q380: 3 | R380: Cash | S380: Neha | T380: arjun.rao@company.com | U380: 9349012570 | V380: Pending | AQ380: 45667
A381: ORD10380 | B381: C006 | C381: P101 | D381: 46009 | E381: 19/12/2025 | F381: Sneha Joshi | G381: Female | H381: 25/12/1995 | I381: Delhi | J381: North | K381: Electronics | L381: Laptop | M381: 8 | N381: 55000 | O381: 0.2 | P381: 352000 | Q381: 5 | R381: Card | S381: Karan | T381: sneha.joshi@company.com | U381: 9442163790 | V381: Pending | AQ381: 46009
...

Sheet working Sales Dashboard 
D1: KPI
C3: Sum of Sales | D3: Average of Sales | E3: Count of Order_ID
C4: 34762098 | D4: 69663.522 | E4: 500
C7: Sales By Region | F7: Sales Distribution by Category | J7: Monthly Sales Trend
C9: Row Labels | D9: Sum of Sales | F9: Row Labels | G9: Sum of Sales | J9: Row Labels | K9: Sum of Sales
C10: East | D10: 4041922 | F10: Electronics | G10: 27829619 | J10: 2025 | K10: 26260282
C11: North | D11: 10022852 | F11: Home Appliances | G11: 6816975 | J11: Jan | K11: 3848385
C12: South | D12: 7493791.5 | F12: Stationery | G12: 115503.5 | J12: Feb | K12: 3367633.5
C13: West | D13: 13203532 | F13: Grand Total | G13: 34762098 | J13: Mar | K13: 2087782.2
C14: Grand Total | D14: 34762098 | J14: Apr | K14: 3169953.2
J15: May | K15: 2344972.5
J16: Jun | K16: 1579645.5
J17: Jul | K17: 1332201.5
J18: Aug | K18: 2527097.8
J19: Sep | K19: 1812692.2
J20: Oct | K20: 1600111.8
J21: Nov | K21: 522077
J22: Dec | K22: 2067729.8
J23: 2026 | K23: 8501815.5
J24: Jan | K24: 2288950
J25: Feb | K25: 1010360.2
J26: Mar | K26: 2087134.5
... J36: Grand Total | K36: 34762098

Sheet Sales Dashboard 
